Workbook

Sheet Consumables
A2: Month | B2: Customer | C2: Sales (VAT 포함) | D2: Sales (VAT 제외) | E2: CM | F2: CM % | G2: Commission 15% | H2: 입금 내역 | I2: 입금일 | J2: 비고
A3: 5 | B3: 세흥인쇄 | C3: =D3*1.1 -> 1738000 | D3: 1580000 | E3: 192600 | F3: =E3/D3 -> 0.12189873 | G3: =E3*30% -> 57780 | H3: 입금되었음 | I3: 41851 | J3: 7/31 입금 57,708원
C4: =D4*1.1 -> 1738000 | D4: 1580000 | E4: 192600 | F4: =E4/D4 -> 0.12189873 | G4: =E4*30% -> 57780 | H4: .
A5: 6 | B5: 세흥인쇄 | C5: =D5*1.1 -> 2519000 | D5: 2290000 | E5: 456300 | F5: =E5/D5 -> 0.19925764 | G5: =E5*30% -> 136890 | H5: 입금되었음 | I5: 41874 | J5: 8/23 입금 136,890원
C6: =D6*1.1 -> 2519000 | D6: 2290000 | E6: 456300 | F6: =E6/D6 -> 0.19925764 | G6: =E6*30% -> 136890 | H6: .
A7: 7 | B7: 세흥인쇄 | C7: =D7*1.1 -> 6833750 | D7: 6212500 | E7: 1532500 | F7: =E7/D7 -> 0.24668008 | G7: =E7*30% -> 459750 | H7: 입금되었음 | I7: 41907 | J7: 9/25 입금 459,750원
B8: 정명인쇄 | C8: =D8*1.1 -> 2057000 | D8: 1870000 | E8: 332000 | F8: =E8/D8 -> 0.17754011 | G8: =E8*30% -> 99600 | H8: 입금되었음 | I8: 41938 | J8: 10/26 입금 755,610원
C9: =D9*1.1 -> 8890750 | D9: 8082500 | E9: 1864500 | F9: =E9/D9 -> 0.23068358 | G9: =E9*30% -> 559350 | H9: .
A10: 8 | B10: 세흥인쇄 | C10: =D10*1.1 -> 9880750 | D10: 8982500 | E10: 2186500 | F10: =E10/D10 -> 0.24341776 | G10: =E10*30% -> 655950 | H10: 입금되었음 | I10: 41938
B11: 일흥피앤피 | C11: =D11*1.1 -> 1131900 | D11: 1029000 | E11: 259000 | F11: =E11/D11 -> 0.25170068 | G11: =E11*30% -> 77700 | H11: 입금되었음 | I11: 11월 22일 | J11: 11/22 732,630원
C12: =D12*1.1 -> 11012650 | D12: 10011500 | E12: 2445500 | F12: =E12/D12 -> 0.24426909 | G12: =E12*30% -> 733650 | H12: .
A13: 9 | B13: 세흥인쇄 | C13: =D13*1.1 -> 6611000 | D13: 6010000 | E13: 1765500 | F13: =E13/D13 -> 0.2937604 | G13: =E13*30% -> 529650 | H13: 입금되었음 | I13: 11월 22일
B14: 덕수산업 | C14: =D14*1.1 -> 110000 | D14: 100000 | E14: 75000 | F14: =E14/D14 -> 0.75 | G14: =E14*30% -> 22500 | H14: 입금되었음 | I14: 12월 30일
C15: =D15*1.1 -> 6721000 | D15: 6110000 | E15: 1840500 | F15: =E15/D15 -> 0.3012275 | G15: =E15*30% -> 552150 | H15: .
A16: 10 | B16: 맥스타 | C16: =D16*1.1 -> 1100000 | D16: 1000000 | E16: 300000 | F16: =E16/D16 -> 0.3 | G16: =E16*30% -> 90000 | H16: 입금되었음 | I16: 11월 22일
B17: 부경인재 | C17: =D17*1.1 -> 198000 | D17: 180000 | E17: 36000 | F17: =E17/D17 -> 0.2 | G17: =E17*30% -> 10800 | H17: 입금되었음 | I17: 11월 22일
B18: 세흥인쇄 | C18: =D18*1.1 -> 8179600 | D18: 7436000 | E18: 1976500 | F18: =E18/D18 -> 0.26580151 | G18: =E18*30% -> 592950 | H18: 입금되었음 | I18: 12월 30일 | J18: 12/30 입금 890,550원
B19: 이펙피앤피 | C19: =D19*1.1 -> 642400 | D19: 584000 | E19: 81600 | F19: =E19/D19 -> 0.13972603 | G19: =E19*30% -> 24480 | H19: 입금되었음 | I19: 11월 22일
B20: 대하팩키지 | C20: =D20*1.1 -> 1375000 | D20: 1250000 | E20: 457000 | F20: =E20/D20 -> 0.3656 | G20: =E20*30% -> 137100 | H20: 입금되었음 | I20: 12월 30일
B21: 동양인재 | C21: =D21*1.1 -> 1650000 | D21: 1500000 | E21: 190000 | F21: =E21/D21 -> 0.12666667 | G21: =E21*30% -> 57000 | H21: 입금되었음 | I21: 12월 30일
C22: =SUM(C16:C21) -> 13145000 | D22: =SUM(D16:D21) -> 11950000 | E22: =SUM(E16:E21) -> 3041100 | F22: =E22/D22 -> 0.25448536 | G22: =SUM(G16:G21) -> 912330 | H22: .
A23: 11 | B23: 세흥인쇄 | C23: =D23*1.1 -> 13402400 | D23: 12184000 | E23: 3373500 | F23: =E23/D23 -> 0.27687951 | G23: =E23*30% -> 1012050 | H23: 입금되었음 | I23: 41663 | J23: 1/24 입금 1.194,900원
B24: 세영애드 | C24: =D24*1.1 -> 2596000 | D24: 2360000 | E24: 440000 | F24: =E24/D24 -> 0.18644068 | G24: =E24*30% -> 132000 | H24: 입금되었음 | I24: 41800
B25: 동양인재 | C25: =D25*1.1 -> 1485000 | D25: 1350000 | E25: 270000 | F25: =E25/D25 -> 0.2 | G25: =E25*30% -> 81000 | H25: 입금되었음 | I25: 12월 30일
B26: 삼영특수(차인수) | C26: =D26*1.1 -> 968000 | D26: 880000 | E26: 251700 | F26: =E26/D26 -> 0.28602273 | G26: =E26*30% -> 75510 | H26: 입금되었음 | I26: 41800
B27: 삼영특수(차인수) | C27: =D27*1.1 -> 4400000 | D27: 4000000 | E27: 1401600 | F27: =E27/D27 -> 0.3504 | G27: =E27*30% -> 420480 | H27: 입금되었음 | I27: 41800
B28: 우정인쇄 | C28: =D28*1.1 -> 440000 | D28: 400000 | E28: 92000 | F28: =E28/D28 -> 0.23 | G28: =E28*30% -> 27600 | H28: 입금되었음 | I28: HKR Commission
B29: 대일프린텍 | C29: =D29*1.1 -> 715000 | D29: 650000 | E29: 125000 | F29: =E29/D29 -> 0.19230769 | G29: =E29*30% -> 37500 | H29: 입금되었음 | I29: HKR Commission
C30: =SUM(C23:C29) -> 24006400 | D30: =SUM(D23:D29) -> 21824000 | E30: =SUM(E23:E29) -> 5953800 | F30: =E30/D30 -> 0.27280975 | H30: .
A31: 12 | B31: 세흥인쇄 | C31: =D31*1.1 -> 12310650 | D31: 11191500 | E31: 3378000 | F31: =E31/D31 -> 0.30183621 | G31: =E31*20% -> 675600 | H31: 입금되었음 | I31: 41703 | J31: 3/5 입금 1,177,804원
B32: 정명인쇄 | C32: =D32*1.1 -> 1611500 | D32: 1465000 | E32: 249500 | F32: =E32/D32 -> 0.17030717 | G32: =E32*30% -> 74850 | H32: 입금되었음 | I32: 41663
B33: 일흥피앤피 | C33: =D33*1.1 -> 1273800 | D33: 1158000 | E33: 343000 | F33: =E33/D33 -> 0.29620035 | G33: =E33*30% -> 102900 | H33: 입금되었음 | I33: 41730 | J33: 4/1 입금 207,092원 469,412-60,000(주차료) -202,320(연말정산)=207,092
B34: 대하팩키지 | C34: =D34*1.1 -> 1375000 | D34: 1250000 | E34: 457000 | F34: =E34/D34 -> 0.3656 | G34: =E34*30% -> 137100 | H34: 입금 확인요망
B35: 덕수산업 | C35: =D35*1.1 -> 2750000 | D35: 2500000 | E35: 659200 | F35: =E35/D35 -> 0.26368 | G35: =E35*20% -> 131840 | H35: 입금되었음 | I35: 41703
B36: 동양인재 | C36: =D36*1.1 -> 1980000 | D36: 1800000 | E36: 360000 | F36: =E36/D36 -> 0.2 | G36: =E36*30% -> 108000 | H36: 입금되었음 | I36: 41663
C37: =SUM(C31:C36) -> 21300950 | D37: =SUM(D31:D36) -> 19364500 | E37: =SUM(E31:E36) -> 5446700 | F37: =E37/D37 -> 0.28127243 | H37: .
A38: 2014. 1 | B38: 덕수산업 | C38: 2750000 | D38: 2500000 | E38: 659200 | F38: =E38/D38 -> 0.26368 | G38: =E38*20% -> 131840 | H38: 입금되었음 | I38: 41703
B39: 동양인재 | C39: 2277000 | D39: 2070000 | E39: 77000 | F39: =E39/D39 -> 0.037198068 | G39: =E39*20% -> 15400 | H39: 입금되었음 | I39: 41703
B40: 디자인부산 | C40: 748000 | D40: 680000 | E40: 162140 | F40: =E40/D40 -> 0.23844118 | G40: =E40*20% -> 32428 | H40: 입금되었음 | I40: 41703
B41: 세영애드 | C41: 1298000 | D41: 1180000 | E41: 220000 | F41: =E41/D41 -> 0.18644068 | G41: =E41*20% -> 44000 | H41: 입금되었음 | I41: 41703
B42: 세흥인쇄 | C42: 3856050 | D42: 3505500 | E42: 916000 | F42: =E42/D42 -> 0.26130367 | G42: =E42*30% -> 274800 | H42: 입금되었음 | I42: 41730
B43: 태영정판 | C43: 1485000 | D43: 1350000 | E43: 392320 | F43: =E43/D43 -> 0.29060741 | G43: =E43*20% -> 78464 | H43: 입금되었음 | I43: 41703
B44: 한글그래픽스 | C44: 1430000 | D44: 1300000 | E44: 341160 | F44: =E44/D44 -> 0.26243077 | G44: =E44*20% -> 68232 | H44: 입금되었음 | I44: 41703
C45: 13844050 | D45: 12585500 | E45: 2767820 | F45: =E45/D45 -> 0.21992134
A46: 2014. 2 | B46: 덕수산업 | C46: 1375000 | D46: 1250000 | E46: 329560 | F46: =E46/D46 -> 0.263648 | G46: =E46*20% -> 65912 | H46: 입금되었음 | I46: 41730
B47: 동양인재 | C47: 1485000 | D47: 1350000 | E47: 129000 | F47: =E47/D47 -> 0.095555556 | G47: =E47*20% -> 25800 | H47: 입금되었음 | I47: 41730
B48: 세흥인쇄 | C48: 9455600 | D48: 8596000 | E48: 2473250 | F48: =E48/D48 -> 0.28772103 | G48: 494650 | H48: 입금되었음 | I48: 41771 | J48: * 5/12 입금 1,157,582원
B49: 일흥피앤피 | C49: 323400 | D49: 294000 | E49: 74000 | F49: =E49/D49 -> 0.25170068 | G49: =E49*30% -> 22200 | H49: 입금되었음 | I49: 41800
C50: =SUM(C46:C49) -> 12639000 | D50: =SUM(D46:D49) -> 11490000 | E50: =SUM(E46:E49) -> 3005810 | F50: =E50/D50 -> 0.26160226
A51: 2014. 3 | B51: 덕수산업 | C51: 1375000 | D51: 1250000 | E51: 329560 | F51: =E51/D51 -> 0.263648 | G51: =E51*20% -> 65912 | H51: 입금되었음 | I51: 41771
B52: 대하팩키지 | C52: 715000 | D52: 650000 | E52: 203100 | F52: =E52/D52 -> 0.31246154 | G52: =E52*30% -> 60930
B53: 동양인재 | C53: 2722500 | D53: 2475000 | E53: 351200 | F53: =E53/D53 -> 0.14189899 | G53: =E53*30% -> 105360 | H53: 입금되었음 | I53: 41800
B54: 동양인재 | C54: 3960000 | D54: 3600000 | E54: 576200 | F54: =E54/D54 -> 0.16005556 | G54: =E54*30% -> 172860 | H54: 입금되었음 | I54: 41800
B55: 세흥인쇄 | C55: 7808350 | D55: 7098500 | E55: 1829500 | F55: =E55/D55 -> 0.25773051 | G55: =E55*20% -> 365900 | H55: 입금되었음 | I55: 41771
B56: 우정인쇄 | C56: 440000 | D56: 400000 | E56: 92000 | F56: =E56/D56 -> 0.23 | G56: =E56*30% -> 27600 | H56: 입금되었음 | I56: HKR Commission
C57: =SUM(C51:C56) -> 17020850 | D57: =SUM(D51:D56) -> 15473500 | E57: =SUM(E51:E56) -> 3381560 | F57: =E57/D57 -> 0.21853879 | G57: =SUM(G51:G56) -> 798562
A58: 2014. 4 | B58: 덕수산업 | C58: =D58*1.1 -> 1485000 | D58: 1350000 | E58: 367100 | F58: =E58/D58 -> 0.27192593 | G58: =E58*30% -> 110130 | H58: 입금되었음 | I58: 41800
B59: 동양인재 | C59: =D59*1.1 -> 5566000 | D59: 5060000 | E59: 724400 | F59: =E59/D59 -> 0.14316206 | G59: =E59*30% -> 217320 | H59: 입금되었음 | I59: 41771
B60: 세흥인쇄 | C60: =D60*1.1 -> 8641600 | D60: 7856000 | E60: 2388500 | F60: =E60/D60 -> 0.30403513 | G60: =E60*30% -> 716550 | H60: 입금되었음 | I60: 41800 | J60: * 6/10 입금 1,848,587원
B61: 미래인텍 | C61: =D61*1.1 -> 341000 | D61: 310000 | E61: 46000 | F61: =E61/D61 -> 0.1483871 | G61: =E61*30% -> 13800 | H61: 입금되었음 | I61: 41771
B62: 세영애드인 | C62: =D62*1.1 -> 1298000 | D62: 1180000 | E62: 220000 | F62: =E62/D62 -> 0.18644068 | G62: =E62*30% -> 66000 | H62: 입금되었음 | I62: 41800
C63: =SUM(C58:C62) -> 17331600 | D63: =SUM(D58:D62) -> 15756000 | E63: =SUM(E58:E62) -> 3746000 | F63: =E63/D63 -> 0.2377507 | G63: =SUM(G58:G62) -> 1123800
A64: 2014. 5 | B64: 대하팩키지 | C64: =D64*1.1 -> 1705000 | D64: 1550000 | E64: 482400 | F64: =E64/D64 -> 0.31122581 | G64: =E64*30% -> 144720 | J64: *대하팩키지 8/14 통화, 현재잔액 2,420,000원(3월,5월)확인
B65: 덕수산업 | C65: =D65*1.1 -> 1210000 | D65: 1100000 | E65: 180000 | F65: =E65/D65 -> 0.16363636 | G65: =E65*30% -> 54000 | H65: 입금되었음 | I65: 41841
B66: 디자인부산 | C66: =D66*1.1 -> 748000 | D66: 680000 | E66: 162200 | F66: =E66/D66 -> 0.23852941 | G66: =E66*30% -> 48660 | H66: 입금되었음 | I66: 41841
B67: 세흥인쇄 | C67: =D67*1.1 -> 4139300 | D67: 3763000 | E67: 953750 | F67: =E67/D67 -> 0.25345469 | G67: =E67*30% -> 286125 | H67: 입금되었음 | I67: 41841
B68: 태영정판 | C68: =D68*1.1 -> 1430000 | D68: 1300000 | E68: 342320 | F68: =E68/D68 -> 0.26332308 | G68: =E68*30% -> 102696 | H68: 입금되었음 | I68: 41841 | J68: * 7/21 입금 491,481원
B69: 교학사 | C69: =D69*1.1 -> 4455000 | D69: 4050000 | E69: 1050000 | F69: =E69/D69 -> 0.25925926 | G69: =E69*30% -> 315000
C70: =SUM(C64:C69) -> 13687300 | D70: =SUM(D64:D69) -> 12443000 | E70: =SUM(E64:E69) -> 3170670 | F70: =E70/D70 -> 0.25481556 | G70: =SUM(G64:G69) -> 951201
A71: 2014. 6 | B71: 덕수산업 | C71: =D71*1.1 -> 18700000 | D71: 17000000 | E71: 4700000 | F71: =E71/D71 -> 0.27647059 | G71: =E71*15% -> 705000 | J71: *농도계 commission 15%
B72: 덕수산업 | C72: =D72*1.1 -> 2420000 | D72: 2200000 | E72: 360000 | F72: =E72/D72 -> 0.16363636 | G72: =E72*30% -> 108000
B73: 동양인재 | C73: =D73*1.1 -> 1534500 | D73: 1395000 | E73: 108820 | F73: =E73/D73 -> 0.078007168 | G73: =E73*30% -> 32646
B74: 맥스타 | C74: =D74*1.1 -> 770000 | D74: 700000 | E74: 200000 | F74: =E74/D74 -> 0.28571429 | G74: =E74*30% -> 60000 | J74: HKR Commission
B75: 세흥인쇄 | C75: =D75*1.1 -> 8093800 | D75: 7358000 | E75: 2144120 | F75: =E75/D75 -> 0.29139984 | G75: =E75*30% -> 643236
B76: 미래인텍 | C76: =D76*1.1 -> 341000 | D76: 310000 | E76: 46000 | F76: =E76/D76 -> 0.1483871 | G76: =E76*30% -> 13800
B77: 교학사 | C77: =D77*1.1 -> 2909500 | D77: 2645000 | E77: 615000 | F77: =E77/D77 -> 0.23251418 | G77: =E77*30% -> 184500
B78: 천재상사 | C78: =D78*1.1 -> 2956250 | D78: 2687500 | E78: 315000 | F78: =E78/D78 -> 0.1172093 | G78: =E78*30% -> 94500
B79: 프린피아 문발공장 | C79: =D79*1.1 -> 594000 | D79: 540000 | E79: 108000 | F79: =E79/D79 -> 0.2 | G79: =E79*30% -> 32400
C80: =SUM(C71:C79) -> 38319050 | D80: =SUM(D71:D79) -> 34835500 | E80: =SUM(E71:E79) -> 8596940 | F80: =E80/D80 -> 0.24678675 | G80: =SUM(G71:G79) -> 1874082
A81: 2014. 7 | B81: 디자인부산 | C81: 680000 | D81: 680000 | E81: 162200 | F81: =E81/D81 -> 0.23852941 | G81: =E81*30% -> 48660
B82: 동양인재 | C82: 2475000 | D82: 2250000 | E82: 306200 | F82: =E82/D82 -> 0.13608889 | G82: =E82*30% -> 91860
B83: 세영애드인 | C83: 1298000 | D83: 1180000 | E83: 220000 | F83: =E83/D83 -> 0.18644068 | G83: =E83*30% -> 66000
B84: 정명인쇄 | C84: 891000 | D84: 810000 | E84: 165000 | F84: =E84/D84 -> 0.2037037 | G84: =E84*30% -> 49500
B85: 동양인재 | C85: 44000 | D85: 40000 | E85: 6000 | F85: =E85/D85 -> 0.15 | G85: =E85*30% -> 1800
B86: 프린피아 문발공장 | C86: 217800 | D86: 198000 | E86: 22000 | F86: =E86/D86 -> 0.11111111 | G86: =E86*30% -> 6600
B87: 한글그래픽스 | C87: 1430000 | D87: 1300000 | E87: 340000 | F87: =E87/D87 -> 0.26153846 | G87: =E87*30% -> 102000
B88: 덕수산업 | C88: 3630000 | D88: 3300000 | E88: 540000 | F88: =E88/D88 -> 0.16363636 | G88: =E88*30% -> 162000
B89: 세흥인쇄 | C89: 9329100 | D89: 8481000 | E89: 2141000 | F89: =E89/D89 -> 0.25244665 | G89: =E89*30% -> 642300
B90: 천재상사 | C90: 6363500 | D90: 5785000 | E90: 872000 | F90: =E90/D90 -> 0.15073466 | G90: =E90*30% -> 261600
B91: 세흥인쇄 | C91: 9350000 | D91: 8500000 | E91: 3390000 | F91: =E91/D91 -> 0.39882353 | G91: =E91*15% -> 508500 | J91: *농도계 commission 15%
C92: =SUM(C81:C91) -> 35708400 | D92: =SUM(D81:D91) -> 32524000 | E92: =SUM(E81:E91) -> 8164400 | F92: =E92/D92 -> 0.25102693 | G92: =SUM(G81:G91) -> 1940820
A93: 2014. 8 | B93: 덕수산업 | C93: 2420000 | D93: 2200000 | E93: 360000 | F93: =E93/D93 -> 0.16363636 | G93: =E93*30% -> 108000
B94: 동양인재 | C94: 1856250 | D94: 1687500 | E94: 337500 | F94: =E94/D94 -> 0.2 | G94: =E94*30% -> 101250
B95: 동양인재 | C95: 1485000 | D95: 1350000 | E95: 126200 | F95: =E95/D95 -> 0.093481481 | G95: =E95*30% -> 37860
B96: 세흥인쇄 | C96: 8573675 | D96: 7794250 | E96: 1988320 | F96: =E96/D96 -> 0.25510088 | G96: =E96*30% -> 596496
B97: 교학사 | C97: 16799200 | D97: 15272000 | E97: 5077000 | F97: =E97/D97 -> 0.33243845 | G97: =E97*15% -> 761550 | J97: *농도계 commission 15%
B98: 천재상사 | C98: 5698000 | D98: 5180000 | E98: 837000 | F98: =E98/D98 -> 0.16158301 | G98: =E98*30% -> 251100
B99: 세영애드인 | C99: 1298000 | D99: 1180000 | E99: 220000 | F99: =E99/D99 -> 0.18644068 | G99: =E99*30% -> 66000
B100: 상지사 | C100: 9900000 | D100: 9000000 | E100: 2835000 | F100: =E100/D100 -> 0.315 | G100: =E100*15% -> 425250 | J100: *농도계 commission 15%
B101: 한국하이델베르그 (납품-동도씨앤피) | C101: 9350000 | D101: 8500000 | E101: 2260000 | F101: =E101/D101 -> 0.26588235 | G101: =E101*15% -> 339000 | J101: *농도계 commission 15%
...

Sheet Technotrans
A1: Month | B1: Customer | C1: Sales (VAT 포함) | D1: Sales (VAT 제외) | E1: CM | F1: CM % | G1: Commission 15% | H1: 입금 내역 | I1: 입금일
A2: 2014. 5 | B2: 세흥인쇄 | C2: 42900000 | D2: 39000000 | F2: =E2/D2 -> 0 | G2: =E2*30% -> 0
C3: =SUM(C2:C2) -> 42900000 | D3: =SUM(D2:D2) -> 39000000 | E3: =SUM(E2:E2) -> 0 | F3: =E3/D3 -> 0 | G3: =SUM(G2:G2) -> 0
A4: 2014. 7 | B4: 팩컴 AAP | C4: 2090000 | D4: 1900000 | E4: 500000 | F4: =E4/D4 -> 0.26315789 | G4: =E4*30% -> 150000
B5: 신창 디지털프린텍 | C5: 431200 | D5: 392000 | F5: =E5/D5 -> 0 | G5: =E5*30% -> 0
C6: =SUM(C4:C5) -> 2521200 | D6: =SUM(D4:D5) -> 2292000 | E6: =SUM(E4:E5) -> 500000 | F6: =E6/D6 -> 0.21815009 | G6: =SUM(G4:G5) -> 150000
A7: 2014. 10 | B7: 송운사 | C7: 9515000 | D7: 8650000 | F7: =E7/D7 -> 0 | G7: =E7*30% -> 0
C8: =SUM(C7) -> 9515000 | D8: =SUM(D7) -> 8650000 | E8: =SUM(E7) -> 0 | F8: =E8/D8 -> 0 | G8: =SUM(G6:G7) -> 150000
A9: 2015. 1 | B9: 상현원색 | C9: 3850000 | D9: 3500000 | F9: =E9/D9 -> 0 | G9: =E9*30% -> 0
C10: =SUM(C9:C9) -> 3850000 | D10: =SUM(D9:D9) -> 3500000 | E10: =SUM(E9:E9) -> 0 | F10: =E10/D10 -> 0 | G10: =SUM(G9:G9) -> 0
A11: 2015. 2 | B11: 아이피디 | C11: 1375000 | D11: 1250000 | F11: =E11/D11 -> 0 | G11: =E11*30% -> 0
C12: =SUM(C11) -> 1375000 | D12: =SUM(D11) -> 1250000 | E12: =SUM(E11) -> 0 | F12: =E12/D12 -> 0 | G12: =SUM(G10:G11) -> 0
A13: 2015. 4 | B13: 팩컴 AAP | C13: 2090000 | D13: 1900000 | E13: 789354 | F13: =E13/D13 -> 0.41544947 | G13: =E13*30% -> 236806.2
B14: 아이피디 | C14: 790900 | D14: 719000 | E14: 457622 | F14: =E14/D14 -> 0.6364701
B15: 재능인쇄 | C15: 28490000 | D15: 25900000 | F15: =E15/D15 -> 0
C16: =SUM(C13:C15) -> 31370900 | D16: =SUM(D13:D15) -> 28519000 | E16: =SUM(E13:E15) -> 1246976 | F16: =E16/D16 -> 0.043724394 | G16: =SUM(G13:G15) -> 236806.2
A17: 2015. 5 | B17: 삼원인쇄 | C17: 2090000 | D17: 1900000 | E17: 789354 | F17: =E17/D17 -> 0.41544947
B18: 덕수산업 | C18: 369600 | D18: 336000 | E18: 177712 | F18: =E18/D18 -> 0.52890476 | G18: =E18*30% -> 53313.6
C19: =SUM(C17:C18) -> 2459600 | D19: =SUM(D17:D18) -> 2236000 | E19: =SUM(E17:E18) -> 967066 | F19: =E19/D19 -> 0.43249821 | G19: =SUM(G17:G18) -> 53313.6
A20: 2015. 6 | B20: 신흥피앤피 | C20: 583000 | D20: 530000 | E20: 216000 | F20: =E20/D20 -> 0.40754717 | G20: =E20*30% -> 64800
B21: 퍼시픽패키지 | C21: 577500 | D21: 525000 | E21: 228000 | F21: =E21/D21 -> 0.43428571 | G21: =E21*30% -> 68400
B22: 퍼시픽패키지 | C22: 462000 | D22: 420000 | E22: 176500 | F22: =E22/D22 -> 0.4202381 | G22: =E22*30% -> 52950
B23: 국민피앤텍 | C23: 198000 | D23: 180000 | E23: 100856 | F23: =E23/D23 -> 0.56031111 | G23: =E23*30% -> 30256.8
C24: =SUM(C20:C23) -> 1820500 | D24: =SUM(D20:D23) -> 1655000 | E24: =SUM(E20:E23) -> 721356 | F24: =E24/D24 -> 0.43586465 | G24: =SUM(G20:G23) -> 216406.8
A25: 2015. 7 | B25: 보문특수칼라 | C25: 440000 | D25: 400000 | E25: 202140 | F25: =E25/D25 -> 0.50535 | G25: =E25*30% -> 60642
B26: 퍼시픽패키지 | C26: 1309000 | D26: 1190000 | E26: 413200 | F26: =E26/D26 -> 0.34722689 | G26: =E26*30% -> 123960
B27: 퍼시픽패키지 | C27: 577500 | D27: 525000 | E27: 228000 | F27: =E27/D27 -> 0.43428571 | G27: =E27*30% -> 68400
B28: 배원인쇄사 | C28: 297000 | D28: 270000 | E28: 151284 | F28: =E28/D28 -> 0.56031111 | G28: =E28*30% -> 45385.2
C29: =SUM(C25:C28) -> 2623500 | D29: =SUM(D25:D28) -> 2385000 | E29: =SUM(E25:E28) -> 994624 | F29: =E29/D29 -> 0.41703312 | G29: =SUM(G25:G28) -> 298387.2
A30: 2015. 8 | B30: 세종씨앤피 | C30: 165000 | D30: 150000 | E30: 51070 | F30: =E30/D30 -> 0.34046667 | G30: =E30*30% -> 15321
B31: 국민피앤텍 | C31: 4950000 | D31: 4500000 | E31: 1700000 | F31: =E31/D31 -> 0.37777778 | G31: =E31*30% -> 510000
C32: =SUM(C30:C31) -> 5115000 | D32: =SUM(D30:D31) -> 4650000 | E32: =SUM(E30:E31) -> 1751070 | F32: =E32/D32 -> 0.37657419 | G32: =SUM(G30:G31) -> 525321
A33: 2015. 9 | B33: 한빛테크 | C33: 1342000 | D33: 1220000 | E33: 451800 | F33: =E33/D33 -> 0.37032787 | G33: =E33*30% -> 135540
C34: =SUM(C33:C33) -> 1342000 | D34: =SUM(D33:D33) -> 1220000 | E34: =SUM(E33:E33) -> 451800 | F34: =E34/D34 -> 0.37032787 | G34: =SUM(G33:G33) -> 135540
A35: 2015. 10 | B35: 퍼시픽패키지 | C35: 577500 | D35: 525000 | E35: 228000 | F35: =E35/D35 -> 0.43428571 | G35: =E35*30% -> 68400
B36: 퍼시픽패키지 | C36: 435600 | D36: 396000 | E36: 263800 | F36: =E36/D36 -> 0.66616162 | G36: =E36*30% -> 79140
B37: ㈜에스제이씨성전 | C37: 2310000 | D37: 2100000 | E37: 516600 | F37: =E37/D37 -> 0.246 | G37: =E37*30% -> 154980
B38: 조일인쇄 | C38: 418000 | D38: 380000 | E38: 36000 | F38: =E38/D38 -> 0.094736842 | J38: * 박영용 이사
C39: =SUM(C35:C38) -> 3741100 | D39: =SUM(D35:D38) -> 3401000 | E39: =SUM(E35:E38) -> 1044400 | F39: =E39/D39 -> 0.30708615 | G39: =SUM(G35:G38) -> 302520
A40: 2015. 11 | B40: 퍼시픽패키지 | C40: 770000 | D40: 700000 | E40: 304000 | F40: =E40/D40 -> 0.43428571 | G40: =E40*30% -> 91200
B41: ㈜ 대흥 | C41: 264000 | D41: 240000 | E41: 121284 | F41: =E41/D41 -> 0.50535 | G41: =E41*30% -> 36385.2
B42: 세종씨앤피 | C42: 330000 | D42: 300000 | E42: 102140 | F42: =E42/D42 -> 0.34046667 | G42: =E42*30% -> 30642
C43: =SUM(C40:C42) -> 1364000 | D43: =SUM(D40:D42) -> 1240000 | E43: =SUM(E40:E42) -> 527424 | F43: =E43/D43 -> 0.42534194 | G43: =SUM(G40:G42) -> 158227.2
A44: 2015. 12 | B44: 재능인쇄 | C44: 2310000 | D44: 2100000 | E44: 570000 | F44: =E44/D44 -> 0.27142857 | J44: * 박영용 이사
B45: 대한프린테크 | C45: 176000 | D45: 160000 | E45: 80856 | F45: =E45/D45 -> 0.50535 | G45: =E45*30% -> 24256.8
B46: 퍼시픽패키지 | C46: 13530000 | D46: 12300000 | E46: 6990000 | F46: =E46/D46 -> 0.56829268 | G46: =E46*15% -> 1048500 | J46: * commission 15%
B47: ㈜에스제이씨성전 | C47: 2310000 | D47: 2100000 | E47: 570000 | F47: =E47/D47 -> 0.27142857 | G47: =E47*30% -> 171000
B48: 퍼시픽패키지 | C48: 1155000 | D48: 1050000 | E48: 456000 | F48: =E48/D48 -> 0.43428571 | G48: =E48*30% -> 136800
C49: =SUM(C44:C48) -> 19481000 | D49: =SUM(D44:D48) -> 17710000 | E49: =SUM(E44:E48) -> 8666856 | F49: =E49/D49 -> 0.4893764 | G49: =SUM(G44:G48) -> 1380556.8
A50: 2016. 1 | B50: 대일프린텍 | C50: 220000 | D50: 200000 | E50: 160400 | F50: =E50/D50 -> 0.802 | G50: =E50*30% -> 48120
C51: =SUM(C50:C50) -> 220000 | D51: =SUM(D50:D50) -> 200000 | E51: =SUM(E50:E50) -> 160400 | F51: =E51/D51 -> 0.802 | G51: =SUM(G50:G50) -> 48120
A52: 2016. 2 | B52: 보진재 | C52: 429000 | D52: 390000 | E52: 75000 | F52: =E52/D52 -> 0.19230769
B53: 퍼시픽패키지 | C53: 577500 | D53: 525000 | E53: 228000 | F53: =E53/D53 -> 0.43428571 | G53: =E53*30% -> 68400
B54: 성원애드피아 | C54: 1848000 | D54: 1680000 | E54: 888000 | F54: =E54/D54 -> 0.52857143 | G54: =E54*30% -> 266400
B55: 현진인쇄 | C55: 2750000 | D55: 2500000 | E55: 700000 | F55: =E55/D55 -> 0.28 | G55: =E55*30% -> 210000
C56: =SUM(C52:C55) -> 5604500 | D56: =SUM(D52:D55) -> 5095000 | E56: =SUM(E52:E55) -> 1891000 | F56: =E56/D56 -> 0.37114818 | G56: =SUM(G52:G55) -> 544800
A57: 2016. 3 | B57: ㈜ 대흥 | C57: 1247400 | D57: 1134000 | E57: 357376.62 | F57: =E57/D57 -> 0.31514693 | G57: =E57*30% -> 107212.99
B58: 퍼시픽패키지 | C58: 847000 | D58: 770000 | E58: 286300 | F58: =E58/D58 -> 0.37181818 | G58: =E58*30% -> 85890
C59: =SUM(C57:C58) -> 2094400 | D59: =SUM(D57:D58) -> 1904000 | E59: =SUM(E57:E58) -> 643676.62 | F59: =E59/D59 -> 0.33806545 | G59: =SUM(G57:G58) -> 193102.99
A60: 2016. 4 | B60: 퍼시픽패키지 | C60: 1661000 | D60: 1510000 | E60: 649700 | F60: =E60/D60 -> 0.4302649 | G60: =E60*30% -> 194910
B61: 국민피앤텍 | C61: 247500 | D61: 225000 | E61: 126070 | F61: =E61/D61 -> 0.56031111 | G61: =E61*30% -> 37821
C62: =SUM(C60:C61) -> 1908500 | D62: =SUM(D60:D61) -> 1735000 | E62: =SUM(E60:E61) -> 775770 | F62: =E62/D62 -> 0.44712968 | G62: =SUM(G60:G61) -> 232731
A63: 2016. 5 | B63: 성원애드피아 | C63: 4730000 | D63: 4300000 | E63: 800000 | F63: =E63/D63 -> 0.18604651 | G63: =E63*30% -> 240000
B64: 퍼시픽패키지 | C64: 319000 | D64: 290000 | E64: 113000 | F64: =E64/D64 -> 0.38965517 | G64: =E64*30% -> 33900
B65: 국민피앤텍 | C65: 1210000 | D65: 1100000 | E65: 556000 | F65: =E65/D65 -> 0.50545455 | G65: =E65*30% -> 166800
B66: 퍼시픽패키지 | C66: 1463000 | D66: 1330000 | E66: 588000 | F66: =E66/D66 -> 0.44210526 | G66: =E66*30% -> 176400
B67: 세종씨앤피 | C67: 330000 | D67: 300000 | E67: 102140 | F67: =E67/D67 -> 0.34046667 | G67: =E67*30% -> 30642
B68: 팩컴 AAP | C68: 1540000 | D68: 1400000 | E68: 658000 | F68: =E68/D68 -> 0.47 | G68: =E68*30% -> 197400
B69: 재능인쇄 | C69: 880000 | D69: 800000 | E69: 256000 | F69: =E69/D69 -> 0.32 | G69: =E69*30% -> 76800
C70: =SUM(C63:C69) -> 10472000 | D70: =SUM(D63:D69) -> 9520000 | E70: =SUM(E63:E69) -> 3073140 | F70: =E70/D70 -> 0.32280882 | G70: =SUM(G63:G69) -> 921942
A71: 2016. 6 | B71: 퍼시픽패키지 | C71: 3190000 | D71: 2900000 | E71: 1555000 | F71: =E71/D71 -> 0.5362069 | G71: =E71*30% -> 466500
B72: 재능인쇄 | C72: 52580000 | D72: 47800000 | E72: 13320000 | F72: =E72/D72 -> 0.27866109 | H72: 습수정화장치
B73: 송운사 | C73: 148500 | D73: 135000 | E73: 75600 | F73: =E73/D73 -> 0.56 | G73: =E73*30% -> 22680
C74: =SUM(C71:C73) -> 55918500 | D74: =SUM(D71:D73) -> 50835000 | E74: =SUM(E71:E73) -> 14950600 | F74: =E74/D74 -> 0.29410052 | G74: =SUM(G71:G73) -> 489180
A75: 2016. 7 | B75: 퍼시픽패키지 | C75: 3289000 | D75: 2990000 | E75: 2203800 | F75: =E75/D75 -> 0.73705686 | G75: =E75*30% -> 661140
B76: 덕수산업 | C76: 17600000 | D76: 16000000 | E76: 5400000 | F76: =E76/D76 -> 0.3375 | G76: =E76*15% -> 810000 | J76: * Commission 15% (습수정화장치)
B77: 세흥인쇄 | C77: 330000 | D77: 300000 | E77: 102000 | F77: =E77/D77 -> 0.34 | G77: =E77*30% -> 30600
B78: 삼원인쇄 | C78: 2090000 | D78: 1900000 | E78: 789000 | F78: =E78/D78 -> 0.41526316 | G78: =E78*30% -> 236700
C79: =SUM(C75:C78) -> 23309000 | D79: =SUM(D75:D78) -> 21190000 | E79: =SUM(E75:E78) -> 8494800 | F79: =E79/D79 -> 0.40088721 | G79: =SUM(G75:G78) -> 1738440
A80: 2016. 8 | B80: ㈜에스제이씨성전 | C80: 9680000 | D80: 8800000 | E80: 2730000 | F80: =E80/D80 -> 0.31022727 | G80: =E80*30% -> 819000
B81: 퍼시픽패키지 | C81: 1155000 | D81: 1050000 | E81: 456000 | F81: =E81/D81 -> 0.43428571 | G81: =E81*30% -> 136800
B82: 퍼시픽패키지 | C82: 1199000 | D82: 1090000 | E82: 210000 | F82: =E82/D82 -> 0.19266055 | G82: =E82*30% -> 63000
B83: 퍼시픽패키지 | C83: 577500 | D83: 525000 | E83: 228000 | F83: =E83/D83 -> 0.43428571 | G83: =E83*30% -> 68400
B84: 삼화인쇄 | C84: 660000 | D84: 600000 | E84: 204000 | F84: =E84/D84 -> 0.34 | G84: =E84*30% -> 61200
B85: 엔투비 (포스코) | C85: 1111000 | D85: 1010000 | E85: 510000 | F85: =E85/D85 -> 0.5049505
C86: =SUM(C80:C85) -> 14382500 | D86: =SUM(D80:D85) -> 13075000 | E86: =SUM(E80:E85) -> 4338000 | F86: =E86/D86 -> 0.3317782 | G86: =SUM(G80:G85) -> 1148400
A87: 2016. 10 | B87: 국민피앤텍 | C87: 247500 | D87: 225000 | E87: 126070 | F87: =E87/D87 -> 0.56031111 | G87: =E87*30% -> 37821
B88: 퍼시픽패키지 | C88: 8712000 | D88: 7920000 | E88: 1808920.1 | F88: =E88/D88 -> 0.22839901 | G88: =E88*30% -> 542676.04
B89: 세종씨앤피 | C89: 330000 | D89: 300000 | E89: 102140 | F89: =E89/D89 -> 0.34046667 | G89: =E89*30% -> 30642
B90: 한국경제신문 | C90: 7360980 | D90: 6691800 | E90: 2491800 | F90: =E90/D90 -> 0.37236618
C91: =SUM(C87:C90) -> 16650480 | D91: =SUM(D87:D90) -> 15136800 | E91: =SUM(E87:E90) -> 4528930.1 | F91: =E91/D91 -> 0.29919997 | G91: =SUM(G87:G90) -> 611139.04
A92: 2016. 11 | B92: 케이엠피 | C92: 6050000 | D92: 5500000 | E92: 2068000 | F92: =E92/D92 -> 0.376 | G92: =E92*30% -> 620400
B93: 재능인쇄 | C93: 2277000 | D93: 2070000 | E93: 549000 | F93: =E93/D93 -> 0.26521739 | G93: =E93*30% -> 164700
B94: 퍼시픽패키지 | C94: 770000 | D94: 700000 | E94: 304000 | F94: =E94/D94 -> 0.43428571 | G94: =E94*30% -> 91200
B95: 에스엠 인터내셔널 | C95: 165000 | D95: 150000 | E95: 51000 | F95: =E95/D95 -> 0.34 | G95: =E95*30% -> 15300
B96: 시엠시 | C96: 330000 | D96: 300000 | E96: 102000 | F96: =E96/D96 -> 0.34 | G96: =E96*30% -> 30600
B97: 정광인쇄 | C97: 110000 | D97: 100000 | E97: 60400 | F97: =E97/D97 -> 0.604 | G97: =E97*30% -> 18120
C98: =SUM(C92:C97) -> 9702000 | D98: =SUM(D92:D97) -> 8820000 | E98: =SUM(E92:E97) -> 3134400 | F98: =E98/D98 -> 0.35537415 | G98: =SUM(G92:G97) -> 940320
A99: 2016. 12 | B99: 송운사 | C99: 148500 | D99: 135000 | E99: 75600 | F99: =E99/D99 -> 0.56 | G99: =E99*30% -> 22680
B100: 케이엠피 | C100: 440000 | D100: 400000 | E100: 202000 | F100: =E100/D100 -> 0.505 | G100: =E100*30% -> 60600
...

Sheet GOSS
A1: Month | B1: Customer | C1: Sales (VAT 포함) | D1: Sales (VAT 제외) | E1: CM | F1: CM % | G1: Commission 2% | H1: 입금 내역 | I1: 입금일 | J1: 비고
A2: 2015. 7 | B2: 매일신문사 | C2: 2508000 | D2: 2280000 | E2: 620300 | F2: =E2/D2 -> 0.2720614
C3: =SUM(C2:C2) -> 2508000 | D3: =SUM(D2:D2) -> 2280000 | E3: =SUM(E2:E2) -> 620300 | F3: =E3/D3 -> 0.2720614 | G3: =SUM(G2:G2) -> 0
A4: 2015. 10 | B4: 신흥피앤피 | C4: 4400000 | D4: 4000000 | E4: 2073198.1 | F4: =E4/D4 -> 0.51829952
B5: 재능인쇄 | C5: 1980000 | D5: 1800000 | E5: 892000 | F5: =E5/D5 -> 0.49555556
B6: 교학사 | C6: 418000 | D6: 380000 | E6: 205120 | F6: =E6/D6 -> 0.53978947
C7: =SUM(C4:C6) -> 6798000 | D7: =SUM(D4:D6) -> 6180000 | E7: =SUM(E4:E6) -> 3170318.1 | F7: =E7/D7 -> 0.51299645 | G7: =SUM(G4:G6) -> 0
A8: 2015. 11 | B8: 교학사 | C8: 1166000 | D8: 1060000 | E8: 677120 | F8: =E8/D8 -> 0.63879245
B9: 프린피아 문발공장-임경영대리 | C9: 1694000 | D9: 1540000 | E9: 764720 | F9: =E9/D9 -> 0.49657143
B10: 프린피아 주안 -임경영 대리 | C10: 946000 | D10: 860000 | E10: 382000 | F10: =E10/D10 -> 0.44418605
C11: =SUM(C8:C10) -> 3806000 | D11: =SUM(D8:D10) -> 3460000 | E11: =SUM(E8:E10) -> 1823840 | F11: =E11/D11 -> 0.52712139 | G11: =SUM(G8:G10) -> 0
A12: 2015. 12 | B12: 재능인쇄 | C12: 570900 | D12: 519000 | E12: 231000 | F12: =E12/D12 -> 0.44508671
B13: 프린피아 문발공장-임경영대리 | C13: 409200 | D13: 372000 | E13: 102000 | F13: =E13/D13 -> 0.27419355
B14: 프린피아 파주- 임경영대리 | C14: 464200 | D14: 422000 | E14: 150000 | F14: =E14/D14 -> 0.35545024
B15: 신흥피앤피 | C15: 165000 | D15: 150000 | E15: 150000 | F15: =E15/D15 -> 1
B16: 팩컴 AAP | C16: 759000 | D16: 690000 | E16: 482000 | F16: =E16/D16 -> 0.69855072
B17: 한국하이델베르그 | C17: 880000 | D17: 800000 | E17: 320000 | F17: =E17/D17 -> 0.4
B18: 교학사 | C18: 418000 | D18: 380000 | E18: 205120 | F18: =E18/D18 -> 0.53978947
B19: 한국경제신문 | C19: 20680000 | D19: 18800000 | E19: 2100000 | F19: =E19/D19 -> 0.11170213
B20: 팩컴 AAP | C20: 440000 | D20: 400000 | E20: 207000 | F20: =E20/D20 -> 0.5175
B21: 신흥피앤피 | C21: 1485000 | D21: 1350000 | E21: 804000 | F21: =E21/D21 -> 0.59555556
B22: 프린피아 주안 -임경영 대리 | C22: 990000 | D22: 900000 | E22: 442500 | F22: =E22/D22 -> 0.49166667
B23: 프린피아 문발공장-임경영대리 | C23: 5060000 | D23: 4600000 | E23: 1792000 | F23: =E23/D23 -> 0.38956522
C24: =SUM(C12:C23) -> 32321300 | D24: =SUM(D12:D23) -> 29383000 | E24: =SUM(E12:E23) -> 6985620 | F24: =E24/D24 -> 0.23774359 | G24: =SUM(G12:G23) -> 0
A25: 2016. 1 | B25: 팩컴 AAP | C25: 9350000 | D25: 8500000 | E25: 4170000 | F25: =E25/D25 -> 0.49058824
B26: HnP(에치엔피) (구, 학원사) | C26: 11000000 | D26: 10000000 | E26: -1436000 | F26: =E26/D26 -> -0.1436
B27: 삼화인쇄 | C27: 990000 | D27: 900000 | E27: 275000 | F27: =E27/D27 -> 0.30555556
B28: 교학사 | C28: 264000 | D28: 240000 | E28: 188000 | F28: =E28/D28 -> 0.78333333
B29: 프린피아 주안 -임경영 대리 | C29: 3102000 | D29: 2820000 | E29: 1322500 | F29: =E29/D29 -> 0.46897163
B30: 매일경제(MBN) | C30: 1178650 | D30: 1071500 | E30: 1071500 | F30: =E30/D30 -> 1
C31: =SUM(C25:C30) -> 25884650 | D31: =SUM(D25:D30) -> 23531500 | E31: =SUM(E25:E30) -> 5591000 | F31: =E31/D31 -> 0.23759641 | G31: =SUM(G25:G30) -> 0
A32: 2016. 2 | B32: 매일경제(MBN) | C32: 6457000 | D32: 5870000 | E32: 1170000 | F32: =E32/D32 -> 0.19931857
B33: 삼화인쇄 | C33: 676500 | D33: 615000 | E33: 243000 | F33: =E33/D33 -> 0.39512195
B34: 보진재 | C34: 660000 | D34: 600000 | E34: 327600 | F34: =E34/D34 -> 0.546
B35: 신흥피앤피 | C35: 891000 | D35: 810000 | E35: 332000 | F35: =E35/D35 -> 0.40987654
B36: 재능인쇄 | C36: 1584000 | D36: 1440000 | E36: 713600 | F36: =E36/D36 -> 0.49555556
B37: 프린피아 주안 -임경영 대리 | C37: 500500 | D37: 455000 | E37: 171000 | F37: =E37/D37 -> 0.37582418
C38: =SUM(C32:C37) -> 10769000 | D38: =SUM(D32:D37) -> 9790000 | E38: =SUM(E32:E37) -> 2957200 | F38: =E38/D38 -> 0.30206333 | G38: =SUM(G32:G37) -> 0
A39: 2016. 3 | B39: 란쌍미디어 Lanxang Media | C39: 1650000 | D39: 1650000 | E39: 630000 | F39: =E39/D39 -> 0.38181818
B40: 재능인쇄 | C40: 2772000 | D40: 2520000 | E40: 1229000 | F40: =E40/D40 -> 0.48769841
B41: 프린피아 문발공장-임경영대리 | C41: 1100000 | D41: 1000000 | E41: 372000 | F41: =E41/D41 -> 0.372
B42: 교학사 | C42: 5500000 | D42: 5000000 | E42: 2776000 | F42: =E42/D42 -> 0.5552
C43: =SUM(C39:C42) -> 11022000 | D43: =SUM(D39:D42) -> 10170000 | E43: =SUM(E39:E42) -> 5007000 | F43: =E43/D43 -> 0.49233038 | G43: =SUM(G39:G42) -> 0
A44: 2016. 4 | B44: 재능인쇄 | C44: 660000 | D44: 600000 | E44: 496000 | F44: =E44/D44 -> 0.82666667
B45: 신흥피앤피 | C45: 5500000 | D45: 5000000 | E45: 1990000 | F45: =E45/D45 -> 0.398
B46: 교학사 | C46: 418000 | D46: 380000 | E46: 205120 | F46: =E46/D46 -> 0.53978947
B47: 프린피아 주안 -임경영 대리 | C47: 17710000 | D47: 16100000 | E47: 3642500 | F47: =E47/D47 -> 0.22624224
C48: =SUM(C44:C47) -> 24288000 | D48: =SUM(D44:D47) -> 22080000 | E48: =SUM(E44:E47) -> 6333620 | F48: =E48/D48 -> 0.28684873 | G48: =SUM(G44:G47) -> 0
A49: 2016. 5 | B49: 재능인쇄 | C49: 2200000 | D49: 2000000 | E49: 952000 | F49: =E49/D49 -> 0.476
B50: 신흥피앤피 | C50: 1848000 | D50: 1680000 | E50: 840000 | F50: =E50/D50 -> 0.5
B51: 교학사 | C51: 418000 | D51: 380000 | E51: 205120 | F51: =E51/D51 -> 0.53978947
B52: 보진재 | C52: 3905000 | D52: 3550000 | E52: 990000 | F52: =E52/D52 -> 0.27887324
C53: =SUM(C49:C52) -> 8371000 | D53: =SUM(D49:D52) -> 7610000 | E53: =SUM(E49:E52) -> 2987120 | F53: =E53/D53 -> 0.39252562 | G53: =SUM(G49:G52) -> 0
A54: 2016. 6 | B54: 신흥피앤피 | C54: 4730000 | D54: 4300000 | E54: 1300000 | F54: =E54/D54 -> 0.30232558
B55: 보진재 | C55: 594000 | D55: 540000 | E55: 312000 | F55: =E55/D55 -> 0.57777778
B56: 교학사 | C56: 2596000 | D56: 2360000 | E56: 2185120 | F56: =E56/D56 -> 0.92589831
B57: 프린피아 주안 -임경영 대리 | C57: 2475000 | D57: 2250000 | E57: 910000 | F57: =E57/D57 -> 0.40444444
C58: =SUM(C54:C57) -> 10395000 | D58: =SUM(D54:D57) -> 9450000 | E58: =SUM(E54:E57) -> 4707120 | F58: =E58/D58 -> 0.49810794 | G58: =SUM(G54:G57) -> 0
A59: 2016. 7 | B59: 프린피아 문발공장-임경영대리 | C59: 1100000 | D59: 1000000 | E59: 470000 | F59: =E59/D59 -> 0.47
B60: 프린피아 주안 -임경영 대리 | C60: 2090000 | D60: 1900000 | E60: 912500 | F60: =E60/D60 -> 0.48026316
B61: 매일경제(MBN) | C61: 7590000 | D61: 6900000 | E61: 900000 | F61: =E61/D61 -> 0.13043478
C62: =SUM(C59:C61) -> 10780000 | D62: =SUM(D59:D61) -> 9800000 | E62: =SUM(E59:E61) -> 2282500 | F62: =E62/D62 -> 0.23290816 | G62: =SUM(G59:G61) -> 0
A63: 2016. 8 | B63: 신흥피앤피 | C63: 2970000 | D63: 2700000 | E63: 938000 | F63: =E63/D63 -> 0.34740741
B64: 미래엔 | C64: 9570000 | D64: 8700000 | E64: 3090000 | F64: =E64/D64 -> 0.35517241
B65: 재능인쇄 | C65: 8360000 | D65: 7600000 | E65: 1620000 | F65: =E65/D65 -> 0.21315789
B66: 매일경제(MBN) | C66: 24926000 | D66: 22660000 | E66: 6081000 | F66: =E66/D66 -> 0.26835834
B67: 프린피아 주안 -임경영 대리 | C67: 2651000 | D67: 2410000 | E67: 1705500 | F67: =E67/D67 -> 0.70767635
B68: 매일경제(MBN) | C68: 1650000 | D68: 1500000 | E68: 500000 | F68: =E68/D68 -> 0.33333333
B69: 교학사 | C69: 1870000 | D69: 1700000 | E69: 1170000 | F69: =E69/D69 -> 0.68823529
B70: 교학사 | C70: 1738000 | D70: 1580000 | E70: 1204000 | F70: =E70/D70 -> 0.76202532
C71: =SUM(C63:C70) -> 53735000 | D71: =SUM(D63:D70) -> 48850000 | E71: =SUM(E63:E70) -> 16308500 | F71: =E71/D71 -> 0.33384852 | G71: =SUM(G63:G70) -> 0
A72: 2016. 9 | B72: 재능인쇄 | C72: 22000000 | D72: 20000000 | E72: 7000000 | F72: =E72/D72 -> 0.35
B73: 보진재 | C73: 7040000 | D73: 6400000 | E73: 3292000 | F73: =E73/D73 -> 0.514375
B74: 매일경제(MBN) | C74: 1650000 | D74: 1500000 | E74: 450000 | F74: =E74/D74 -> 0.3
B75: 매일경제(MBN) | C75: 6600000 | D75: 6000000 | E75: 2000000 | F75: =E75/D75 -> 0.33333333
B76: 교학사 | C76: 2191200 | D76: 1992000 | E76: 1352000 | F76: =E76/D76 -> 0.67871486
B77: 프린피아 문발 | C77: 3272500 | D77: 2975000 | E77: 883000 | F77: =E77/D77 -> 0.29680672
B78: 프린피아 주안 | C78: 4807000 | D78: 4370000 | E78: 2003000 | F78: =E78/D78 -> 0.4583524
C79: =SUM(C72:C78) -> 47560700 | D79: =SUM(D72:D78) -> 43237000 | E79: =SUM(E72:E78) -> 16980000 | F79: =E79/D79 -> 0.3927192 | G79: =SUM(G72:G78) -> 0
A80: 2016. 10 | B80: 신흥피앤피 | C80: 3080000 | D80: 2800000 | E80: 1269647 | F80: =E80/D80 -> 0.45344534
B81: 프린피아 문발 | C81: 990000 | D81: 900000 | E81: 459440 | F81: =E81/D81 -> 0.51048889
B82: 프린피아 주안 | C82: 990000 | D82: 900000 | E82: 442500 | F82: =E82/D82 -> 0.49166667
C83: =SUM(C80:C82) -> 5060000 | D83: =SUM(D80:D82) -> 4600000 | E83: =SUM(E80:E82) -> 2171587 | F83: =E83/D83 -> 0.47208412 | G83: =SUM(G80:G82) -> 0
A84: 2016. 11 | B84: 미래엔 | C84: 6512000 | D84: 5920000 | E84: 2562576.4 | F84: =E84/D84 -> 0.43286763
B85: 신흥피앤피 | C85: 1386000 | D85: 1260000 | E85: 600000 | F85: =E85/D85 -> 0.47619048
B86: 교학사 | C86: 418000 | D86: 380000 | E86: 205120 | F86: =E86/D86 -> 0.53978947
B87: 프린피아 주안 | C87: 990000 | D87: 900000 | E87: 442500 | F87: =E87/D87 -> 0.49166667
C88: =SUM(C84:C87) -> 9306000 | D88: =SUM(D84:D87) -> 8460000 | E88: =SUM(E84:E87) -> 3810196.4 | F88: =E88/D88 -> 0.45037782 | G88: =SUM(G84:G87) -> 0
A89: 2016. 12 | B89: 프린피아 문발 | C89: 12100000 | D89: 11000000 | E89: 5040000 | F89: =E89/D89 -> 0.45818182
B90: 매일경제(MBN) | C90: 9685500 | D90: 8805000 | E90: 1755000 | F90: =E90/D90 -> 0.19931857
B91: 매일신문사(대구) | C91: 5450500 | D91: 4955000 | E91: 1238000 | F91: =E91/D91 -> 0.24984864
C92: =SUM(C89:C91) -> 27236000 | D92: =SUM(D89:D91) -> 24760000 | E92: =SUM(E89:E91) -> 8033000 | F92: =E92/D92 -> 0.32443457 | G92: =SUM(G89:G91) -> 0
A93: 2017. 1 | B93: 삼화인쇄 | C93: 2035000 | D93: 1850000 | E93: 935000 | F93: =E93/D93 -> 0.50540541
B94: 재능인쇄 | C94: 5940000 | D94: 5400000 | E94: 2463000 | F94: =E94/D94 -> 0.45611111
B95: 교학사 | C95: 836000 | D95: 760000 | E95: 410240 | F95: =E95/D95 -> 0.53978947
B96: 프린피아 주안 -임경영 대리 | C96: 990000 | D96: 900000 | E96: 442500 | F96: =E96/D96 -> 0.49166667
B97: 17,1 | C97: =SUM(C93:C96) -> 9801000 | D97: =SUM(D93:D96) -> 8910000 | E97: =SUM(E93:E96) -> 4250740 | F97: =E97/D97 -> 0.4770752 | G97: =SUM(G93:G96) -> 0
A98: 2017. 2 | B98: 미래엔 | C98: 11440000 | D98: 10400000 | E98: 5320000 | F98: =E98/D98 -> 0.51153846
B99: 한국경제신문 | C99: 1958000 | D99: 1780000 | E99: 896000 | F99: =E99/D99 -> 0.50337079
B100: 재능인쇄 | C100: 550000 | D100: 500000 | E100: 318000 | F100: =E100/D100 -> 0.636
...

Sheet 서비스
A1: Month | B1: Customer | C1: Sales (VAT 포함) | D1: Sales (VAT 제외) | E1: CM | F1: CM % | G1: Commission 2% | H1: 입금 내역 | I1: 입금일
A2: 2015. 11 | B2: 교학사 | C2: 275000 | D2: 250000 | E2: 250000 | F2: =E2/D2 -> 1
B3: 한국하이델베르그 | C3: 2640000 | D3: 2400000 | E3: 1200000 | F3: =E3/D3 -> 0.5
C4: =SUM(C2:C3) -> 2915000 | D4: =SUM(D2:D3) -> 2650000 | E4: =SUM(E2:E3) -> 1450000 | F4: =E4/D4 -> 0.54716981 | G4: =SUM(G2:G3) -> 0
A5: 2015. 12 | B5: 프린피아 문발공장-임경영대리 | C5: 409200 | D5: 372000 | E5: 102000 | F5: =E5/D5 -> 0.27419355
B6: 프린피아 파주- 임경영대리 | C6: 464200 | D6: 422000 | E6: 150000 | F6: =E6/D6 -> 0.35545024
B7: 신흥피앤피 | C7: 165000 | D7: 150000 | E7: 150000 | F7: =E7/D7 -> 1
B8: 팩컴 AAP | C8: 275000 | D8: 250000 | E8: 250000 | F8: =E8/D8 -> 1
B9: 한국하이델베르그 | C9: 880000 | D9: 800000 | E9: 320000 | F9: =E9/D9 -> 0.4
C10: =SUM(C5:C9) -> 2193400 | D10: =SUM(D5:D9) -> 1994000 | E10: =SUM(E5:E9) -> 972000 | F10: =E10/D10 -> 0.48746239 | G10: =SUM(G5:G9) -> 0
A11: 2016. 1 | B11: 신흥피앤피 | C11: 550000 | D11: 500000 | E11: 300000 | F11: =E11/D11 -> 0.6
C12: =SUM(C11:C11) -> 550000 | D12: =SUM(D11:D11) -> 500000 | E12: =SUM(E11:E11) -> 300000 | F12: =E12/D12 -> 0.6 | G12: =SUM(G11:G11) -> 0
A13: 2016. 3 | B13: 삼화인쇄 | C13: 1108800 | D13: 1008000 | E13: 300000 | F13: =E13/D13 -> 0.29761905
B14: 팩컴 AAP | C14: 605000 | D14: 550000 | E14: 550000 | F14: =E14/D14 -> 1
B15: 아이앤피 | C15: 385000 | D15: 350000 | E15: 350000 | F15: =E15/D15 -> 1
B16: 프린피아 문발공장-임경영대리 | C16: 165000 | D16: 150000 | E16: 150000 | F16: =E16/D16 -> 1
B17: ㈜ 대흥 | C17: 165000 | D17: 150000 | E17: 150000 | F17: =E17/D17 -> 1
C18: =SUM(C13:C17) -> 2428800 | D18: =SUM(D13:D17) -> 2208000 | E18: =SUM(E13:E17) -> 1500000 | F18: =E18/D18 -> 0.67934783 | G18: =SUM(G13:G17) -> 0
A19: 2016. 4 | B19: HKR (재능인쇄 서비스 비용) | C19: -2095500 | D19: -1905000 | E19: -1905000 | F19: =E19/D19 -> 1 | G19: * HKR 청구금액 for 재능인쇄 M600 서비스(이상훈 이사)
B20: 재능인쇄 | C20: 1375000 | D20: 1250000 | E20: 1250000 | F20: =E20/D20 -> 1 | G20: * GOSS M600 연간 서비스계약 (총 5백만원, 4회 분할) 1회
B21: 재능인쇄 | C21: 55000 | D21: 50000 | E21: 50000 | F21: =E21/D21 -> 1 | G21: * M600 서비스 야간출장비 100,000원을 2회 분할 발행
B22: 재능인쇄 | C22: 55000 | D22: 50000 | E22: 50000 | F22: =E22/D22 -> 1 | G22: * M600 서비스 야간출장비 100,000원을 2회 분할 발행
B23: 교학사 | C23: 605000 | D23: 550000 | E23: 550000 | F23: =E23/D23 -> 1
B24: 프린피아 문발공장-임경영대리 | C24: 1210000 | D24: 1100000 | E24: 1100000 | F24: =E24/D24 -> 1
C25: =SUM(C19:C24) -> 1204500 | D25: =SUM(D19:D24) -> 1095000 | E25: =SUM(E19:E24) -> 1095000 | F25: =E25/D25 -> 1 | G25: =SUM(G19:G24) -> 0
A26: 2016. 5 | B26: 프린피아 문발공장-임경영대리 | C26: 275000 | D26: 250000 | E26: 250000 | F26: =E26/D26 -> 1
C27: =SUM(C26:C26) -> 275000 | D27: =SUM(D26:D26) -> 250000 | E27: =SUM(E26:E26) -> 250000 | F27: =E27/D27 -> 1 | G27: =SUM(G26:G26) -> 0
A28: 2016. 6 | B28: 재능인쇄 | C28: 1375000 | D28: 1250000 | E28: 1250000 | F28: =E28/D28 -> 1 | G28: * GOSS M600 연간 서비스계약 (총 5백만원, 4회 분할) 2회
C29: =SUM(C28:C28) -> 1375000 | D29: =SUM(D28:D28) -> 1250000 | E29: =SUM(E28:E28) -> 1250000 | F29: =E29/D29 -> 1 | G29: =SUM(G28:G28) -> 0
A30: 2016. 8 | B30: 삼화인쇄 | C30: 959200 | D30: 872000 | E30: 0 | F30: =E30/D30 -> 0 | G30: * GOSS 본사 엔지니어 서비스 비용
B31: 재능인쇄 | C31: 1375000 | D31: 1250000 | E31: 1250000 | F31: =E31/D31 -> 1 | G31: * GOSS M600 연간 서비스계약 (총 5백만원, 4회 분할) 3회
B32: 교학사 | C32: 1992100 | D32: 1811000 | E32: 0 | F32: =E32/D32 -> 0 | G32: * GOSS 본사 엔지니어 서비스 비용
B33: 프린피아 주안 -임경영 대리 | C33: 706200 | D33: 642000 | E33: 0 | F33: =E33/D33 -> 0 | G33: * GOSS 본사 엔지니어 서비스 비용
C34: =SUM(C30:C33) -> 5032500 | D34: =SUM(D30:D33) -> 4575000 | E34: =SUM(E30:E33) -> 1250000 | F34: =E34/D34 -> 0.27322404 | G34: =SUM(G30:G33) -> 0
A35: 2016. 10 | B35: 재능인쇄 | C35: 1375000 | D35: 1250000 | E35: 1250000 | F35: =E35/D35 -> 1 | G35: * GOSS M600 연간 서비스계약 (총 5백만원, 4회 분할) 4회
C36: =SUM(C35:C35) -> 1375000 | D36: =SUM(D35:D35) -> 1250000 | E36: =SUM(E35:E35) -> 1250000 | F36: =E36/D36 -> 1 | G36: =SUM(G35:G35) -> 0
A37: 2016. 12 | B37: 보진재 | C37: 275000 | D37: 250000 | E37: 250000 | F37: =E37/D37 -> 1
B38: 신흥피앤피 | C38: 242000 | D38: 220000 | E38: 220000 | F38: =E38/D38 -> 1
C39: =SUM(C37:C38) -> 517000 | D39: =SUM(D37:D38) -> 470000 | E39: =SUM(E37:E38) -> 470000 | F39: =E39/D39 -> 1 | G39: =SUM(G37:G38) -> 0
A40: 2017. 1 | B40: 보진재 | C40: 165000 | D40: 150000 | E40: 150000 | F40: =E40/D40 -> 1
B41: 17,1 | C41: =SUM(C40:C40) -> 165000 | D41: =SUM(D40:D40) -> 150000 | E41: =SUM(E40:E40) -> 150000 | F41: =E41/D41 -> 1 | G41: =SUM(G40:G40) -> 0
A42: 2017. 2 | B42: 프린피아 문발공장-임경영대리 | C42: 7700000 | D42: 7000000 | E42: 7000000 | F42: =E42/D42 -> 1
B43: 프린피아 주안 -임경영 대리 | C43: 275000 | D43: 250000 | E43: 250000 | F43: =E43/D43 -> 1
C44: =SUM(C42:C43) -> 7975000 | D44: =SUM(D42:D43) -> 7250000 | E44: =SUM(E42:E43) -> 7250000 | F44: =E44/D44 -> 1 | G44: =SUM(G42:G43) -> 0
A45: ,
A46: 2017. 4 | B46: 재능인쇄 | C46: 1375000 | D46: 1250000 | E46: 1250000 | F46: =E46/D46 -> 1 | G46: *GOSS M600 연간 서비스계약 (총 5백만원, 4회 분할) 1회
B47: 보진재 | C47: 165000 | D47: 150000 | E47: 150000 | F47: =E47/D47 -> 1
B48: 프린피아 주안 -임경영 대리 | C48: 275000 | D48: 250000 | E48: 250000 | F48: =E48/D48 -> 1
C49: =SUM(C46:C48) -> 1815000 | D49: =SUM(D46:D48) -> 1650000 | E49: =SUM(E46:E48) -> 1650000 | F49: =E49/D49 -> 1 | G49: =SUM(G46:G48) -> 0
A50: ,
A51: 2017. 6 | B51: 프린피아 주안 | C51: =SUMIFS(INDIRECT("Report!F58:F120"),INDIRECT("Report!B58:B120"),B51,INDIRECT("report!H58:H120"), "Service") -> 275000 | D51: 250000 | E51: =SUMIFS(INDIRECT("Report!J58:J120"),INDIRECT("Report!B58:B120"),B51,INDIRECT("report!H58:H120"), "Service") -> 250000 | F51: =E51/D51 -> 1
B52: 신흥피앤피 | C52: =SUMIFS(INDIRECT("Report!F58:F120"),INDIRECT("Report!B58:B120"),B52,INDIRECT("report!H58:H120"), "Service") -> 330000 | D52: =(C52/11*10) -> 300000 | E52: =SUMIFS(INDIRECT("Report!J58:J120"),INDIRECT("Report!B58:B120"),B52,INDIRECT("report!H58:H120"), "Service") -> 300000 | F52: =E52/D52 -> 1
B53: 재능 | C53: =SUMIFS(INDIRECT("Report!F58:F120"),INDIRECT("Report!B58:B120"),B53,INDIRECT("report!H58:H120"), "Service") -> 1375000 | D53: =(C53/11*10) -> 1250000 | E53: =SUMIFS(INDIRECT("Report!J58:J120"),INDIRECT("Report!B58:B120"),B53,INDIRECT("report!H58:H120"), "Service") -> 1250000 | F53: =E53/D53 -> 1 | G53: *GOSS M600 연간 서비스계약 (총 5백만원, 4회 분할) 2회
C54: =SUM(C51:C53) -> 1980000 | D54: =SUM(D51:D53) -> 1800000 | E54: =SUM(E51:E53) -> 1800000 | F54: =E54/D54 -> 1 | G54: =SUM(G48:G51) -> 0
A55: ,
A56: 2017. 8 | B56: 교학사 | C56: =SUMIFS(INDIRECT("Report!F100:F1000"),INDIRECT("Report!B100:B1000"),B56,INDIRECT("report!H100:H1000"),"Service",INDIRECT("Report!L100:L1000"),"17.8") -> 5665000 | D56: =(C56/11*10) -> 5150000 | E56: =D56 -> 5150000
B57: 프린피아 문발 | C57: =SUMIFS(INDIRECT("Report!F100:F1000"),INDIRECT("Report!B100:B1000"),B57,INDIRECT("report!H100:H1000"),"Service",INDIRECT("Report!L100:L1000"),"17.8") -> 4002900 | D57: =(C57/11*10) -> 3639000 | E57: =D57 -> 3639000
B58: 프린피아 주안 | C58: =SUMIFS(INDIRECT("Report!F100:F1000"),INDIRECT("Report!B100:B1000"),B58,INDIRECT("report!H100:H1000"),"Service",INDIRECT("Report!L100:L1000"),"17.8") -> 13242900 | D58: =(C58/11*10) -> 12039000 | E58: =D58 -> 12039000
B59: 재능 | C59: =SUMIFS(INDIRECT("Report!F100:F1000"),INDIRECT("Report!B100:B1000"),B59,INDIRECT("report!H100:H1000"),"Service",INDIRECT("Report!L100:L1000"),"17.8")-1375000 -> 2241800 | D59: =(C59/11*10) -> 2038000 | E59: =D59 -> 2038000
B60: 삼화인쇄 | C60: =SUMIFS(INDIRECT("Report!F100:F1000"),INDIRECT("Report!B100:B1000"),B60,INDIRECT("report!H100:H1000"),"Service",INDIRECT("Report!L100:L1000"),"17.8") -> 2376000 | D60: =(C60/11*10) -> 2160000 | E60: =D60 -> 2160000
B61: 보진재 | C61: =SUMIFS(INDIRECT("Report!F100:F1000"),INDIRECT("Report!B100:B1000"),B61,INDIRECT("report!H100:H1000"),"Service",INDIRECT("Report!L100:L1000"),"17.8") -> 275000 | D61: =(C61/11*10) -> 250000 | E61: =D61 -> 250000
B62: 재능 | C62: 1375000 | D62: =(C62/11*10) -> 1250000 | E62: =D62 -> 1250000 | G62: *GOSS M600 연간 서비스계약 (총 5백만원, 4회 분할) 3회
A63: , | C63: =SUM(C56:C62) -> 29178600 | D63: =SUM(D56:D62) -> 26526000 | E63: =SUM(E56:E62) -> 26526000 | F63: =E63/D63 -> 1 | G63: =SUM(G58:G60) -> 0
A64: 2017. 9 | B64: 재능 | C64: =SUMIFS(INDIRECT("Report!F100:F1000"),INDIRECT("Report!B100:B1000"),B64,INDIRECT("report!H100:H1000"),"Service",INDIRECT("Report!L100:L1000"),"17.9") -> 2420000 | D64: =(C64/11*10) -> 2200000 | E64: =D64 -> 2200000
B65: 보진재 | C65: =SUMIFS(INDIRECT("Report!F100:F1000"),INDIRECT("Report!B100:B1000"),B65,INDIRECT("report!H100:H1000"),"Service",INDIRECT("Report!L100:L1000"),"17.9") -> 165000 | D65: =(C65/11*10) -> 150000 | E65: =D65 -> 150000
A66: , | C66: =SUM(C64:C65) -> 2585000 | D66: =SUM(D64:D65) -> 2350000 | E66: =SUM(E64:E65) -> 2350000 | F66: =E66/D66 -> 1 | G66: =SUM(G61:G63) -> 0
A67: 2017.1 | B67: 재능 | C67: 1375000 | D67: =(C67/11*10) -> 1250000 | E67: =D67 -> 1250000 | G67: *GOSS M600 연간 서비스계약 (총 5백만원, 4회 분할) 4회
A68: , | C68: =SUM(C67) -> 1375000 | D68: =SUM(D67) -> 1250000 | E68: =SUM(E67) -> 1250000 | F68: =E68/D68 -> 1 | G68: =SUM(G63:G65) -> 0
A69: 2017.11 | B69: 교학사 | C69: =SUMIFS(INDIRECT("Report!F100:F1000"),INDIRECT("Report!B100:B1000"),B69,INDIRECT("report!H100:H1000"),"Service",INDIRECT("Report!L100:L1000"),"17.11") -> 1848000 | D69: =(C69/11*10) -> 1680000 | E69: =D69 -> 1680000
B70: 프린피아 문발 | C70: =SUMIFS(INDIRECT("Report!F100:F1000"),INDIRECT("Report!B100:B1000"),B70,INDIRECT("report!H100:H1000"),"Service",INDIRECT("Report!L100:L1000"),"17.11") -> 9515000 | D70: =(C70/11*10) -> 8650000 | E70: 2000000
B71: 프린피아 주안 | C71: =SUMIFS(INDIRECT("Report!F100:F1000"),INDIRECT("Report!B100:B1000"),B71,INDIRECT("report!H100:H1000"),"Service",INDIRECT("Report!L100:L1000"),"17.11") -> 484000 | D71: =(C71/11*10) -> 440000
A72: , | C72: =SUM(C69:C71) -> 11847000 | D72: =SUM(D69:D71) -> 10770000 | E72: =SUM(E69:E71) -> 3680000 | F72: =E72/D72 -> 0.34168988 | G72: =SUM(G67:G69) -> 0
A73: 2017.12 | B73: 프린피아 주안 | C73: =SUMIFS(INDIRECT("Report!F100:F1000"),INDIRECT("Report!B100:B1000"),B73,INDIRECT("report!H100:H1000"),"Service",INDIRECT("Report!L100:L1000"),"17.12") -> 275000 | D73: =(C73/11*10) -> 250000 | E73: =D73 -> 250000
A74: , | C74: =SUM(C73) -> 275000 | D74: =SUM(D73) -> 250000 | E74: =SUM(E73) -> 250000 | F74: =E74/D74 -> 1 | G74: =SUM(G69:G71) -> 0
A75: 2018.1 | B75: 삼화인쇄 | C75: =SUMIFS(INDIRECT("Report!F100:F1000"),INDIRECT("Report!B100:B1000"),B75,INDIRECT("report!H100:H1000"),"Service",INDIRECT("Report!L100:L1000"),"18.1") -> 275000 | D75: =(C75/11*10) -> 250000 | E75: =D75 -> 250000
B76: 프린피아 문발 | C76: =SUMIFS(INDIRECT("Report!F100:F1000"),INDIRECT("Report!B100:B1000"),B76,INDIRECT("report!H100:H1000"),"Service",INDIRECT("Report!L100:L1000"),"18.1") -> 165000 | D76: =(C76/11*10) -> 150000 | E76: =D76 -> 150000
B77: 재능 | C77: =SUMIFS(INDIRECT("Report!F100:F1000"),INDIRECT("Report!B100:B1000"),B77,INDIRECT("report!H100:H1000"),"Service",INDIRECT("Report!L100:L1000"),"18.1") -> 0 | D77: =(C77/11*10) -> 0 | E77: =D77 -> 0 | G77: *서비스 시간 9시간 공제
C78: =SUM(C75:C77) -> 440000 | D78: =SUM(D75:D77) -> 400000 | E78: =SUM(E75:E77) -> 400000 | F78: =E78/D78 -> 1 | G78: =SUM(G73:G75) -> 0
A79: 2018.2 | B79: 보진재 | C79: =SUMIFS(INDIRECT("Report!F100:F1000"),INDIRECT("Report!B100:B1000"),B79,INDIRECT("report!H100:H1000"),"Service",INDIRECT("Report!L100:L1000"),"18.2") -> 605000 | D79: =(C79/11*10) -> 550000 | E79: =D79 -> 550000
B80: 재능 | C80: =SUMIFS(INDIRECT("Report!F100:F1000"),INDIRECT("Report!B100:B1000"),B80,INDIRECT("report!H100:H1000"),"Service",INDIRECT("Report!L100:L1000"),"18.1") -> 0 | D80: =(C80/11*10) -> 0 | E80: =D80 -> 0 | G80: *서비스 시간 4시간 공제
A81: , | C81: =SUM(C79:C80) -> 605000 | D81: =SUM(D79:D80) -> 550000 | E81: =SUM(E79:E80) -> 550000 | F81: =E81/D81 -> 1 | G81: =SUM(G76:G78) -> 0
A82: 2018.3
A83: , | C83: =SUM(C82) -> 0 | D83: =SUM(D82) -> 0 | E83: =SUM(E82) -> 0 | F83: =E83/D83 -> #DIV/0! | G83: =SUM(G78:G80) -> 0
A84: 2018.4 | B84: 재능 | C84: =SUMIFS(INDIRECT("Report!F100:F1000"),INDIRECT("Report!B100:B1000"),B84,INDIRECT("report!H100:H1000"),"Service",INDIRECT("Report!L100:L1000"),"18.4") -> 1375000 | D84: =(C84/11*10) -> 1250000 | E84: =D84 -> 1250000 | G84: *GOSS M600 연간 서비스계약 (총 5백만원, 4회 분할) 1회
C85: =SUM(C84) -> 1375000 | D85: =SUM(D84) -> 1250000 | E85: =SUM(E84) -> 1250000 | F85: =E85/D85 -> 1 | G85: =SUM(G80:G82) -> 0
A86: ,
A87: 2018.6 | B87: 재능 | C87: =SUMIFS(INDIRECT("Report!F100:F1000"),INDIRECT("Report!B100:B1000"),B87,INDIRECT("report!H100:H1000"),"Service",INDIRECT("Report!L100:L1000"),"18.4") -> 1375000 | D87: =(C87/11*10) -> 1250000 | E87: =D87 -> 1250000 | G87: *GOSS M600 연간 서비스계약 (총 5백만원, 4회 분할) 2회
B88: 하이델베르그 | C88: =SUMIFS(INDIRECT("Report!F100:F10000"),INDIRECT("Report!B100:B10000"),B88,INDIRECT("report!H100:H10000"),"Service",INDIRECT("Report!L100:L10000"),"18.6") -> 3238900.5 | D88: =(C88/11*10) -> 2944455 | E88: 2400000 | G88: 베트남 서비스 건 항공료 제
C89: =SUM(C87:C88) -> 4613900.5 | D89: =SUM(D87:D88) -> 4194455 | E89: =SUM(E87:E88) -> 3650000 | F89: =E89/D89 -> 0.87019649 | G89: =SUM(G83:G85) -> 0
A90: ,
A91: 2018.8 | B91: 재능 | C91: =SUMIFS(INDIRECT("Report!F100:F1000"),INDIRECT("Report!B100:B1000"),B91,INDIRECT("report!H100:H1000"),"Service",INDIRECT("Report!L100:L1000"),"18.4") -> 1375000 | D91: =(C91/11*10) -> 1250000 | E91: =D91 -> 1250000 | G91: *GOSS M600 연간 서비스계약 (총 5백만원, 4회 분할) 3회
B92: 교학사 | C92: =SUMIFS(INDIRECT("Report!F100:F10000"),INDIRECT("Report!B100:B10000"),B92,INDIRECT("report!H100:H10000"),"Service",INDIRECT("Report!L100:L10000"),"18.8") -> 8800000 | D92: =(C92/11*10) -> 8000000 | E92: =Report!J1224 -> 1161211.1 | G92: 드라이어 수리비
B93: 재능 | C93: 5500000 | D93: 5000000 | E93: 500000 | G93: M600 실린더 수리
C94: =SUM(C91:C93) -> 15675000 | D94: =SUM(D91:D93) -> 14250000 | E94: =SUM(E91:E93) -> 2911211.1 | F94: =E94/D94 -> 0.20429551 | G94: =SUM(G87:G89) -> 0
A95: ,
A96: 2018.1 | B96: 재능 | C96: =SUMIFS(INDIRECT("Report!F100:F1000"),INDIRECT("Report!B100:B1000"),B96,INDIRECT("report!H100:H1000"),"Service",INDIRECT("Report!L100:L1000"),"18.4") -> 1375000 | D96: =(C96/11*10) -> 1250000 | E96: =D96 -> 1250000 | G96: *GOSS M600 연간 서비스계약 (총 5백만원, 4회 분할) 4회
B97: 매일경제 | C97: =SUMIFS(INDIRECT("Report!F100:F10000"),INDIRECT("Report!B100:B10000"),B97,INDIRECT("report!H100:H10000"),"Service",INDIRECT("Report!L100:L10000"),"18,10") -> 1708095.4 | D97: =(C97/11*10) -> 1552814 | E97: 0
B98: 보진재 | C98: =SUMIFS(INDIRECT("Report!F100:F10000"),INDIRECT("Report!B100:B10000"),B98,INDIRECT("report!H100:H10000"),"Service",INDIRECT("Report!L100:L10000"),"18,10") -> 1650000 | D98: =(C98/11*10) -> 1500000 | E98: =Report!J1378 -> 292261.18 | H98: 초록색 총 합산한게 총 마진(마이크 드라이어 방문)
B99: 프린피아 파주출판단지 | C99: =SUMIFS(INDIRECT("Report!F100:F10000"),INDIRECT("Report!B100:B10000"),B99,INDIRECT("report!H100:H10000"),"Service",INDIRECT("Report!L100:L10000"),"18,10") -> 242000 | D99: =(C99/11*10) -> 220000
C100: =SUM(C96:C99) -> 4975095.4 | D100: =SUM(D96:D99) -> 4522814 | E100: =SUM(E96:E99) -> 1542261.2 | F100: =E100/D100 -> 0.34099593 | G100: =SUM(G92:G94) -> 0
...

Sheet 2017
A1: Sales
B2: 2017
A3: Product | B3: 1 | C3: 2 | D3: 3 | E3: 4 | F3: 5 | G3: 6 | H3: 7 | I3: 8 | J3: 9 | K3: 10 | L3: 11 | M3: 12 | N3: TOTAL | O3: Portion
A4: Blanket | B4: 12905500 | C4: 9640000 | D4: 13889500 | E4: 14045000 | F4: =SUMIF(INDIRECT("Report!I3:I55"),A4,INDIRECT("Report!G3:G55")) -> 7740000 | G4: =SUMIF(INDIRECT("Report!I58:I119"),A4,INDIRECT("Report!G58:G119")) -> 12827500 | H4: =SUMIF(INDIRECT("Report!I120:I196"),A4,INDIRECT("Report!G120:G196")) -> 9295000 | I4: =SUMIF(INDIRECT("Report!I198:I264"),A4,INDIRECT("Report!G198:G264")) -> 10901000 | J4: =SUMIF(INDIRECT("Report!I266:I342"),A4,INDIRECT("Report!G266:G342")) -> 16287000 | K4: =SUMIF(INDIRECT("Report!I344:I407"),A4,INDIRECT("Report!G344:G407")) -> 4200000 | L4: =SUMIF(INDIRECT("Report!I409:I480"),A4,INDIRECT("Report!G409:G480")) -> 8690000 | M4: =SUMIF(INDIRECT("Report!I482:I565"),A4,INDIRECT("Report!G482:G565")) -> 10125000 | N4: =SUM(B4:M4) -> 130545500 | O4: =N4/$N$17 -> 0.10748405
A5: CTP | B5: 22394000 | C5: 11505000 | D5: 4270000 | E5: 7123000 | F5: =SUMIF(INDIRECT("Report!I3:I55"),A5,INDIRECT("Report!G3:G55")) -> 9358000 | G5: =SUMIF(INDIRECT("Report!I58:I120"),A5,INDIRECT("Report!G58:G120")) -> 8560000 | H5: =SUMIF(INDIRECT("Report!I120:I196"),A5,INDIRECT("Report!G120:G196")) -> 9460000 | I5: =SUMIF(INDIRECT("Report!I198:I264"),A5,INDIRECT("Report!G198:G264")) -> 4456000 | J5: =SUMIF(INDIRECT("Report!I266:I342"),A5,INDIRECT("Report!G266:G342")) -> 5368000 | K5: =SUMIF(INDIRECT("Report!I344:I407"),A5,INDIRECT("Report!G344:G407")) -> 4171000 | L5: =SUMIF(INDIRECT("Report!I409:I480"),A5,INDIRECT("Report!G409:G480")) -> 3147400 | M5: =SUMIF(INDIRECT("Report!I482:I565"),A5,INDIRECT("Report!G482:G565")) -> 4461000 | N5: =SUM(B5:M5) -> 94273400 | O5: =N5/$N$17 -> 0.077619583
A6: Film | B6: 4961000 | C6: 4961000 | D6: 5054000 | E6: 2434000 | F6: =SUMIF(INDIRECT("Report!I3:I55"),A6,INDIRECT("Report!G3:G55")) -> 5054000 | G6: =SUMIF(INDIRECT("Report!I58:I120"),A6,INDIRECT("Report!G58:G120")) -> 2527000 | H6: =SUMIF(INDIRECT("Report!I120:I196"),A6,INDIRECT("Report!G120:G196")) -> 4868000 | I6: =SUMIF(INDIRECT("Report!I198:I264"),A6,INDIRECT("Report!G198:G264")) -> 2434000 | J6: =SUMIF(INDIRECT("Report!I266:I342"),A6,INDIRECT("Report!G266:G342")) -> 2475000 | K6: =SUMIF(INDIRECT("Report!I344:I407"),A6,INDIRECT("Report!G344:G407")) -> 5043000 | L6: =SUMIF(INDIRECT("Report!I409:I480"),A6,INDIRECT("Report!G409:G480")) -> 2527000 | M6: =SUMIF(INDIRECT("Report!I482:I565"),A6,INDIRECT("Report!G482:G565")) -> 7488000 | N6: =SUM(B6:M6) -> 49826000 | O6: =N6/$N$17 -> 0.041024014
A7: Fount | B7: 1790000 | C7: 1665000 | D7: 4037500 | E7: 145000 | F7: =SUMIF(INDIRECT("Report!I3:I55"),A7,INDIRECT("Report!G3:G55")) -> 4037500 | G7: =SUMIF(INDIRECT("Report!I58:I120"),A7,INDIRECT("Report!G58:G120")) -> 2185000 | H7: =SUMIF(INDIRECT("Report!I120:I196"),A7,INDIRECT("Report!G120:G196")) -> 1687500 | I7: =SUMIF(INDIRECT("Report!I198:I264"),A7,INDIRECT("Report!G198:G264")) -> 1175000 | J7: =SUMIF(INDIRECT("Report!I266:I342"),A7,INDIRECT("Report!G266:G342")) -> 4577500 | L7: =SUMIF(INDIRECT("Report!I409:I480"),A7,INDIRECT("Report!G409:G480")) -> 4155000 | M7: =SUMIF(INDIRECT("Report!I482:I565"),A7,INDIRECT("Report!G482:G565")) -> 4717500 | N7: =SUM(B7:M7) -> 30172500 | O7: =N7/$N$17 -> 0.024842393
A8: GOSS | B8: 8910000 | C8: 36207000 | D8: 10970000 | E8: 13000000 | F8: =SUMIF(INDIRECT("Report!H3:H55"),A8,INDIRECT("Report!G3:G55")) -> 9210000 | G8: =SUMIF(INDIRECT("Report!H58:H120"),A8,INDIRECT("Report!G58:G120")) -> 6935000 | H8: =SUMIF(INDIRECT("Report!H120:H196"),A8,INDIRECT("Report!G120:G196")) -> 53520000 | I8: =SUMIF(INDIRECT("Report!H198:H264"),A8,INDIRECT("Report!G198:G264")) -> 18460000 | J8: =SUMIF(INDIRECT("Report!H266:H342"),A8,INDIRECT("Report!G266:G342")) -> 531000 | K8: =SUMIF(INDIRECT("Report!H344:H407"),A8,INDIRECT("Report!G344:G407")) -> 10210000 | L8: =SUMIF(INDIRECT("Report!H409:H480"),A8,INDIRECT("Report!G409:G480")) -> 10029000 | M8: =SUMIF(INDIRECT("Report!H482:H565"),A8,INDIRECT("Report!G482:G565")) -> 8995000 | N8: =SUM(B8:M8) -> 186977000 | O8: =N8/$N$17 -> 0.15394668
A9: Others | B9: 6624000 | C9: 31268000 | D9: 22656000 | E9: 45507000 | F9: =SUMIF(INDIRECT("Report!I3:I55"),A9,INDIRECT("Report!G3:G55")) -> 2890000 | G9: =SUMIF(INDIRECT("Report!I58:I120"),A9,INDIRECT("Report!G58:G120")) -> 8461000 | H9: =SUMIF(INDIRECT("Report!I120:I196"),A9,INDIRECT("Report!G120:G196"))+43000000 -> 49921000 | I9: =SUMIF(INDIRECT("Report!I198:I264"),A9,INDIRECT("Report!G198:G264")) -> 4274000 | J9: =SUMIF(INDIRECT("Report!I266:I342"),A9,INDIRECT("Report!G266:G342")) -> 32592000 | K9: =SUMIF(INDIRECT("Report!I344:I407"),A9,INDIRECT("Report!G344:G407")) -> 3568000 | L9: =SUMIF(INDIRECT("Report!I409:I480"),A9,INDIRECT("Report!G409:G480")) -> 48431904 | M9: =SUMIF(INDIRECT("Report!I482:I565"),A9,INDIRECT("Report!G482:G565")) -> 4922000 | N9: =SUM(B9:M9) -> 261114904 | O9: =N9/$N$17 -> 0.21498779
A10: Roller | B10: 7570000 | C10: 469000 | F10: =SUMIF(INDIRECT("Report!I3:I55"),A10,INDIRECT("Report!G3:G55")) -> 9790000 | G10: =SUMIF(INDIRECT("Report!I58:I120"),A10,INDIRECT("Report!G58:G120")) -> 1660000 | H10: =SUMIF(INDIRECT("Report!I120:I196"),A10,INDIRECT("Report!G120:G196")) -> 3280000 | I10: =SUMIF(INDIRECT("Report!I198:I264"),A10,INDIRECT("Report!G198:G264")) -> 264000 | J10: =SUMIF(INDIRECT("Report!I266:I342"),A10,INDIRECT("Report!G266:G342")) -> 7385000 | K10: =SUMIF(INDIRECT("Report!I344:I407"),A10,INDIRECT("Report!G344:G407")) -> 0 | L10: =SUMIF(INDIRECT("Report!I409:I480"),A10,INDIRECT("Report!G409:G480")) -> 0 | M10: =SUMIF(INDIRECT("Report!I482:I565"),A10,INDIRECT("Report!G482:G565")) -> 7760000 | N10: =SUM(B10:M10) -> 38178000 | O10: =N10/$N$17 -> 0.031433686
A11: Technotrans | B11: 11180000 | C11: 2282000 | D11: 1816000 | E11: 52376840 | F11: =(Technotrans!D130) -> 91842200 | G11: =SUMIF(INDIRECT("Report!h58:h120"),A11,INDIRECT("Report!G58:G120"))+36876560 -> 44676560 | H11: =SUMIF(INDIRECT("Report!H120:H196"),A11,INDIRECT("Report!G120:G196")) -> 580000 | I11: =SUMIF(INDIRECT("Report!H198:H264"),A11,INDIRECT("Report!G198:G264")) -> 5933000 | J11: =SUMIF(INDIRECT("Report!H266:H342"),A11,INDIRECT("Report!G266:G342")) -> 15319000 | K11: =SUMIF(INDIRECT("Report!H344:H407"),A11,INDIRECT("Report!G344:G407")) -> 925000 | L11: =SUMIF(INDIRECT("Report!H409:H480"),A11,INDIRECT("Report!G409:G480")) -> 2380000 | M11: =SUMIF(INDIRECT("Report!H482:H565"),A11,INDIRECT("Report!G482:G565")) -> 2325000 | N11: =SUM(B11:M11) -> 231635600 | O11: =N11/$N$17 -> 0.19071614
A12: Wash | B12: 6410000 | C12: 4106000 | D12: 4595000 | E12: 2689000 | F12: =SUMIF(INDIRECT("Report!I3:I55"),A12,INDIRECT("Report!G3:G55")) -> 5465500 | G12: =SUMIF(INDIRECT("Report!I58:I120"),A12,INDIRECT("Report!G58:G120")) -> 7523000 | H12: =SUMIF(INDIRECT("Report!I120:I196"),A12,INDIRECT("Report!G120:G196")) -> 3732500 | I12: =SUMIF(INDIRECT("Report!I198:I264"),A12,INDIRECT("Report!G198:G264")) -> 4081000 | J12: =SUMIF(INDIRECT("Report!I266:I342"),A12,INDIRECT("Report!G266:G342")) -> 4860000 | K12: =SUMIF(INDIRECT("Report!I344:I407"),A12,INDIRECT("Report!G344:G407")) -> 4779000 | L12: =SUMIF(INDIRECT("Report!I409:I480"),A12,INDIRECT("Report!G409:G480")) -> 6677000 | M12: =SUMIF(INDIRECT("Report!I482:I565"),A12,INDIRECT("Report!G482:G565")) -> 9771000 | N12: =SUM(B12:M12) -> 64689000 | O12: =N12/$N$17 -> 0.053261399
A13: 농도계 | B13: 0 | C13: 0 | D13: 0 | E13: 0 | F13: 0 | G13: 0 | H13: =SUMIF(INDIRECT("Report!I120:I196"),A13,INDIRECT("Report!G120:G196")) -> 0 | I13: 0 | J13: =SUMIF(INDIRECT("Report!I266:I342"),A13,INDIRECT("Report!J266:J342")) -> 0 | K13: =SUMIF(INDIRECT("Report!I344:I407"),A13,INDIRECT("Report!G344:G407")) -> 0 | L13: =SUMIF(INDIRECT("Report!I409:I480"),A13,INDIRECT("Report!G409:G480")) -> 0 | M13: =SUMIF(INDIRECT("Report!I482:I565"),A13,INDIRECT("Report!G482:G565")) -> 0 | N13: =SUM(B13:M13) -> 0 | O13: =N13/$N$17 -> 0
A14: Ink | B14: 0 | C14: 0 | D14: 0 | E14: 0 | F14: =SUMIF(INDIRECT("Report!I3:I55"),A14,INDIRECT("Report!G3:G55")) -> 723000 | G14: =SUMIF(INDIRECT("Report!I58:I120"),A14,INDIRECT("Report!G58:G120")) -> 13358800 | H14: =SUMIF(INDIRECT("Report!I120:I196"),A14,INDIRECT("Report!G120:G196")) -> 13559000 | I14: =SUMIF(INDIRECT("Report!I198:I264"),A14,INDIRECT("Report!G198:G264")) -> 9919000 | J14: =SUMIF(INDIRECT("Report!I266:I342"),A14,INDIRECT("Report!G266:G342")) -> 11371600 | K14: =SUMIF(INDIRECT("Report!I344:I407"),A14,INDIRECT("Report!G344:G407")) -> 9718800 | L14: =SUMIF(INDIRECT("Report!I409:I480"),A14,INDIRECT("Report!G409:G480")) -> 9482800 | M14: =SUMIF(INDIRECT("Report!I482:I565"),A14,INDIRECT("Report!G482:G565")) -> 9436000 | N14: =SUM(B14:M14) -> 77569000 | O14: =N14/$N$17 -> 0.06386609
A15: Service | B15: 150000 | C15: 7250000 | D15: 0 | E15: 1650000 | F15: =SUMIF(INDIRECT("Report!H3:H55"),A15,INDIRECT("Report!F3:F55")) -> 0 | G15: =SUMIF(INDIRECT("Report!h58:h120"),A15,INDIRECT("Report!F58:F120")) -> 1980000 | H15: =SUMIF(INDIRECT("Report!H120:H196"),A15,INDIRECT("Report!G120:G196")) -> 0 | I15: =SUMIF(INDIRECT("Report!H198:H264"),A15,INDIRECT("Report!G198:G264")) -> 17178000 | J15: =SUMIF(INDIRECT("Report!H266:H342"),A15,INDIRECT("Report!G266:G342")) -> 9538000 | K15: =SUMIF(INDIRECT("Report!H344:H407"),A15,INDIRECT("Report!G344:G407")) -> 1250000 | L15: =SUMIF(INDIRECT("Report!H409:H480"),A15,INDIRECT("Report!G409:G480")) -> 10330000 | M15: =SUMIF(INDIRECT("Report!H482:H565"),A15,INDIRECT("Report!G482:G565")) -> 250000 | N15: =SUM(B15:M15) -> 49576000 | O15: =N15/$N$17 -> 0.040818178
A16: Machine | L16: =SUMIF(INDIRECT("Report!I409:I480"),A16,INDIRECT("Report!G409:G480")) -> 240000000 | M16: =SUMIF(INDIRECT("Report!I482:I565"),A16,INDIRECT("Report!G482:G565")) -> 27400000 | N16: =SUM(B16:M16) -> 267400000 | O16: =N16/$N$17 -> 0.2201626
A17: 총합계(+VAT) | B17: =SUM(B4:B16)*1.1 -> 91183950 | C17: =SUM(C4:C16)*1.1 -> 1.202883e+08 | D17: =SUM(D4:D16)*1.1 -> 74016800 | E17: =SUM(E4:E16)*1.1 -> 152866824 | F17: =SUM(F4:F16)*1.1 -> 160721220 | G17: =SUM(G4:G16)*1.1 -> 1.2176325e+08 | H17: =SUM(H4:H16)*1.1 -> 164893300 | I17: =SUM(I4:I16)*1.1 -> 86982500 | ... M17: =SUM(M4:M16)*1.1 -> 1.0741555e+08 | N17: =SUM(N4:N15) -> 1214556904 | O17: =N17/$N$17 -> 1
A19: Margin
B20: 2017 | P20: 품목별
A21: Product | B21: 1 | C21: 2 | D21: 3 | E21: 4 | F21: 5 | G21: 6 | H21: 7 | I21: 8 | J21: 9 | K21: 10 | L21: 11 | M21: 12 | N21: TOTAL | O21: Portion | P21: Margin
A22: Blanket | B22: 3416500 | C22: 2287800 | D22: 3407500 | E22: 3424500 | F22: =SUMIF(INDIRECT("Report!I3:I55"),A22,INDIRECT("Report!J3:J55")) -> 1763500 | G22: =SUMIF(INDIRECT("Report!I58:I119"),A22,INDIRECT("Report!J58:J119")) -> 3290200 | H22: =SUMIF(INDIRECT("Report!I120:I196"),A22,INDIRECT("Report!J120:J196")) -> 2291000 | I22: =SUMIF(INDIRECT("Report!I198:I264"),A22,INDIRECT("Report!J198:J264")) -> 2371500 | J22: =SUMIF(INDIRECT("Report!I266:I342"),A22,INDIRECT("Report!J266:J342")) -> 3492500 | K22: =SUMIF(INDIRECT("Report!I344:I407"),A22,INDIRECT("Report!J344:J407")) -> 836000 | L22: =SUMIF(INDIRECT("Report!I409:I480"),A22,INDIRECT("Report!J409:J480")) -> 1934000 | M22: =SUMIF(INDIRECT("Report!I482:I565"),A22,INDIRECT("Report!J482:J565")) -> 2431800 | N22: =SUM(B22:M22) -> 30946800 | O22: =N22/$N$34 -> 0.069111686 | P22: =N22/N4 -> 0.23705758
A23: CTP | B23: 4546000 | C23: 2474000 | D23: 995000 | E23: 1967000 | F23: =SUMIF(INDIRECT("Report!I3:I55"),A23,INDIRECT("Report!J3:J55")) -> 2980000 | G23: =SUMIF(INDIRECT("Report!I58:I120"),A23,INDIRECT("Report!J58:J120")) -> 2730000 | H23: =SUMIF(INDIRECT("Report!I120:I196"),A23,INDIRECT("Report!J120:J196")) -> 3020000 | I23: =SUMIF(INDIRECT("Report!I198:I264"),A23,INDIRECT("Report!J198:J264")) -> 1085000 | J23: =SUMIF(INDIRECT("Report!I266:I342"),A23,INDIRECT("Report!J266:J342")) -> 1730000 | K23: =SUMIF(INDIRECT("Report!I344:I407"),A23,INDIRECT("Report!J344:J407")) -> 1355000 | L23: =SUMIF(INDIRECT("Report!I409:I480"),A23,INDIRECT("Report!J409:J480")) -> 758000 | M23: =SUMIF(INDIRECT("Report!I482:I565"),A23,INDIRECT("Report!J482:J565")) -> 1470000 | N23: =SUM(B23:M23) -> 25110000 | O23: =N23/$N$34 -> 0.0560767 | P23: =N23/N5 -> 0.26635297
A24: Film | B24: 1038560 | C24: 1038560 | D24: 1046640 | E24: 477860 | F24: =SUMIF(INDIRECT("Report!I3:I55"),A24,INDIRECT("Report!J3:J55")) -> 1021720 | G24: =SUMIF(INDIRECT("Report!I58:I120"),A24,INDIRECT("Report!J58:J120")) -> 510860 | H24: =SUMIF(INDIRECT("Report!I120:I196"),A24,INDIRECT("Report!J120:J196")) -> 980640 | I24: =SUMIF(INDIRECT("Report!I198:I264"),A24,INDIRECT("Report!J198:J264")) -> 477860 | J24: =SUMIF(INDIRECT("Report!I266:I342"),A24,INDIRECT("Report!J266:J342")) -> 493860 | K24: =SUMIF(INDIRECT("Report!I344:I407"),A24,INDIRECT("Report!J344:J407")) -> 1020720 | L24: =SUMIF(INDIRECT("Report!I409:I480"),A24,INDIRECT("Report!J409:J480")) -> 510860 | M24: =SUMIF(INDIRECT("Report!I482:I565"),A24,INDIRECT("Report!J482:J565")) -> 1499580 | N24: =SUM(B24:M24) -> 10117720 | O24: =N24/$N$34 -> 0.022595315 | P24: =N24/N6 -> 0.20306105
A25: Fount | B25: 922500 | C25: 585000 | D25: 1712500 | E25: 65000 | F25: =SUMIF(INDIRECT("Report!I3:I55"),A25,INDIRECT("Report!J3:J55")) -> 1712500 | G25: =SUMIF(INDIRECT("Report!I58:I120"),A25,INDIRECT("Report!J58:J120")) -> 1117500 | H25: =SUMIF(INDIRECT("Report!I120:I196"),A25,INDIRECT("Report!J120:J196")) -> 487500 | I25: =SUMIF(INDIRECT("Report!I198:I264"),A25,INDIRECT("Report!J198:J264")) -> 612500 | J25: =SUMIF(INDIRECT("Report!I266:I342"),A25,INDIRECT("Report!J266:J342")) -> 1972500 | K25: =SUMIF(INDIRECT("Report!I344:I407"),A25,INDIRECT("Report!J344:J407")) -> 612500 | L25: =SUMIF(INDIRECT("Report!I409:I480"),A25,INDIRECT("Report!J409:J480")) -> 1720000 | M25: =SUMIF(INDIRECT("Report!I482:I565"),A25,INDIRECT("Report!J482:J565")) -> 1882500 | N25: =SUM(B25:M25) -> 13402500 | O25: =N25/$N$34 -> 0.029931023 | P25: =N25/N7 -> 0.44419587
A26: GOSS | B26: 4250740 | C26: 17656413 | D26: 4691140 | E26: 7084000 | F26: =SUMIF(INDIRECT("Report!H3:H55"),A26,INDIRECT("Report!J3:J55")) -> 4024340 | G26: =SUMIF(INDIRECT("Report!h58:h120"),A26,INDIRECT("Report!J58:J120")) -> 6635000 | H26: =SUMIF(INDIRECT("Report!H120:H196"),A26,INDIRECT("Report!J120:J196")) -> 52854000 | I26: =SUMIF(INDIRECT("Report!H198:H264"),A26,INDIRECT("Report!J198:J264")) -> 15160000 | J26: =SUMIF(INDIRECT("Report!H266:H342"),A26,INDIRECT("Report!J266:J342")) -> 531000 | K26: =SUMIF(INDIRECT("Report!H344:H407"),A26,INDIRECT("Report!J344:J407")) -> 7959288.8 | L26: =SUMIF(INDIRECT("Report!H409:H480"),A26,INDIRECT("Report!J409:J480")) -> 7911000 | M26: =SUMIF(INDIRECT("Report!H482:H565"),A26,INDIRECT("Report!J482:J565")) -> 8005000 | N26: =SUM(B26:M26) -> 1.3676192e+08 | O26: =N26/$N$34 -> 0.30542243 | P26: =N26/N8 -> 0.73143714
A27: Others | B27: 2396000 | C27: 12634526 | D27: 5058500 | E27: 10324624 | F27: =SUMIF(INDIRECT("Report!I3:I55"),A27,INDIRECT("Report!J3:J55")) -> 850000 | G27: =SUMIF(INDIRECT("Report!I58:I120"),A27,INDIRECT("Report!J58:J120")) -> 1406200 | H27: =SUMIF(INDIRECT("Report!I120:I196"),A27,INDIRECT("Report!J120:J196"))+9708427 -> 11248027 | I27: =SUMIF(INDIRECT("Report!I198:I264"),A27,INDIRECT("Report!J198:J264")) -> 1198600 | J27: =SUMIF(INDIRECT("Report!I266:I342"),A27,INDIRECT("Report!J266:J342")) -> 1746000 | K27: =SUMIF(INDIRECT("Report!I344:I407"),A27,INDIRECT("Report!J344:J407")) -> 1118000 | L27: =SUMIF(INDIRECT("Report!I409:I480"),A27,INDIRECT("Report!J409:J480"))+SUMIF(INDIRECT("Report!H409:H480"),A27,INDIRECT("Report!J409:J480")) -> 59483344 | M27: =SUMIF(INDIRECT("Report!I482:I565"),A27,INDIRECT("Report!J482:J565")) -> 1405800 | N27: =SUM(B27:M27) -> 1.0886962e+08 | O27: =N27/$N$34 -> 0.24313218 | P27: =N27/N9 -> 0.41694143
A28: Roller | B28: 1860000 | C28: -757000 | F28: =SUMIF(INDIRECT("Report!I3:I55"),A28,INDIRECT("Report!J3:J55")) -> 2482094 | G28: =SUMIF(INDIRECT("Report!I58:I120"),A28,INDIRECT("Report!J58:J120")) -> 200000 | H28: =SUMIF(INDIRECT("Report!I120:I196"),A28,INDIRECT("Report!J120:J196")) -> 500000 | I28: =SUMIF(INDIRECT("Report!I198:I264"),A28,INDIRECT("Report!J198:J264")) -> 84000 | J28: =SUMIF(INDIRECT("Report!I266:I342"),A28,INDIRECT("Report!J266:J342")) -> 255000 | K28: =SUMIF(INDIRECT("Report!I344:I407"),A28,INDIRECT("Report!J344:J407")) -> 0 | L28: =SUMIF(INDIRECT("Report!I409:I480"),A28,INDIRECT("Report!J409:J480")) -> 0 | M28: =SUMIF(INDIRECT("Report!I482:I565"),A28,INDIRECT("Report!J482:J565")) -> 2000000 | N28: =SUM(B28:M28) -> 6624094 | O28: =N28/$N$34 -> 0.014793203 | P28: =N28/N10 -> 0.17350553
A29: Technotrans | B29: 3528562 | C29: 1064898.9 | D29: 742670 | E29: =(Technotrans!E124) -> 6544755.2 | F29: =Technotrans!E130 -> 11831906 | G29: =Technotrans!E138 -> 7551889.7 | H29: =SUMIF(INDIRECT("Report!H120:H196"),A29,INDIRECT("Report!J120:J196")) -> 310468 | I29: =SUMIF(INDIRECT("Report!H198:H264"),A29,INDIRECT("Report!J198:J264")) -> 5326373.5 | J29: =SUMIF(INDIRECT("Report!H266:H342"),A29,INDIRECT("Report!J266:J342")) -> 5748662 | K29: =SUMIF(INDIRECT("Report!H344:H407"),A29,INDIRECT("Report!J344:J407")) -> 812695 | L29: =SUMIF(INDIRECT("Report!H409:H480"),A29,INDIRECT("Report!J409:J480")) -> 2380000 | M29: =SUMIF(INDIRECT("Report!H482:H565"),A29,INDIRECT("Report!J482:J565")) -> 2325000 | N29: =SUM(B29:M29) -> 48167880 | O29: =N29/$N$34 -> 0.10757052 | P29: =N29/N11 -> 0.20794679
A30: Wash | B30: 1455000 | C30: 1066000 | D30: 905000 | E30: 674000 | F30: =SUMIF(INDIRECT("Report!I3:I55"),A30,INDIRECT("Report!J3:J55")) -> 1213500 | G30: =SUMIF(INDIRECT("Report!I58:I120"),A30,INDIRECT("Report!J58:J120")) -> 2234000 | H30: =SUMIF(INDIRECT("Report!I120:I196"),A30,INDIRECT("Report!J120:J196")) -> 872500 | I30: =SUMIF(INDIRECT("Report!I198:I264"),A30,INDIRECT("Report!J198:J264")) -> 872000 | J30: =SUMIF(INDIRECT("Report!I266:I342"),A30,INDIRECT("Report!J266:J342")) -> 1372000 | K30: =SUMIF(INDIRECT("Report!I344:I407"),A30,INDIRECT("Report!J344:J407")) -> 1104000 | L30: =SUMIF(INDIRECT("Report!I409:I480"),A30,INDIRECT("Report!J409:J480")) -> 2381000 | M30: =SUMIF(INDIRECT("Report!I482:I565"),A30,INDIRECT("Report!J482:J565")) -> 2605000 | N30: =SUM(B30:M30) -> 16754000 | O30: =N30/$N$34 -> 0.037415732 | P30: =N30/N12 -> 0.25899303
A31: 농도계 | B31: 0 | C31: 0 | D31: 0 | E31: 0 | F31: 0 | G31: 0 | H31: =SUMIF(INDIRECT("Report!I120:I196"),A31,INDIRECT("Report!J120:J196")) -> 0 | I31: 0 | J31: =SUMIF(INDIRECT("Report!I266:I342"),A31,INDIRECT("Report!J266:J342")) -> 0 | K31: =SUMIF(INDIRECT("Report!I344:I407"),A31,INDIRECT("Report!J344:J407")) -> 0 | L31: =SUMIF(INDIRECT("Report!I409:I480"),A31,INDIRECT("Report!J409:J480")) -> 0 | M31: =SUMIF(INDIRECT("Report!I482:I565"),A31,INDIRECT("Report!J482:J565")) -> 0 | N31: =SUM(B31:M31) -> 0 | O31: =N31/$N$34 -> 0 | P31: =N31/N13 -> #DIV/0!
A32: Ink | B32: 0 | C32: 0 | D32: 0 | E32: 0 | F32: =SUMIF(INDIRECT("Report!I3:I55"),A32,INDIRECT("Report!J3:J55")) -> 79700 | G32: =SUMIF(INDIRECT("Report!I58:I120"),A32,INDIRECT("Report!J58:J120")) -> 1383360 | H32: =SUMIF(INDIRECT("Report!I120:I196"),A32,INDIRECT("Report!J120:J196")) -> 1502120 | I32: =SUMIF(INDIRECT("Report!I198:I264"),A32,INDIRECT("Report!J198:J264")) -> 1058040 | J32: =SUMIF(INDIRECT("Report!I266:I342"),A32,INDIRECT("Report!J266:J342")) -> 1214080 | K32: =SUMIF(INDIRECT("Report!I344:I407"),A32,INDIRECT("Report!J344:J407")) -> 1054680 | L32: =SUMIF(INDIRECT("Report!I409:I480"),A32,INDIRECT("Report!J409:J480")) -> 1020760 | M32: =SUMIF(INDIRECT("Report!I482:I565"),A32,INDIRECT("Report!J482:J565")) -> 966280 | N32: =SUM(B32:M32) -> 8279020 | O32: =N32/$N$34 -> 0.018489053 | P32: =N32/N14 -> 0.10673104
A33: Service | B33: 150000 | C33: 7250000 | D33: 0 | E33: 1650000 | F33: =SUMIF(INDIRECT("Report!H3:H55"),A33,INDIRECT("Report!J3:J55")) -> 0 | G33: =SUMIF(INDIRECT("Report!h58:h120"),A33,INDIRECT("Report!J58:J120")) -> 1800000 | H33: =SUMIF(INDIRECT("Report!H120:H196"),A33,INDIRECT("Report!J120:J196")) -> 0 | I33: =I15 -> 17178000 | J33: =J15 -> 9538000 | K33: =SUMIF(INDIRECT("Report!H344:H407"),A33,INDIRECT("Report!J344:J407")) -> 1250000 | L33: =SUMIF(INDIRECT("Report!H409:H480"),A33,INDIRECT("Report!J409:J480")) -> 3680000 | M33: =SUMIF(INDIRECT("Report!H482:H565"),A33,INDIRECT("Report!J482:J565")) -> 250000 | N33: =SUM(B33:M33) -> 42746000 | O33: =N33/$N$34 -> 0.095462152 | P33: =N33/N15 -> 0.86223173
A34: Margin Total | B34: =SUM(B22:B33)*1.1 -> 25920248 | C34: =SUM(C22:C33)*1.1 -> 49830217 | D34: =SUM(D22:D33)*1.1 -> 20414845 | E34: =SUM(E22:E33)*1.1 -> 35432913 | F34: =SUM(F22:F33)*1.1 -> 30755186 | G34: =SUM(G22:G33)*1.1 -> 31744911 | H34: =SUM(H22:H33)*1.1 -> 81472880 | I34: =SUM(I22:I33)*1.1 -> 49966261 | ... M34: =SUM(M22:M33)*1.1 -> 27325056 | N34: =SUM(N22:N33) -> 4.4777956e+08 | O34: =SUM(O22:O33) -> 1
A35: 마진 % | B35: =B34/B17 -> 0.28426327 | C35: =C34/C17 -> 0.41425656 | D35: =D34/D17 -> 0.27581367 | E35: =E34/E17 -> 0.23178942 | F35: =F34/F17 -> 0.19135735 | G35: =G34/G17 -> 0.26071012 | H35: =H34/H17 -> 0.49409455 | I35: =I34/I17 -> 0.57444039 | ... N35: =N34/N17 -> 0.3686773
I37: YTD 12 months
B38: 합계 : Sales | F38: 합계 : CM
A39: Product | B39: 2013 | C39: 2014 | D39: 2015 | E39: 2016 | F39: 2013 | G39: 2014 | H39: 2015 | I39: 2016
A40: Blanket | B40: 21270000 | C40: 106683000 | D40: 169374500 | E40: 156041000 | F40: 4474380 | G40: 19408300 | H40: 33702400 | I40: 36698800
A41: CTP | D41: 16645000 | E41: 254899000 | H41: 2891300 | I41: 48134500
A42: Film | B42: 34629000 | C42: 53408500 | D42: 51778000 | E42: 48463000 | F42: 11489000 | G42: 14591500 | H42: 14188330 | I42: 10634320
A43: Fount | B43: 10650000 | C43: 24369000 | D43: 15203000 | E43: 26967500 | F43: 3612000 | G43: 7169000 | H43: 5463000 | I43: 10867500
A44: GOSS | D44: 35420000 | E44: 201838500 | H44: 10087778 | I44: 70032843
A45: Others | B45: 760000 | C45: 1397000 | D45: 19243000 | E45: 133305500 | F45: 219000 | G45: 573200 | H45: 5777500 | I45: 45402695
A46: Roller | B46: 10882000 | C46: 4182000 | D46: 22121000 | E46: 37684000 | F46: 6789000 | G46: 2877000 | H46: 8046000 | I46: 6291500
A47: Technotrans | D47: 25917000 | E47: 136595800 | H47: 12642642 | I47: 45665517
A48: Wash | B48: 9075000 | C48: 46490500 | D48: 72432000 | E48: 62378500 | F48: 2089400 | G48: 8160500 | H48: 15128000 | I48: 13338500
A49: 농도계 | C49: 113672000 | D49: 60295450 | E49: 24330000 | G49: 37322000 | H49: 16544950 | I49: 6723000
A50: 서비스 | D50: 4644000 | E50: 15256000 | H50: 2422000 | I50: 7365000
A51: 총합계 | B51: 87310000 | C51: 354923000 | D51: 501034950 | E51: =SUM(E40:E50) -> 1097758800 | F51: 28686380 | G51: 90830500 | H51: 1.284521e+08 | I51: =SUM(I40:I50) -> 3.0115418e+08
D245: total | I245: Consumable | M245: Technotrans | Q245: GOSS | U245: Service
D246: 2016.1 | E246: 70787200 | F246: 15197776 | I246: 2016.1 | J246: 44012550 | K246: 8959760 | M246: 2016.1 | N246: 220000 | O246: 160400 | Q246: 2016.1 | R246: 25884650 | S246: 5591000 | U246: 2016.1 | V246: 550000 | W246: 300000
D247: 2016.2 | E247: 60660050 | F247: 21873830 | I247: 2016.2 | J247: 44286550 | K247: 15037100 | M247: 2016.2 | N247: 5604500 | O247: 1891000 | Q247: 2016.2 | R247: 10769000 | S247: 2957200 | U247: 2016.2 | V247: 0 | W247: 0
D248: 2016.3 | E248: 56713250 | F248: 16866165 | I248: 2016.3 | J248: 41003050 | K248: 8182200 | M248: 2016.3 | N248: 2094400 | O248: 643677 | Q248: 2016.3 | R248: 11022000 | S248: 5007000 | U248: 2016.3 | V248: 2428800 | W248: 1500000
D249: 2016.4 | E249: 80611300 | F249: 26897761 | I249: 2016.4 | J249: 51114800 | K249: 16216700 | M249: 2016.4 | N249: 1908500 | O249: 775770 | Q249: 2016.4 | R249: 24288000 | S249: 6333620 | U249: 2016.4 | V249: 1204500 | W249: 1095000
D250: 2016.5 | E250: 1.0534205e+08 | F250: 25496829 | I250: 2016.5 | J250: 86224050 | K250: 16758675 | M250: 2016.5 | N250: 10472000 | O250: 3073140 | Q250: 2016.5 | R250: 8371000 | S250: 2987120 | U250: 2016.5 | V250: 275000 | W250: 250000
D251: 2016.6 | E251: 1.3363295e+08 | F251: 37687760 | I251: 2016.6 | J251: 64016150 | K251: 14129880 | M251: 2016.6 | N251: 55918500 | O251: 14950600 | Q251: 2016.6 | R251: 10395000 | S251: 4707120 | U251: 2016.6 | V251: 1375000 | W251: 1250000
D252: 2016.7 | E252: 81625500 | F252: 22605462 | I252: 2016.7 | J252: 47536500 | K252: 9706920 | M252: 2016.7 | N252: 23309000 | O252: 8494800 | Q252: 2016.7 | R252: 10780000 | S252: 2282500 | U252: 2016.7 | V252: 0 | W252: 0
D253: 2016.8 | E253: 177157750 | F253: 46326324 | I253: 2016.8 | J253: 104007750 | K253: 21008340 | M253: 2016.8 | N253: 0 | O253: 0 | Q253: 2016.8 | R253: 53735000 | S253: 16308500 | U253: 2016.8 | V253: 5032500 | W253: 1250000
D254: 2016.9 | E254: 1.02168e+08 | F254: 30225558 | I254: 2016.9 | J254: 54607300 | K254: 10497780 | M254: 2016.9 | N254: 14382500 | O254: 4338000 | Q254: 2016.9 | R254: 47560700 | S254: 16980000 | U254: 2016.9 | V254: 0 | W254: 0
D255: 2016.1 | E255: 91679830 | F255: 24070747 | I255: 2016.1 | J255: 68594350 | K255: 13931980 | M255: 2016.1 | N255: 16650480 | O255: 4528930 | Q255: 2016.1 | R255: 5060000 | S255: 2171587 | U255: 2016.1 | V255: 1375000 | W255: 1250000
D256: 2016.11 | E256: 73328750 | F256: 20924614 | I256: 2016.11 | J256: 54320750 | K256: 12077780 | M256: 2016.11 | N256: 9702000 | O256: 3134400 | Q256: 2016.11 | R256: 9306000 | S256: 3810196 | U256: 2016.11 | V256: 0 | W256: 0
D257: 2016.12 | E257: 173828050 | F257: 43096768 | I257: 2016.12 | J257: 136081550 | K257: 27067280 | M257: 2016.12 | N257: 9993500 | O257: 3608600 | Q257: 2016.12 | R257: 27236000 | S257: 8033000 | U257: 2016.12 | V257: 517000 | W257: 470000
I258: 2017.1 | J258: 64962150 | K258: 14704560 | M258: 2017.1 | N258: 12298000 | O258: 3528562 | Q258: 2017.1 | R258: 9801000 | S258: 4250740 | U258: 2017.1 | V258: 165000 | W258: 150000
I259: 2017.2 | J259: 69975400 | K259: 20204886 | M259: 2017.2 | N259: 2510200 | O259: 1064899 | Q259: 2017.2 | R259: 39827700 | S259: 17656413 | U259: 2017.2 | V259: 7975000 | W259: 7250000
I260: 2017.3 | J260: 59952200 | K260: 13125140 | M260: 2017.3 | N260: 1997600 | O260: 742670 | Q260: 2017.3 | R260: 12067000 | S260: 4691140 | U260: 2017.3 | V260: 0 | W260: 0
I261: 2017.4 | J261: =([2]Consumables!C78) -> 79137300 | K261: =([2]Consumables!E78) -> 16977984 | M261: 2017.4 | N261: 57614524 | O261: 51961110 | Q261: 2017.4 | R261: 14300000 | S261: 7084000 | U261: 2017.4 | V261: 1815000 | W261: 1650000
I262: 2017.5 | J262: =([2]Consumables!C91) -> 51543800 | K262: =([2]Consumables!E91) -> 13433014 | M262: 2017.5 | N262: =(Technotrans!C130) -> 101026420 | O262: =Technotrans!E130 -> 11831906 | Q262: 2017.5 | R262: =GOSS!C115 -> 10131000 | S262: =GOSS!E115 -> 4024340 | U262: 2017.5 | V262: 0 | W262: 0
E263: =E246*1.1 -> 77865920 | F263: =F246*1.1 -> 16717554 | I263: 2017.6 | J263: =(Consumables!C616) -> 59820530 | K263: =(Consumables!E616) -> 12212120 | M263: 2017.6 | N263: =(Technotrans!C138) -> 49144216 | O263: =Technotrans!E138 -> 7551889.7 | Q263: 2017.6 | R263: =GOSS!C120 -> 7628500 | S263: =GOSS!E120 -> 6635000 | U263: 2017.6 | V263: =서비스!C54 -> 1980000 | W263: =서비스!E54 -> 1800000
E264: =E247*1.1 -> 66726055 | F264: =F247*1.1 -> 24061213 | I264: 2017.7 | J264: =(Consumables!C631) -> 34566400 | K264: =(Consumables!E631) -> 7042240 | M264: 2017.7 | N264: =(Technotrans!C141) -> 638000 | O264: =Technotrans!E141 -> 310468 | Q264: 2017.7 | R264: =GOSS!C125 -> 56672000 | S264: =GOSS!E125 -> 51154000 | U264: 2017.7 | V264: 0 | W264: 0
E265: =E248*1.1 -> 62384575 | F265: =F248*1.1 -> 18552781 | I265: 2017.8 | J265: =(Consumables!C643) -> 24847900 | K265: =(Consumables!E643) -> 5516460 | M265: 2017.8 | N265: =(Technotrans!C146) -> 6526300 | O265: =(Technotrans!E146) -> 5326373.5 | Q265: 2017.8 | R265: =GOSS!C129 -> 20306000 | S265: =GOSS!E129 -> 15160000 | U265: 2017.8 | V265: =서비스!C63 -> 29178600 | W265: =서비스!E63 -> 26526000
E266: =E249*1.1 -> 88672430 | F266: =F249*1.1 -> 29587537 | I266: 2017.9 | J266: 94859710 | K266: 12415940 | M266: 2017.9 | N266: 16850900 | O266: 5828492 | Q266: 2017.9 | R266: 2784100 | S266: 1405438.6 | U266: 2017.9 | V266: 2585000
E267: =E250*1.1 -> 1.1587626e+08 | F267: =F250*1.1 -> 28046511 | I267: 2017.1 | J267: 37355780 | K267: 7485900 | M267: 2017.1 | N267: 770000 | O267: 323276.93 | Q267: 2017.1 | R267: 11781000 | S267: 6274823.5 | U267: 2017.1 | V267: 1375000
E268: =E251*1.1 -> 1.4699625e+08 | F268: =F251*1.1 -> 41456536 | J268: 42459120 | K268: 9121620 | N268: 2618000 | O268: 566904.98 | R268: 57145994 | S268: 6731545.4 | V268: 11847000
E269: =E252*1.1 -> 89788050 | F269: =F252*1.1 -> 24866008 | J269: 52457350 | K269: 12597180 | N269: 2442000 | O269: 894194.78 | R269: 9394000 | S269: 3559736.1 | V269: 275000
E270: =E253*1.1 -> 1.9487353e+08 | F270: =F253*1.1 -> 50958956
E271: =E254*1.1 -> 1.123848e+08 | F271: =F254*1.1 -> 33248114
E272: =E255*1.1 -> 1.0084781e+08 | F272: =F255*1.1 -> 26477821
E273: =E256*1.1 -> 80661625 | F273: =F256*1.1 -> 23017075
E274: =E257*1.1 -> 1.9121086e+08 | F274: =F257*1.1 -> 47406445
H282: 70787200 | I282: 15197776
H283: 60660050 | I283: 21873830
H284: 56713250 | I284: 16866165
H285: 80611300 | I285: 26897761
H286: 1.0534205e+08 | I286: 25496829
H287: 1.3363295e+08 | I287: 37687760
H288: 81625500 | I288: 22605462
H289: 177157750 | I289: 46326324
H290: 1.02168e+08 | I290: 30225558
H291: 91679830 | I291: 24070747
H292: 73328750 | I292: 20924614
H293: 173828050 | I293: 43096768

Sheet Others
A1: Month | B1: Customer | C1: Sales (VAT 포함) | D1: Sales (VAT 제외) | E1: CM | F1: CM % | G1: 비고 | H1: 담당자
A2: 2017. 7 | B2: 재능(Ink & CTP) | C2: =SUMIFS(INDIRECT("Report!F100:F1000"),INDIRECT("Report!B100:B1000"),B2,INDIRECT("report!H100:H1000"),"Consums",INDIRECT("Report!L100:L1000"),"17.7") -> 25320900 | D2: =(C2/11*10) -> 23019000 | E2: =SUMIFS(INDIRECT("Report!J100:J1000"),INDIRECT("Report!B100:B1000"),B2,INDIRECT("report!H100:H1000"),"Consums",INDIRECT("Report!L100:L1000"),"17.7") -> 4522120 | F2: =E2/D2 -> 0.19645163
B3: 프린피아 문발 | C3: 47300000 | D3: =(C3/11*10) -> 43000000 | E3: 9708427 | F3: =E3/D3 -> 0.22577737 | G3: 판 절곡기
B4: 17,7 | C4: =SUM(C2:C3) -> 72620900 | D4: =SUM(D2:D3) -> 66019000 | E4: =SUM(E2:E3) -> 14230547 | F4: =E4/D4 -> 0.2155523
A5: 2017. 8 | B5: 재능(Ink & CTP) | C5: =SUMIFS(INDIRECT("Report!F100:F1000"),INDIRECT("Report!B100:B1000"),B5,INDIRECT("report!H100:H1000"),"Consums",INDIRECT("Report!L100:L1000"),"17.8") -> 15812500 | D5: =(C5/11*10) -> 14375000 | E5: =SUMIFS(INDIRECT("Report!J100:J1000"),INDIRECT("Report!B100:B1000"),B5,INDIRECT("report!H100:H1000"),"Consums",INDIRECT("Report!L100:L1000"),"17.8") -> 2143040 | F5: =E5/D5 -> 0.14908104 | G5: 잉크,판
C6: =SUM(C5) -> 15812500 | D6: =SUM(D5) -> 14375000 | E6: =SUM(E5) -> 2143040 | F6: =E6/D6 -> 0.14908104
A7: 2017. 9 | B7: 재능(Ink & CTP) | C7: =SUMIFS(INDIRECT("Report!F100:F1000"),INDIRECT("Report!B100:B1000"),B7,INDIRECT("report!H100:H1000"),"Consums",INDIRECT("Report!L100:L1000"),"17.9") -> 19865560 | D7: =(C7/11*10) -> 18059600 | E7: =SUMIFS(INDIRECT("Report!J100:J1000"),INDIRECT("Report!B100:B1000"),B7,INDIRECT("report!H100:H1000"),"Consums",INDIRECT("Report!L100:L1000"),"17.9") -> 3084080 | F7: =E7/D7 -> 0.17077233
B8: 재능 | C8: =SUMIFS(INDIRECT("Report!F100:F1000"),INDIRECT("Report!B100:B1000"),B8,INDIRECT("report!H100:H1000"),"Consums",INDIRECT("Report!L100:L1000"),"17.9") -> 29700000 | D8: =(C8/11*10) -> 27000000 | G8: OneVision Asura
C9: =SUM(C7:C8) -> 49565560 | D9: =SUM(D7:D8) -> 45059600
A10: 2017. 10 | B10: 재능(Ink & CTP) | C10: =SUMIFS(INDIRECT("Report!F100:F1000"),INDIRECT("Report!B100:B1000"),B10,INDIRECT("report!H100:H1000"),"Consums",INDIRECT("Report!L100:L1000"),"17.10") -> 15278780 | D10: =(C10/11*10) -> 13889800 | E10: =SUMIFS(INDIRECT("Report!J100:J1000"),INDIRECT("Report!B100:B1000"),B10,INDIRECT("report!H100:H1000"),"Consums",INDIRECT("Report!L100:L1000"),"17.10") -> 2409680 | F10: =E10/D10 -> 0.17348558
C11: =SUM(C10) -> 15278780 | D11: =SUM(D10) -> 13889800 | E11: =SUM(E10) -> 2409680 | F11: =E11/D11 -> 0.17348558
A12: 2017. 11 | B12: 재능(Ink & CTP) | C12: =SUMIFS(INDIRECT("Report!F100:F1000"),INDIRECT("Report!B100:B1000"),B12,INDIRECT("report!H100:H1000"),"Consums",INDIRECT("Report!L100:L1000"),"17.11") -> 13893220 | D12: =(C12/11*10) -> 12630200 | E12: =SUMIFS(INDIRECT("Report!J100:J1000"),INDIRECT("Report!B100:B1000"),B12,INDIRECT("report!H100:H1000"),"Consums",INDIRECT("Report!L100:L1000"),"17.11") -> 1778760 | F12: =E12/D12 -> 0.14083387
B13: 매일경제 | C13: =SUMIFS(INDIRECT("Report!F100:F1000"),INDIRECT("Report!B100:B1000"),B13,INDIRECT("report!H100:H1000"),"Others",INDIRECT("Report!L100:L1000"),"17.11") -> 2.707969e+08 | D13: =(C13/11*10) -> 2.46179e+08 | G13: 솔레노이드 밸브, CTP
C14: =SUM(C12:C13) -> 2.8469012e+08 | D14: =SUM(D13:D13) -> 2.46179e+08
A15: 2017. 12 | B15: 재능(Ink & CTP) | C15: =SUMIFS(INDIRECT("Report!F100:F1000"),INDIRECT("Report!B100:B1000"),B15,INDIRECT("report!H100:H1000"),"Others",INDIRECT("Report!L100:L1000"),"17.12") -> 15286700 | D15: =(C15/11*10) -> 13897000 | E15: =SUMIFS(INDIRECT("Report!J100:J1000"),INDIRECT("Report!B100:B1000"),B15,INDIRECT("report!H100:H1000"),"Others",INDIRECT("Report!L100:L1000"),"17.12") -> 2436280 | F15: =E15/D15 -> 0.17530978
B16: 지엔에스 | C16: =SUMIFS(INDIRECT("Report!F100:F1000"),INDIRECT("Report!B100:B1000"),B16,INDIRECT("report!H100:H1000"),"Others",INDIRECT("Report!L100:L1000"),"17.12") -> 30140000 | D16: =(C16/11*10) -> 27400000 | G16: 중고 CTP
C17: =SUM(C15:C16) -> 45426700 | D17: =SUM(D15:D16) -> 41297000
A18: 2018.1 | B18: 재능(Ink) | C18: =SUMIFS(INDIRECT("Report!F100:F1000"),INDIRECT("Report!B100:B1000"),B18,INDIRECT("report!H100:H1000"),"Others",INDIRECT("Report!L100:L1000"),"18.1") -> 9559000 | D18: =(C18/11*10) -> 8690000 | E18: =SUMIFS(INDIRECT("Report!J100:J1000"),INDIRECT("Report!B100:B1000"),B18,INDIRECT("report!H100:H1000"),"Others",INDIRECT("Report!L100:L1000"),"18.1") -> 976000 | F18: =E18/D18 -> 0.112313
B19: 재능(CTP) | C19: =SUMIFS(INDIRECT("Report!F100:F1000"),INDIRECT("Report!B100:B1000"),B19,INDIRECT("report!H100:H1000"),"Others",INDIRECT("Report!L100:L1000"),"18.1") -> 17954200 | D19: =(C19/11*10) -> 16322000 | E19: =SUMIFS(INDIRECT("Report!J100:J1000"),INDIRECT("Report!B100:B1000"),B19,INDIRECT("report!H100:H1000"),"Others",INDIRECT("Report!L100:L1000"),"18.1") -> 5230000 | F19: =E19/D19 -> 0.32042642
C20: =SUM(C18:C19) -> 27513200 | D20: =SUM(D18:D19) -> 25012000
A21: 2018.2 | B21: 재능(Ink) | C21: =SUMIFS(INDIRECT("Report!F100:F1000"),INDIRECT("Report!B100:B1000"),B21,INDIRECT("report!H100:H1000"),"Others",INDIRECT("Report!L100:L1000"),"18.2") -> 7832000 | D21: =(C21/11*10) -> 7120000 | E21: =SUMIFS(INDIRECT("Report!J100:J1000"),INDIRECT("Report!B100:B1000"),B21,INDIRECT("report!H100:H1000"),"Others",INDIRECT("Report!L100:L1000"),"18.2") -> 732000 | F21: =E21/D21 -> 0.10280899
B22: 재능(CTP) | C22: =SUMIFS(INDIRECT("Report!F100:F1000"),INDIRECT("Report!B100:B1000"),B22,INDIRECT("report!H100:H1000"),"Others",INDIRECT("Report!L100:L1000"),"18.2") -> 16700200 | D22: =(C22/11*10) -> 15182000 | E22: =SUMIFS(INDIRECT("Report!J100:J1000"),INDIRECT("Report!B100:B1000"),B22,INDIRECT("report!H100:H1000"),"Others",INDIRECT("Report!L100:L1000"),"18.2") -> 4870000 | F22: =E22/D22 -> 0.3207746
B23: 지엔에스 | C23: =SUMIFS(INDIRECT("Report!F100:F1000"),INDIRECT("Report!B100:B1000"),B23,INDIRECT("report!H100:H1000"),"Others",INDIRECT("Report!L100:L1000"),"18.2") -> 164450 | D23: =(C23/11*10) -> 149500 | E23: 149500 | F23: =E23/D23 -> 1
C24: =SUM(C21:C23) -> 24696650 | D24: =SUM(D21:D23) -> 22451500
A25: 2018.3 | B25: 재능(Ink) | C25: =SUMIFS(INDIRECT("Report!F100:F1000"),INDIRECT("Report!B100:B1000"),B25,INDIRECT("report!H100:H1000"),"Others",INDIRECT("Report!L100:L1000"),"18.3") -> 13915000 | D25: =(C25/11*10) -> 12650000 | E25: =SUMIFS(INDIRECT("Report!J100:J1000"),INDIRECT("Report!B100:B1000"),B25,INDIRECT("report!H100:H1000"),"Others",INDIRECT("Report!L100:L1000"),"18.3") -> 1136000 | F25: =E25/D25 -> 0.089802372
B26: 재능(CTP) | C26: =SUMIFS(INDIRECT("Report!F100:F1000"),INDIRECT("Report!B100:B1000"),B26,INDIRECT("report!H100:H1000"),"Others",INDIRECT("Report!L100:L1000"),"18.3") -> 40733000 | D26: =(C26/11*10) -> 37030000 | E26: =SUMIFS(INDIRECT("Report!J100:J1000"),INDIRECT("Report!B100:B1000"),B26,INDIRECT("report!H100:H1000"),"Others",INDIRECT("Report!L100:L1000"),"18.3") -> 12592000 | F26: =E26/D26 -> 0.34004861 | G26: 재고판 소진 포함
B27: 조선일보 | C27: =SUMIFS(INDIRECT("Report!F100:F1000"),INDIRECT("Report!B100:B1000"),B27,INDIRECT("report!H100:H1000"),"Others",INDIRECT("Report!L100:L1000"),"18.3") -> 6985000 | D27: =(C27/11*10) -> 6350000 | E27: =SUMIFS(INDIRECT("Report!J100:J1000"),INDIRECT("Report!B100:B1000"),B27,INDIRECT("report!H100:H1000"),"Others",INDIRECT("Report!L100:L1000"),"18.3") -> 1805000 | F27: =E27/D27 -> 0.28425197 | G27: QuadTech 기판
C28: =SUM(C25:C27) -> 61633000 | D28: =SUM(D25:D27) -> 56030000
A29: 2018.4 | B29: 재능(Ink) | C29: =SUMIFS(INDIRECT("Report!F100:F1000"),INDIRECT("Report!B100:B1000"),B29,INDIRECT("report!H100:H1000"),"Others",INDIRECT("Report!L100:L1000"),"18.4") -> 10310300 | D29: =(C29/11*10) -> 9373000 | E29: =SUMIFS(INDIRECT("Report!J100:J1000"),INDIRECT("Report!B100:B1000"),B29,INDIRECT("report!H100:H1000"),"Others",INDIRECT("Report!L100:L1000"),"18.4") -> 519000 | F29: =E29/D29 -> 0.055371813
B30: 재능(CTP) | C30: =SUMIFS(INDIRECT("Report!F100:F1000"),INDIRECT("Report!B100:B1000"),B30,INDIRECT("report!H100:H1000"),"Others",INDIRECT("Report!L100:L1000"),"18.4") -> 43948410 | D30: =(C30/11*10) -> 39953100 | E30: =SUMIFS(INDIRECT("Report!J100:J1000"),INDIRECT("Report!B100:B1000"),B30,INDIRECT("report!H100:H1000"),"Others",INDIRECT("Report!L100:L1000"),"18.4") -> 11806500 | F30: =E30/D30 -> 0.29550898 | G30: 재고판 소진 포함
C31: =SUM(C29:C30) -> 54258710 | D31: =SUM(D29:D30) -> 49326100
A32: 2018.5 | B32: 재능(Ink) | C32: =SUMIFS(INDIRECT("Report!F100:F1000"),INDIRECT("Report!B100:B1000"),B32,INDIRECT("report!H100:H1000"),"Others",INDIRECT("Report!L100:L1000"),"18.5") -> 16682600 | D32: =(C32/11*10) -> 15166000 | E32: =SUMIFS(INDIRECT("Report!J100:J1000"),INDIRECT("Report!B100:B1000"),B32,INDIRECT("report!H100:H1000"),"Others",INDIRECT("Report!L100:L1000"),"18.5") -> 1269000 | F32: =E32/D32 -> 0.083674008
B33: 재능(CTP) | C33: =SUMIFS(INDIRECT("Report!F100:F1000"),INDIRECT("Report!B100:B1000"),B33,INDIRECT("report!H100:H1000"),"Others",INDIRECT("Report!L100:L1000"),"18.5") -> 8350100 | D33: =(C33/11*10) -> 7591000 | E33: =SUMIFS(INDIRECT("Report!J100:J1000"),INDIRECT("Report!B100:B1000"),B33,INDIRECT("report!H100:H1000"),"Others",INDIRECT("Report!L100:L1000"),"18.5") -> 2435000 | F33: =E33/D33 -> 0.3207746
B34: 한국경제신문 | C34: =SUMIFS(INDIRECT("Report!F100:F1000"),INDIRECT("Report!B100:B1000"),B34,INDIRECT("report!H100:H1000"),"Others",INDIRECT("Report!L100:L1000"),"18.5") -> 10806576 | D34: =(C34/11*10) -> 9824160 | E34: =SUMIFS(INDIRECT("Report!J100:J1000"),INDIRECT("Report!B100:B1000"),B34,INDIRECT("report!H100:H1000"),"Others",INDIRECT("Report!L100:L1000"),"18.5") -> 3132534.8 | F34: =E34/D34 -> 0.31886032 | G34: 고스 부품
B35: 매일경제 | C35: =SUMIFS(INDIRECT("Report!F100:F1000"),INDIRECT("Report!B100:B1000"),B35,INDIRECT("report!H100:H1000"),"Others",INDIRECT("Report!L100:L1000"),"18.5") -> 9685500 | D35: =(C35/11*10) -> 8805000 | E35: =SUMIFS(INDIRECT("Report!J100:J1000"),INDIRECT("Report!B100:B1000"),B35,INDIRECT("report!H100:H1000"),"Others",INDIRECT("Report!L100:L1000"),"18.5") -> 2362950 | F35: =E35/D35 -> 0.26836457 | G35: 고스 부품
C36: =SUM(C32:C35) -> 45524776 | D36: =SUM(D32:D35) -> 41386160 | E36: =SUM(E32:E35) -> 9199484.8
A37: 2018.6 | B37: 재능(Ink) | C37: =SUMIFS(INDIRECT("Report!F100:F10000"),INDIRECT("Report!B100:B10000"),B37,INDIRECT("report!H100:H10000"),"Others",INDIRECT("Report!L100:L10000"),"18.6") -> 14440800 | D37: =(C37/11*10) -> 13128000 | E37: =SUMIFS(INDIRECT("Report!J100:J10000"),INDIRECT("Report!B100:B10000"),B37,INDIRECT("report!H100:H10000"),"Others",INDIRECT("Report!L100:L10000"),"18.6") -> 1114000 | F37: =E37/D37 -> 0.084856795
B38: 재능(CTP) | C38: =SUMIFS(INDIRECT("Report!F100:F10000"),INDIRECT("Report!B100:B10000"),B38,INDIRECT("report!H100:H10000"),"Others",INDIRECT("Report!L100:L10000"),"18.6") -> 17344800 | D38: =(C38/11*10) -> 15768000 | E38: =SUMIFS(INDIRECT("Report!J100:J10000"),INDIRECT("Report!B100:B10000"),B38,INDIRECT("report!H100:H10000"),"Others",INDIRECT("Report!L100:L10000"),"18.6") -> 5055000 | F38: =E38/D38 -> 0.320586
B39: 프린피아 주안 | C39: =SUMIFS(INDIRECT("Report!F100:F10000"),INDIRECT("Report!B100:B10000"),B39,INDIRECT("report!H100:H10000"),"Others",INDIRECT("Report!L100:L10000"),"18.6") -> 0 | D39: =(C39/11*10) -> 0 | E39: =SUMIFS(INDIRECT("Report!F100:F10000"),INDIRECT("Report!B100:B10000"),D39,INDIRECT("report!H100:H10000"),"Others",INDIRECT("Report!L100:L10000"),"18.6") -> 0 | F39: =E39/D39 -> #DIV/0! | G39: Beta.f 계약금
C40: =SUM(C37:C39) -> 31785600 | D40: =SUM(D37:D39) -> 28896000
A41: 2018.7 | B41: 재능(Ink) | C41: =SUMIFS(INDIRECT("Report!F100:F10000"),INDIRECT("Report!B100:B10000"),B41,INDIRECT("report!H100:H10000"),"Others",INDIRECT("Report!L100:L10000"),"18.7") -> 15301000 | D41: =(C41/11*10) -> 13910000 | E41: =SUMIFS(INDIRECT("Report!J100:J10000"),INDIRECT("Report!B100:B10000"),B41,INDIRECT("report!H100:H10000"),"Others",INDIRECT("Report!L100:L10000"),"18.7") -> 1097000 | F41: =E41/D41 -> 0.078864127
B42: 재능(CTP) | C42: =SUMIFS(INDIRECT("Report!F100:F10000"),INDIRECT("Report!B100:B10000"),B42,INDIRECT("report!H100:H10000"),"Others",INDIRECT("Report!L100:L10000"),"18.7") -> 17446000 | D42: =(C42/11*10) -> 15860000 | E42: =SUMIFS(INDIRECT("Report!J100:J10000"),INDIRECT("Report!B100:B10000"),B42,INDIRECT("report!H100:H10000"),"Others",INDIRECT("Report!L100:L10000"),"18.7") -> 4871000 | F42: =E42/D42 -> 0.30712484
B43: 프린피아 주안1 | C43: =SUMIFS(INDIRECT("Report!F100:F10000"),INDIRECT("Report!B100:B10000"),B43,INDIRECT("report!H100:H10000"),"Others",INDIRECT("Report!L100:L10000"),"18.7") -> 48400000 | D43: =(C43/11*10) -> 44000000 | E43: =SUMIFS(INDIRECT("Report!J100:J10000"),INDIRECT("Report!B100:B10000"),B43,INDIRECT("report!H100:H10000"),"Others",INDIRECT("Report!L100:L10000"),"18.7") -> 10263454 | F43: =E43/D43 -> 0.23326032 | G43: 판절곡기
B44: 프린피아 주안2 | C44: =SUMIFS(INDIRECT("Report!F100:F10000"),INDIRECT("Report!B100:B10000"),B44,INDIRECT("report!H100:H10000"),"Others",INDIRECT("Report!L100:L10000"),"18.7") -> 21450000 | D44: =(C44/11*10) -> 19500000 | E44: =SUMIFS(INDIRECT("Report!J100:J10000"),INDIRECT("Report!B100:B10000"),B44,INDIRECT("report!H100:H10000"),"Others",INDIRECT("Report!L100:L10000"),"18.7") -> 0 | F44: =E44/D44 -> 0 | G44: Beta.f 중도금
B45: ASPT | C45: =SUMIFS(INDIRECT("Report!F100:F10000"),INDIRECT("Report!B100:B10000"),B45,INDIRECT("report!H100:H10000"),"Others",INDIRECT("Report!L100:L10000"),"18.7") -> 18498282 | D45: =(C45/11*10) -> 16816620 | E45: =SUMIFS(INDIRECT("Report!J100:J10000"),INDIRECT("Report!B100:B10000"),B45,INDIRECT("report!H100:H10000"),"Others",INDIRECT("Report!L100:L10000"),"18.7") -> 0 | F45: =E45/D45 -> 0 | G45: ASPT 소모품
B46: 부일인쇄 | C46: =SUMIFS(INDIRECT("Report!F100:F10000"),INDIRECT("Report!B100:B10000"),B46,INDIRECT("report!H100:H10000"),"Others",INDIRECT("Report!L100:L10000"),"18.7") -> 1287000 | D46: =(C46/11*10) -> 1170000 | F46: =E46/D46 -> 0 | G46: 솔레노이드 코일
C47: =SUM(C41:C45) -> 121095282 | D47: =SUM(D41:D45) -> 110086620
A48: 2018.8 | B48: 재능(Ink) | C48: =SUMIFS(INDIRECT("Report!F100:F10000"),INDIRECT("Report!B100:B10000"),B48,INDIRECT("report!H100:H10000"),"Others",INDIRECT("Report!L100:L10000"),"18.8") -> 8519500 | D48: =(C48/11*10) -> 7745000 | E48: =SUMIFS(INDIRECT("Report!J100:J10000"),INDIRECT("Report!B100:B10000"),B48,INDIRECT("report!H100:H10000"),"Others",INDIRECT("Report!L100:L10000"),"18.8") -> 742000 | F48: =E48/D48 -> 0.095803744
B49: 재능(CTP) | C49: =SUMIFS(INDIRECT("Report!F100:F10000"),INDIRECT("Report!B100:B10000"),B49,INDIRECT("report!H100:H10000"),"Others",INDIRECT("Report!L100:L10000"),"18.8") -> 45942600 | D49: =(C49/11*10) -> 41766000 | E49: =SUMIFS(INDIRECT("Report!J100:J10000"),INDIRECT("Report!B100:B10000"),B49,INDIRECT("report!H100:H10000"),"Others",INDIRECT("Report!L100:L10000"),"18.8") -> 13553000 | F49: =E49/D49 -> 0.3244984
B50: 보문특수칼라 | C50: =SUMIFS(INDIRECT("Report!F100:F10000"),INDIRECT("Report!B100:B10000"),B50,INDIRECT("report!H100:H10000"),"Others",INDIRECT("Report!L100:L10000"),"18.8") -> 31900000 | D50: =(C50/11*10) -> 29000000 | E50: =SUMIFS(INDIRECT("Report!J100:J10000"),INDIRECT("Report!B100:B10000"),B50,INDIRECT("report!H100:H10000"),"Others",INDIRECT("Report!L100:L10000"),"18.8") -> 4129308 | F50: =E50/D50 -> 0.14238993 | G50: 조색 소프트웨어 부장님 마진 10% = | H50: =E50*0.1 -> 412930.8
B51: 부일인쇄 | C51: =SUMIFS(INDIRECT("Report!F100:F10000"),INDIRECT("Report!B100:B10000"),B51,INDIRECT("report!H100:H10000"),"Others",INDIRECT("Report!L100:L10000"),"18.8") -> 1287000 | D51: =(C51/11*10) -> 1170000 | F51: =E51/D51 -> 0 | G51: 솔레노이드 코일
C52: =SUM(C48:C51) -> 87649100 | D52: =SUM(D48:D51) -> 79681000
A53: 2018.9 | B53: 재능(Ink) | C53: =SUMIFS(INDIRECT("Report!F100:F10000"),INDIRECT("Report!B100:B10000"),B53,INDIRECT("report!H100:H10000"),"Others",INDIRECT("Report!L100:L10000"),"18.9") -> 15412100 | D53: =(C53/11*10) -> 14011000 | E53: =SUMIFS(INDIRECT("Report!J100:J10000"),INDIRECT("Report!B100:B10000"),B53,INDIRECT("report!H100:H10000"),"Others",INDIRECT("Report!L100:L10000"),"18.9") -> 1368000 | F53: =E53/D53 -> 0.09763757
B54: 재능(CTP) | C54: =SUMIFS(INDIRECT("Report!F100:F10000"),INDIRECT("Report!B100:B10000"),B54,INDIRECT("report!H100:H10000"),"Others",INDIRECT("Report!L100:L10000"),"18.9") -> 42666800 | D54: =(C54/11*10) -> 38788000 | E54: =SUMIFS(INDIRECT("Report!J100:J10000"),INDIRECT("Report!B100:B10000"),B54,INDIRECT("report!H100:H10000"),"Others",INDIRECT("Report!L100:L10000"),"18.9") -> 12330000 | F54: =E54/D54 -> 0.31788182
B55: 재능 | C55: =SUMIFS(INDIRECT("Report!F100:F10000"),INDIRECT("Report!B100:B10000"),B55,INDIRECT("report!H100:H10000"),"Others",INDIRECT("Report!L100:L10000"),"18.9") -> 4400000 | D55: =(C55/11*10) -> 4000000 | E55: =SUMIFS(INDIRECT("Report!J100:J10000"),INDIRECT("Report!B100:B10000"),B55,INDIRECT("report!H100:H10000"),"Others",INDIRECT("Report!L100:L10000"),"18.9") -> 4000000 | F55: =E55/D55 -> 1 | G55: OneVision 서비스 비용
C56: =SUM(C53:C55) -> 62478900 | D56: =SUM(D53:D55) -> 56799000 | E56: =SUM(E53:E55) -> 17698000
A57: 2018.1 | B57: 재능(Ink) | C57: =SUMIFS(INDIRECT("Report!F100:F10000"),INDIRECT("Report!B100:B10000"),B57,INDIRECT("report!H100:H10000"),"Others",INDIRECT("Report!L100:L10000"),"18,10") -> 16181000 | D57: =(C57/11*10) -> 14710000 | E57: =SUMIFS(INDIRECT("Report!J100:J10000"),INDIRECT("Report!B100:B10000"),B57,INDIRECT("report!H100:H10000"),"Others",INDIRECT("Report!L100:L10000"),"18,10") -> 857000 | F57: =E57/D57 -> 0.058259687
B58: 재능(CTP) | C58: =SUMIFS(INDIRECT("Report!F100:F10000"),INDIRECT("Report!B100:B10000"),B58,INDIRECT("report!H100:H10000"),"Others",INDIRECT("Report!L100:L10000"),"18,10") -> 59279000 | D58: =(C58/11*10) -> 53890000 | E58: =SUMIFS(INDIRECT("Report!J100:J10000"),INDIRECT("Report!B100:B10000"),B58,INDIRECT("report!H100:H10000"),"Others",INDIRECT("Report!L100:L10000"),"18,10") -> 17082000 | F58: =E58/D58 -> 0.31697903
B59: 매일경제 | C59: =SUMIFS(INDIRECT("Report!F100:F10000"),INDIRECT("Report!B100:B10000"),B59,INDIRECT("report!H100:H10000"),"Others",INDIRECT("Report!L100:L10000"),"18,10") -> 52737333 | D59: =(C59/11*10) -> 47943030 | E59: =SUMIFS(INDIRECT("Report!J100:J10000"),INDIRECT("Report!B100:B10000"),B59,INDIRECT("report!H100:H10000"),"Others",INDIRECT("Report!L100:L10000"),"18,10") -> 11643422 | F59: =E59/D59 -> 0.24285955 | G59: 클러치 부품
B60: 하이델베르그 | C60: =SUMIFS(INDIRECT("Report!F100:F10000"),INDIRECT("Report!B100:B10000"),B60,INDIRECT("report!H100:H10000"),"Others",INDIRECT("Report!L100:L10000"),"18,10") -> 11000000 | D60: =(C60/11*10) -> 10000000 | E60: 10000000 | F60: =E60/D60 -> 1 | G60: 매엽기 소개비
C61: =SUM(C57:C60) -> 139197333 | D61: =SUM(D57:D60) -> 126543030 | E61: =SUM(E57:E60) -> 39582422
A62: 2018.11 | B62: 재능(Ink) | C62: =SUMIFS(INDIRECT("Report!F100:F10000"),INDIRECT("Report!B100:B10000"),B62,INDIRECT("report!H100:H10000"),"Others",INDIRECT("Report!L100:L10000"),"18.11") -> 12094500 | D62: =(C62/11*10) -> 10995000 | E62: =SUMIFS(INDIRECT("Report!J100:J10000"),INDIRECT("Report!B100:B10000"),B62,INDIRECT("report!H100:H10000"),"Others",INDIRECT("Report!L100:L10000"),"18.11") -> 703000 | F62: =E62/D62 -> 0.063938154
B63: 재능(CTP) | C63: =SUMIFS(INDIRECT("Report!F100:F10000"),INDIRECT("Report!B100:B10000"),B63,INDIRECT("report!H100:H10000"),"Others",INDIRECT("Report!L100:L10000"),"18.11") -> 59080450 | D63: =(C63/11*10) -> 53709500 | E63: =SUMIFS(INDIRECT("Report!J100:J10000"),INDIRECT("Report!B100:B10000"),B63,INDIRECT("report!H100:H10000"),"Others",INDIRECT("Report!L100:L10000"),"18.11") -> 17729000 | F63: =E63/D63 -> 0.33009058
B64: 국제신문 | C64: =SUMIFS(INDIRECT("Report!F100:F10000"),INDIRECT("Report!B100:B10000"),B64,INDIRECT("report!H100:H10000"),"Others",INDIRECT("Report!L100:L10000"),"18.11") -> 9620092.9 | D64: =(C64/11*10) -> 8745539 | E64: =SUMIFS(INDIRECT("Report!J100:J10000"),INDIRECT("Report!B100:B10000"),B64,INDIRECT("report!H100:H10000"),"Others",INDIRECT("Report!L100:L10000"),"18.11") -> 3376896.6 | F64: =E64/D64 -> 0.3861279 | G64: GOSS 롤러
C65: =SUM(C62:C64) -> 80795043 | D65: =SUM(D62:D64) -> 73450039 | E65: =SUM(E62:E64) -> 21808897
A66: 2018.12 | B66: 재능(Ink) | C66: =SUMIFS(INDIRECT("Report!F100:F10000"),INDIRECT("Report!B100:B10000"),B66,INDIRECT("report!H100:H10000"),"Others",INDIRECT("Report!L100:L10000"),"18,12") -> 15416500 | D66: =(C66/11*10) -> 14015000 | E66: =SUMIFS(INDIRECT("Report!J100:J10000"),INDIRECT("Report!B100:B10000"),B66,INDIRECT("report!H100:H10000"),"Others",INDIRECT("Report!L100:L10000"),"18,12") -> 1053500 | F66: =E66/D66 -> 0.075169461
B67: 재능(CTP) | C67: =SUMIFS(INDIRECT("Report!F100:F10000"),INDIRECT("Report!B100:B10000"),B67,INDIRECT("report!H100:H10000"),"Others",INDIRECT("Report!L100:L10000"),"18,12") -> 60494500 | D67: =(C67/11*10) -> 54995000 | E67: =SUMIFS(INDIRECT("Report!J100:J10000"),INDIRECT("Report!B100:B10000"),B67,INDIRECT("report!H100:H10000"),"Others",INDIRECT("Report!L100:L10000"),"18,12") -> 17288000 | F67: =E67/D67 -> 0.31435585
B68: 매일경제 | C68: =SUMIFS(INDIRECT("Report!F100:F10000"),INDIRECT("Report!B100:B10000"),B68,INDIRECT("report!H100:H10000"),"Others",INDIRECT("Report!L100:L10000"),"18,12") -> 12213036 | D68: =(C68/11*10) -> 11102760 | E68: =SUMIFS(INDIRECT("Report!J100:J10000"),INDIRECT("Report!B100:B10000"),B68,INDIRECT("report!H100:H10000"),"Others",INDIRECT("Report!L100:L10000"),"18,12") -> 2298558.6 | F68: =E68/D68 -> 0.20702587 | G68: 클러치 부품(1개)
B69: 한국경제 | C69: =SUMIFS(INDIRECT("Report!F100:F10000"),INDIRECT("Report!B100:B10000"),B69,INDIRECT("report!H100:H10000"),"Others",INDIRECT("Report!L100:L10000"),"18,12") -> 8096110 | D69: =(C69/11*10) -> 7360100 | E69: =SUMIFS(INDIRECT("Report!J100:J10000"),INDIRECT("Report!B100:B10000"),B69,INDIRECT("report!H100:H10000"),"Others",INDIRECT("Report!L100:L10000"),"18,12") -> 0 | G69: 유압전자변 부품(납품전)
B70: 재능 | C70: =SUMIFS(INDIRECT("Report!F100:F10000"),INDIRECT("Report!B100:B10000"),B70,INDIRECT("report!H100:H10000"),"Others",INDIRECT("Report!L100:L10000"),"18,12") -> 49500000 | D70: =(C70/11*10) -> 45000000 | E70: =SUMIFS(INDIRECT("Report!J100:J10000"),INDIRECT("Report!B100:B10000"),B70,INDIRECT("report!H100:H10000"),"Others",INDIRECT("Report!L100:L10000"),"18,12") -> 0 | G70: 판 절곡기
B71: ASPT | C71: =SUMIFS(INDIRECT("Report!F100:F10000"),INDIRECT("Report!B100:B10000"),B71,INDIRECT("report!H100:H10000"),"Others",INDIRECT("Report!L100:L10000"),"18,12") -> 89739006 | D71: =(C71/11*10) -> 81580915 | E71: =SUMIFS(INDIRECT("Report!J100:J10000"),INDIRECT("Report!B100:B10000"),B71,INDIRECT("report!H100:H10000"),"Others",INDIRECT("Report!L100:L10000"),"18,12") -> 0 | G71: Vpak 블랑켓, 플렉소 슬리브, 아니록스 롤러
C72: =SUM(C66:C71) -> 2.3545915e+08 | D72: =SUM(D66:D71) -> 214053775 | E72: =SUM(E66:E71) -> 20640059
A73: 2019,1 | B73: 재능(Ink) | C73: =SUMIFS(INDIRECT("Report!F100:F10000"),INDIRECT("Report!B100:B10000"),B73,INDIRECT("report!H100:H10000"),"Others",INDIRECT("Report!L100:L10000"),"19,1") -> 14289000 | D73: =(C73/11*10) -> 12990000 | E73: =SUMIFS(INDIRECT("Report!J100:J10000"),INDIRECT("Report!B100:B10000"),B73,INDIRECT("report!H100:H10000"),"Others",INDIRECT("Report!L100:L10000"),"19,1") -> 1020000 | F73: =E73/D73 -> 0.07852194
B74: 재능(CTP) | C74: =SUMIFS(INDIRECT("Report!F100:F10000"),INDIRECT("Report!B100:B10000"),B74,INDIRECT("report!H100:H10000"),"Others",INDIRECT("Report!L100:L10000"),"19,1") -> 74956200 | D74: =(C74/11*10) -> 68142000 | E74: =SUMIFS(INDIRECT("Report!J100:J10000"),INDIRECT("Report!B100:B10000"),B74,INDIRECT("report!H100:H10000"),"Others",INDIRECT("Report!L100:L10000"),"19,1") -> 22068500 | F74: =E74/D74 -> 0.32386047
B75: 매일경제 | C75: =SUMIFS(INDIRECT("Report!F100:F10000"),INDIRECT("Report!B100:B10000"),B75,INDIRECT("report!H100:H10000"),"Others",INDIRECT("Report!L100:L10000"),"19,1") -> 14738130 | D75: =(C75/11*10) -> 13398300 | E75: =SUMIFS(INDIRECT("Report!J100:J10000"),INDIRECT("Report!B100:B10000"),B75,INDIRECT("report!H100:H10000"),"Others",INDIRECT("Report!L100:L10000"),"19,1") -> 2629320.1 | F75: =E75/D75 -> 0.19624281 | G75: 클러치 부품(1개), 물로라기어(2개)
B76: ASPT | C76: =SUMIFS(INDIRECT("Report!F100:F10000"),INDIRECT("Report!B100:B10000"),B76,INDIRECT("report!H100:H10000"),"Others",INDIRECT("Report!L100:L10000"),"19,1") -> 12135750 | D76: =(C76/11*10) -> 11032500 | E76: =SUMIFS(INDIRECT("Report!J100:J10000"),INDIRECT("Report!B100:B10000"),B76,INDIRECT("report!H100:H10000"),"Others",INDIRECT("Report!L100:L10000"),"19,1") -> 2661190.6 | G76: 판, 플렉소유니트 부품 | H76: 플렉소 유니트 부품은 돈 받음
C77: =SUM(C73:C76) -> 116119080 | D77: =SUM(D73:D76) -> 105562800 | E77: =SUM(E73:E76) -> 28379011
A78: 2019,2 | B78: 재능(Ink) | C78: =SUMIFS(INDIRECT("Report!F100:F10000"),INDIRECT("Report!B100:B10000"),B78,INDIRECT("report!H100:H10000"),"Others",INDIRECT("Report!L100:L10000"),"19,2") -> 13455200 | D78: =(C78/11*10) -> 12232000 | E78: =SUMIFS(INDIRECT("Report!J100:J10000"),INDIRECT("Report!B100:B10000"),B78,INDIRECT("report!H100:H10000"),"Others",INDIRECT("Report!L100:L10000"),"19,2") -> 816000 | F78: =E78/D78 -> 0.066710268
B79: 재능(CTP) | C79: =SUMIFS(INDIRECT("Report!F100:F10000"),INDIRECT("Report!B100:B10000"),B79,INDIRECT("report!H100:H10000"),"Others",INDIRECT("Report!L100:L10000"),"19,2") -> 60826150 | D79: =(C79/11*10) -> 55296500 | E79: =SUMIFS(INDIRECT("Report!J100:J10000"),INDIRECT("Report!B100:B10000"),B79,INDIRECT("report!H100:H10000"),"Others",INDIRECT("Report!L100:L10000"),"19,2") -> 17902500 | F79: =E79/D79 -> 0.32375467
B80: 재능 | C80: =SUMIFS(INDIRECT("Report!F100:F10000"),INDIRECT("Report!B100:B10000"),B80,INDIRECT("report!H100:H10000"),"Others",INDIRECT("Report!L100:L10000"),"19,2") -> 0 | D80: =(C80/11*10) -> 0 | E80: =SUMIFS(INDIRECT("Report!J100:J10000"),INDIRECT("Report!B100:B10000"),B80,INDIRECT("report!H100:H10000"),"Others",INDIRECT("Report!L100:L10000"),"19,2") -> 0 | F80: =E80/D80 -> #DIV/0!
B81: 신창디지털 | C81: =SUMIFS(INDIRECT("Report!F100:F10000"),INDIRECT("Report!B100:B10000"),B81,INDIRECT("report!H100:H10000"),"Others",INDIRECT("Report!L100:L10000"),"19,2") -> 873400 | D81: =(C81/11*10) -> 794000 | E81: =SUMIFS(INDIRECT("Report!J100:J10000"),INDIRECT("Report!B100:B10000"),B81,INDIRECT("report!H100:H10000"),"Others",INDIRECT("Report!L100:L10000"),"19,2") -> 305941.72 | F81: =E81/D81 -> 0.38531703
C82: =SUM(C78:C81) -> 75154750 | D82: =SUM(D78:D81) -> 68322500 | E82: =SUM(E78:E81) -> 19024442
A83: 2019,3 | B83: 재능(Ink) | C83: =SUMIFS(INDIRECT("Report!F100:F10000"),INDIRECT("Report!B100:B10000"),B83,INDIRECT("report!H100:H10000"),"Others",INDIRECT("Report!L100:L10000"),"19,3") -> 22600380 | D83: =(C83/11*10) -> 20545800 | E83: =SUMIFS(INDIRECT("Report!J100:J10000"),INDIRECT("Report!B100:B10000"),B83,INDIRECT("report!H100:H10000"),"Others",INDIRECT("Report!L100:L10000"),"19,3") -> 1030900 | F83: =E83/D83 -> 0.050175705
B84: 재능(CTP) | C84: =SUMIFS(INDIRECT("Report!F100:F10000"),INDIRECT("Report!B100:B10000"),B84,INDIRECT("report!H100:H10000"),"Others",INDIRECT("Report!L100:L10000"),"19,3") -> 67328800 | D84: =(C84/11*10) -> 61208000 | E84: =SUMIFS(INDIRECT("Report!J100:J10000"),INDIRECT("Report!B100:B10000"),B84,INDIRECT("report!H100:H10000"),"Others",INDIRECT("Report!L100:L10000"),"19,3") -> 19840000 | F84: =E84/D84 -> 0.32414064
B85: 매일경제 | C85: =SUMIFS(INDIRECT("Report!F100:F10000"),INDIRECT("Report!B100:B10000"),B85,INDIRECT("report!H100:H10000"),"Others",INDIRECT("Report!L100:L10000"),"19,3") -> 880000 | D85: =(C85/11*10) -> 800000 | E85: =SUMIFS(INDIRECT("Report!J100:J10000"),INDIRECT("Report!B100:B10000"),B85,INDIRECT("report!H100:H10000"),"Others",INDIRECT("Report!L100:L10000"),"19,3") -> 200000 | F85: =E85/D85 -> 0.25 | G85: CTP 베어링
B86: ASPT | C86: =SUMIFS(INDIRECT("Report!F100:F10000"),INDIRECT("Report!B100:B10000"),B86,INDIRECT("report!H100:H10000"),"Others",INDIRECT("Report!L100:L10000"),"19,3") -> 6831000 | D86: =(C86/11*10) -> 6210000 | E86: =SUMIFS(INDIRECT("Report!J100:J10000"),INDIRECT("Report!B100:B10000"),B86,INDIRECT("report!H100:H10000"),"Others",INDIRECT("Report!L100:L10000"),"19,3") -> 4014000 | F86: =E86/D86 -> 0.64637681 | G86: 플렉소 소모품 | H86: 돈 받음
C87: =SUM(C83:C86) -> 97640180 | D87: =SUM(D83:D86) -> 88763800 | E87: =SUM(E83:E86) -> 25084900
A88: 2019,4 | B88: 재능(Ink) | C88: =SUMIFS(INDIRECT("Report!F100:F10000"),INDIRECT("Report!B100:B10000"),B88,INDIRECT("report!H100:H10000"),"Others",INDIRECT("Report!L100:L10000"),"19,4") -> 28238980 | D88: =(C88/11*10) -> 25671800 | E88: =SUMIFS(INDIRECT("Report!J100:J10000"),INDIRECT("Report!B100:B10000"),B88,INDIRECT("report!H100:H10000"),"Others",INDIRECT("Report!L100:L10000"),"19,4") -> 1479700 | F88: =E88/D88 -> 0.057639122
B89: 재능(CTP) | C89: =SUMIFS(INDIRECT("Report!F100:F10000"),INDIRECT("Report!B100:B10000"),B89,INDIRECT("report!H100:H10000"),"Others",INDIRECT("Report!L100:L10000"),"19,4") -> 76148050 | D89: =(C89/11*10) -> 69225500 | E89: =SUMIFS(INDIRECT("Report!J100:J10000"),INDIRECT("Report!B100:B10000"),B89,INDIRECT("report!H100:H10000"),"Others",INDIRECT("Report!L100:L10000"),"19,4") -> 22433500 | F89: =E89/D89 -> 0.32406411
B90: 한국경제신문 | C90: =SUMIFS(INDIRECT("Report!F100:F10000"),INDIRECT("Report!B100:B10000"),B90,INDIRECT("report!H100:H10000"),"Others",INDIRECT("Report!L100:L10000"),"19,4") -> 3592600 | D90: =(C90/11*10) -> 3266000 | E90: =SUMIFS(INDIRECT("Report!J100:J10000"),INDIRECT("Report!B100:B10000"),B90,INDIRECT("report!H100:H10000"),"Others",INDIRECT("Report!L100:L10000"),"19,4") -> 1067440 | F90: =E90/D90 -> 0.32683405 | G90: Technotrans 부품
B91: ASPT | C91: =SUMIFS(INDIRECT("Report!F100:F10000"),INDIRECT("Report!B100:B10000"),B91,INDIRECT("report!H100:H10000"),"Others",INDIRECT("Report!L100:L10000"),"19,4") -> 7128000 | D91: =(C91/11*10) -> 6480000 | E91: =SUMIFS(INDIRECT("Report!J100:J10000"),INDIRECT("Report!B100:B10000"),B91,INDIRECT("report!H100:H10000"),"Others",INDIRECT("Report!L100:L10000"),"19,4") -> 2070000 | F91: =E91/D91 -> 0.31944444 | G91: CTP 소모품 | H91: 돈 못받음
C92: =SUM(C88:C91) -> 115107630 | D92: =SUM(D88:D91) -> 104643300 | E92: =SUM(E88:E91) -> 27050640
A93: 2019,5 | B93: 재능(Ink) | C93: =SUMIFS(INDIRECT("Report!F100:F10000"),INDIRECT("Report!B100:B10000"),B93,INDIRECT("report!H100:H10000"),"Others",INDIRECT("Report!L100:L10000"),"19,5") -> 12582900 | D93: =(C93/11*10) -> 11439000 | E93: =SUMIFS(INDIRECT("Report!J100:J10000"),INDIRECT("Report!B100:B10000"),B93,INDIRECT("report!H100:H10000"),"Others",INDIRECT("Report!L100:L10000"),"19,5") -> 813000 | F93: =E93/D93 -> 0.071072646
B94: 재능(CTP) | C94: =SUMIFS(INDIRECT("Report!F100:F10000"),INDIRECT("Report!B100:B10000"),B94,INDIRECT("report!H100:H10000"),"Others",INDIRECT("Report!L100:L10000"),"19,5") -> 58795000 | D94: =(C94/11*10) -> 53450000 | E94: =SUMIFS(INDIRECT("Report!J100:J10000"),INDIRECT("Report!B100:B10000"),B94,INDIRECT("report!H100:H10000"),"Others",INDIRECT("Report!L100:L10000"),"19,5") -> 17620000 | F94: =E94/D94 -> 0.32965388
B95: 매일경제 | C95: =SUMIFS(INDIRECT("Report!F100:F10000"),INDIRECT("Report!B100:B10000"),B95,INDIRECT("report!H100:H10000"),"Others",INDIRECT("Report!L100:L10000"),"19,5") -> 12330879 | D95: =(C95/11*10) -> 11209890 | E95: =SUMIFS(INDIRECT("Report!J100:J10000"),INDIRECT("Report!B100:B10000"),B95,INDIRECT("report!H100:H10000"),"Others",INDIRECT("Report!L100:L10000"),"19,5") -> 3906469.3 | F95: =E95/D95 -> 0.34848418 | G95: goss water crutch
B96: ASPT | C96: =SUMIFS(INDIRECT("Report!F100:F10000"),INDIRECT("Report!B100:B10000"),B96,INDIRECT("report!H100:H10000"),"Others",INDIRECT("Report!L100:L10000"),"19,5") -> 1969000 | D96: =(C96/11*10) -> 1790000 | E96: =SUMIFS(INDIRECT("Report!J100:J10000"),INDIRECT("Report!B100:B10000"),B96,INDIRECT("report!H100:H10000"),"Others",INDIRECT("Report!L100:L10000"),"19,5") -> 768000 | F96: =E96/D96 -> 0.42905028 | G96: CTP 판 | H96: 돈 받음
C97: =SUM(C93:C96) -> 85677779 | D97: =SUM(D93:D96) -> 77888890 | E97: =SUM(E93:E96) -> 23107469
A98: 2019,6 | B98: 재능(Ink) | C98: =SUMIFS(INDIRECT("Report!F100:F10000"),INDIRECT("Report!B100:B10000"),B98,INDIRECT("report!H100:H10000"),"Others",INDIRECT("Report!L100:L10000"),"19,6") -> 12474000 | D98: =(C98/11*10) -> 11340000 | E98: =SUMIFS(INDIRECT("Report!J100:J10000"),INDIRECT("Report!B100:B10000"),B98,INDIRECT("report!H100:H10000"),"Others",INDIRECT("Report!L100:L10000"),"19,6") -> 1015500 | F98: =E98/D98 -> 0.089550265
B99: 재능(CTP) | C99: =SUMIFS(INDIRECT("Report!F100:F10000"),INDIRECT("Report!B100:B10000"),B99,INDIRECT("report!H100:H10000"),"Others",INDIRECT("Report!L100:L10000"),"19,6") -> 60119400 | D99: =(C99/11*10) -> 54654000 | E99: =SUMIFS(INDIRECT("Report!J100:J10000"),INDIRECT("Report!B100:B10000"),B99,INDIRECT("report!H100:H10000"),"Others",INDIRECT("Report!L100:L10000"),"19,6") -> 19318000 | F99: =E99/D99 -> 0.35345995
B100: 프린피아 주안 | C100: =SUMIFS(INDIRECT("Report!F100:F10000"),INDIRECT("Report!B100:B10000"),B100,INDIRECT("report!H100:H10000"),"Others",INDIRECT("Report!L100:L10000"),"19,6") -> 1.0281271e+08 | D100: =(C100/11*10) -> 93466100 | E100: =SUMIFS(INDIRECT("Report!J100:J10000"),INDIRECT("Report!B100:B10000"),B100,INDIRECT("report!H100:H10000"),"Others",INDIRECT("Report!L100:L10000"),"19,6") -> 3553510 | F100: =E100/D100 -> 0.038019239 | G100: Pecom 업그레이드
...

Sheet Report
A1: Date | B1: Customer | C1: Item | D1: Qtt | E1: Price | F1: Sales(Tax) | G1: Sales(NonTax) | H1: Type1 | I1: Type2 | J1: Margin | K1: Margin (%) | L1: Month | M1: 비고 | N1: Date | O1: Order | P1: Item | Q1: Qtt | R1: Purchasing Price | S1: Total Purchase | T1: Total Purchase (Non Tax) | U1: 택배비 | V1: 비고 | W1: Margin (check) | X1: 수입
A2: 2017.5 | B2: 매출 | O2: 매입
A3: 170421 | B3: 재능 | C3: M-600 서비스 비용 | H3: Service | L3: 17.5 | M3: 계약시간 6시간 공제 | N3: =A3 -> 170421 | O3: Agfa | P3: =(C3) -> M-600 서비스 비용 | Q3: =D3 -> 0 | R3: 2740 | S3: =(R3*D3)*1.1 -> 0 | T3: =(R3*Q3) -> 0 | U3: =IF(J3=W3,"O", "X") -> O | W3: =(G3-T3) -> 0
A4: 170424 | B4: 재능 | C4: M-600 서비스 비용 | H4: Service | L4: 17.5 | M4: 계약시간 4시간 공제 | N4: =A4 -> 170424 | O4: Agfa | P4: =(C4) -> M-600 서비스 비용 | Q4: =D4 -> 0 | R4: 2740 | S4: =(R4*D4)*1.1 -> 0 | T4: =(R4*Q4) -> 0 | U4: =IF(J4=W4,"O", "X") -> O | W4: =(G4-T4) -> 0
A5: 170428 | B5: 세흥인쇄 | C5: Agfa Film(24inch) | D5: 2 | E5: 327000 | F5: =(E5*D5)*1.1 -> 719400 | G5: =(E5*D5) -> 654000 | H5: Consums | I5: Film | J5: =(G5-(VLOOKUP(C5,Price!B:D,3,FALSE)*D5)) -> 115800 | K5: =(J5/(G5/11*10)) -> 0.19477064 | L5: 17.5 | N5: =A5 -> 170428 | O5: Agfa | P5: =(C5) -> Agfa Film(24inch) | Q5: =D5 -> 2 | R5: 269100 | S5: =(R5*D5)*1.1 -> 592020 | T5: =(R5*Q5) -> 538200 | U5: =IF(J5=W5,"O", "X") -> O | W5: =(G5-T5) -> 115800
A6: 170428 | B6: 세흥인쇄 | C6: Agfa Film(28inch) | D6: 2 | E6: 401000 | F6: =(E6*D6)*1.1 -> 882200 | G6: =(E6*D6) -> 802000 | H6: Consums | I6: Film | J6: =(G6-(VLOOKUP(C6,Price!B:D,3,FALSE)*D6)) -> 174080 | K6: =(J6/(F6/11*10)) -> 0.21705736 | L6: 17.5 | N6: =A6 -> 170428 | O6: Agfa | P6: =(C6) -> Agfa Film(28inch) | Q6: =D6 -> 2 | R6: 313960 | S6: =(R6*D6)*1.1 -> 690712 | T6: =(R6*Q6) -> 627920 | U6: =IF(J6=W6,"O", "X") -> O | W6: =(G6-T6) -> 174080
A7: 170428 | B7: 세흥인쇄 | C7: Agfa Film(32inch) | D7: 2 | E7: 448000 | F7: =(E7*D7)*1.1 -> 985600 | G7: =(E7*D7) -> 896000 | H7: Consums | I7: Film | J7: =(G7-(VLOOKUP(C7,Price!B:D,3,FALSE)*D7)) -> 155980 | K7: =(J7/(F7/11*10)) -> 0.17408482 | L7: 17.5 | N7: =A7 -> 170428 | O7: Agfa | P7: =(C7) -> Agfa Film(32inch) | Q7: =D7 -> 2 | R7: 370010 | S7: =(R7*D7)*1.1 -> 814022 | T7: =(R7*Q7) -> 740020 | U7: =IF(J7=W7,"O", "X") -> O | W7: =(G7-T7) -> 155980
A8: 170428 | B8: 세흥인쇄 | C8: Agfa 현상액 G101C(10L) | D8: 2 | E8: 41000 | F8: =(E8*D8)*1.1 -> 90200 | G8: =(E8*D8) -> 82000 | H8: Consums | I8: Film | J8: =(G8-(VLOOKUP(C8,Price!B:D,3,FALSE)*D8)) -> 32000 | K8: =(J8/(F8/11*10)) -> 0.3902439 | L8: 17.5 | N8: =A8 -> 170428 | O8: Agfa | P8: =(C8) -> Agfa 현상액 G101C(10L) | Q8: =D8 -> 2 | R8: 25000 | S8: =(R8*D8)*1.1 -> 55000 | T8: =(R8*Q8) -> 50000 | U8: =IF(J8=W8,"O", "X") -> O | W8: =(G8-T8) -> 32000
A9: 170428 | B9: 세흥인쇄 | C9: Agfa 정착액 G333C(20L) | D9: 1 | E9: 93000 | F9: =(E9*D9)*1.1 -> 102300 | G9: =(E9*D9) -> 93000 | H9: Consums | I9: Film | J9: =(G9-(VLOOKUP(C9,Price!B:D,3,FALSE)*D9)) -> 33000 | K9: =(J9/(F9/11*10)) -> 0.35483871 | L9: 17.5 | N9: =A9 -> 170428 | O9: Agfa | P9: =(C9) -> Agfa 정착액 G333C(20L) | Q9: =D9 -> 1 | R9: 60000 | S9: =(R9*D9)*1.1 -> 66000 | T9: =(R9*Q9) -> 60000 | U9: =IF(J9=W9,"O", "X") -> O | W9: =(G9-T9) -> 33000
A10: 170502 | B10: 금강인쇄 | C10: Blanket(1050*840) | D10: 20 | E10: 100000 | F10: =(E10*D10)*1.1 -> 2200000 | G10: =(E10*D10) -> 2000000 | H10: Consums | I10: Blanket | J10: =(G10-(VLOOKUP(C10,Price!B:D,3,FALSE)*D10)) -> 390000 | K10: =(J10/(F10/11*10)) -> 0.195 | L10: 17.5 | N10: =A10 -> 170502 | O10: 동양잉크 | P10: =(C10) -> Blanket(1050*840) | Q10: =D10 -> 20 | R10: 80500 | S10: =(R10*D10)*1.1 -> 1771000 | T10: =(R10*Q10) -> 1610000 | U10: =IF(J10=W10,"O", "X") -> O | W10: =(G10-T10) -> 390000
A11: 170502 | B11: 재능 | C11: ENGAGE 27 900X570MM WE | D11: 1200 | E11: 3990 | F11: =(E11*D11)*1.1 -> 5266800 | G11: =(E11*D11) -> 4788000 | H11: Consums | I11: CTP | J11: =(G11-(VLOOKUP(C11,Price!B:D,3,FALSE)*D11)) -> 1500000 | K11: =(J11/(F11/11*10)) -> 0.31328321 | L11: 17.5 | N11: =A11 -> 170502 | O11: Agfa | P11: =(C11) -> ENGAGE 27 900X570MM WE | Q11: =D11 -> 1200 | R11: 2740 | S11: =(R11*D11)*1.1 -> 3616800 | T11: =(R11*Q11) -> 3288000 | U11: =IF(J11=W11,"O", "X") -> O | W11: =(G11-T11) -> 1500000
A12: 170509 | B12: 덕수 | C12: Blanket(1060*860) | D12: 10 | E12: 110000 | F12: =(E12*D12)*1.1 -> 1210000 | G12: =(E12*D12) -> 1100000 | H12: Consums | I12: Blanket | J12: =(G12-(VLOOKUP(C12,Price!B:D,3,FALSE)*D12)) -> 271000 | K12: =(J12/(F12/11*10)) -> 0.24636364 | L12: 17.5 | N12: =A12 -> 170509 | O12: 동양잉크 | P12: =(C12) -> Blanket(1060*860) | Q12: =D12 -> 10 | R12: 82900 | S12: =(R12*D12)*1.1 -> 911900 | T12: =(R12*Q12) -> 829000 | U12: =IF(J12=W12,"O", "X") -> O | W12: =(G12-T12) -> 271000
A13: 170509 | B13: 덕수 | C13: UV wash(20L) | D13: 5 | E13: 135000 | F13: =(E13*D13)*1.1 -> 742500 | G13: =(E13*D13) -> 675000 | H13: Consums | I13: Wash | J13: =(G13-(VLOOKUP(C13,Price!B:D,3,FALSE)*D13)) -> 125000 | K13: =(J13/(F13/11*10)) -> 0.18518519 | L13: 17.5 | N13: =A13 -> 170509 | O13: 붸처코리아 | P13: =(C13) -> UV wash(20L) | Q13: =D13 -> 5 | R13: 110000 | S13: =(R13*D13)*1.1 -> 605000 | T13: =(R13*Q13) -> 550000 | U13: =IF(J13=W13,"O", "X") -> O | W13: =(G13-T13) -> 125000
A14: 170510 | B14: 매일경제 | C14: Fount Web 551AF | D14: 10 | E14: 235000 | F14: =(E14*D14)*1.1 -> 2585000 | G14: =(E14*D14) -> 2350000 | H14: Consums | I14: Fount | J14: =(G14-(VLOOKUP(C14,Price!B:D,3,FALSE)*D14)) -> 1225000 | K14: =(J14/(F14/11*10)) -> 0.5212766 | L14: 17.5 | N14: =A14 -> 170510 | O14: 하이델베르그 | P14: =(C14) -> Fount Web 551AF | Q14: =D14 -> 10 | R14: 112500 | S14: =(R14*D14)*1.1 -> 1237500 | T14: =(R14*Q14) -> 1125000 | U14: =IF(J14=W14,"O", "X") -> O | W14: =(G14-T14) -> 1225000
A15: 170511 | B15: 대일프린텍 | C15: 고무사카 회색 | D15: 100 | E15: 500 | F15: =(E15*D15)*1.1 -> 55000 | G15: =(E15*D15) -> 50000 | H15: Consums | I15: Others | J15: =(G15-(VLOOKUP(C15,Price!B:D,3,FALSE)*D15)) -> 18000 | K15: =(J15/(F15/11*10)) -> 0.36 | L15: 17.5 | N15: =A15 -> 170511 | O15: 하이델베르그 | P15: =(C15) -> 고무사카 회색 | Q15: =D15 -> 100 | R15: 320 | S15: =(R15*D15)*1.1 -> 35200 | T15: =(R15*Q15) -> 32000 | U15: =IF(J15=W15,"O", "X") -> O | W15: =(G15-T15) -> 18000
A16: 170511 | B16: 대일프린텍 | C16: 고무사카 빨간색 | D16: 100 | E16: 500 | F16: =(E16*D16)*1.1 -> 55000 | G16: =(E16*D16) -> 50000 | H16: Consums | I16: Others | J16: =(G16-(VLOOKUP(C16,Price!B:D,3,FALSE)*D16)) -> 18000 | K16: =(J16/(F16/11*10)) -> 0.36 | L16: 17.5 | N16: =A16 -> 170511 | O16: 하이델베르그 | P16: =(C16) -> 고무사카 빨간색 | Q16: =D16 -> 100 | R16: 320 | S16: =(R16*D16)*1.1 -> 35200 | T16: =(R16*Q16) -> 32000 | U16: =IF(J16=W16,"O", "X") -> O | W16: =(G16-T16) -> 18000
A17: 170511 | B17: 팩컴 AAP | C17: 삼각판 코 | D17: 1 | E17: 5400000 | F17: =(E17*D17)*1.1 -> 5940000 | G17: =(E17*D17) -> 5400000 | H17: Goss | J17: =(G17-(VLOOKUP(C17,Price!B:D,3,FALSE)*D17)) -> 2221350 | K17: =(J17/(F17/11*10)) -> 0.41136111 | L17: 17.5 | N17: =A17 -> 170511 | O17: Goss | P17: =(C17) -> 삼각판 코 | Q17: =D17 -> 1 | R17: 3178650 | S17: =(R17*D17)*1.1 -> 3496515 | T17: =(R17*Q17) -> 3178650 | U17: =IF(J17=W17,"O", "X") -> O | W17: =(G17-T17) -> 2221350
A18: 170511 | B18: HnP | C18: 스트리퍼 | D18: 50 | E18: 12000 | F18: =(E18*D18)*1.1 -> 660000 | G18: =(E18*D18) -> 600000 | H18: Goss | J18: =(G18-(VLOOKUP(C18,Price!B:D,3,FALSE)*D18)) -> 150000 | K18: =(J18/(F18/11*10)) -> 0.25 | L18: 17.5 | N18: =A18 -> 170511 | O18: Goss | P18: =(C18) -> 스트리퍼 | Q18: =D18 -> 50 | R18: 6320 | S18: =(R18*D18)*1.1 -> 347600 | T18: =(R18*Q18) -> 316000 | U18: =IF(J18=W18,"O", "X") -> X | W18: =(G18-T18) -> 284000
A19: 170511 | B19: 프린피아 파주 | C19: 샤프트 잠금장치 | D19: 1 | E19: 850000 | F19: =(E19*D19)*1.1 -> 935000 | G19: =(E19*D19) -> 850000 | H19: Goss | J19: =(G19-(VLOOKUP(C19,Price!B:D,3,FALSE)*D19)) -> 423630 | K19: =(J19/(F19/11*10)) -> 0.49838824 | L19: 17.5 | N19: =A19 -> 170511 | O19: Goss | P19: =(C19) -> 샤프트 잠금장치 | Q19: =D19 -> 1 | R19: 426370 | S19: =(R19*D19)*1.1 -> 469007 | T19: =(R19*Q19) -> 426370 | U19: =IF(J19=W19,"O", "X") -> O | W19: =(G19-T19) -> 423630
A20: 170516 | B20: 퍼시픽패키지 | C20: 아스테이지(국전) | D20: 5 | E20: 100000 | F20: =(E20*D20)*1.1 -> 550000 | G20: =(E20*D20) -> 500000 | H20: Consums | I20: Others | J20: =(G20-(VLOOKUP(C20,Price!B:D,3,FALSE)*D20)) -> 250000 | K20: =(J20/(F20/11*10)) -> 0.5 | L20: 17.5 | N20: =A20 -> 170516 | O20: 대우피앤시 | P20: =(C20) -> 아스테이지(국전) | Q20: =D20 -> 5 | R20: 50000 | S20: =(R20*D20)*1.1 -> 275000 | T20: =(R20*Q20) -> 250000 | U20: =IF(J20=W20,"O", "X") -> O | W20: =(G20-T20) -> 250000
B21: 동양인쇄재료상사 | C21: 로랜드 Blanket(1050*910) | D21: 10 | E21: 128500 | F21: =(E21*D21)*1.1 -> 1413500 | G21: =(E21*D21) -> 1285000 | H21: Consums | I21: Blanket | J21: =(G21-(VLOOKUP(C21,Price!B:D,3,FALSE)*D21)) -> 385000 | K21: =(J21/(F21/11*10)) -> 0.29961089 | L21: 17.5 | N21: =A21 -> 0 | O21: 하이델베르그 | P21: =(C21) -> 로랜드 Blanket(1050*910) | Q21: =D21 -> 10 | R21: 90000 | S21: =(R21*D21)*1.1 -> 990000 | T21: =(R21*Q21) -> 900000 | U21: =IF(J21=W21,"O", "X") -> O | W21: =(G21-T21) -> 385000
B22: 동양인쇄재료상사 | C22: 미쯔비시 Blanket(1035*910) | D22: 5 | E22: 115000 | F22: =(E22*D22)*1.1 -> 632500 | G22: =(E22*D22) -> 575000 | H22: Consums | I22: Blanket | J22: =(G22-(VLOOKUP(C22,Price!B:D,3,FALSE)*D22)) -> 131500 | K22: =(J22/(F22/11*10)) -> 0.22869565 | L22: 17.5 | N22: =A22 -> 0 | O22: 하이델베르그 | P22: =(C22) -> 미쯔비시 Blanket(1035*910) | Q22: =D22 -> 5 | R22: 88700 | S22: =(R22*D22)*1.1 -> 487850 | T22: =(R22*Q22) -> 443500 | U22: =IF(J22=W22,"O", "X") -> O | W22: =(G22-T22) -> 131500
B23: 동양인쇄재료상사 | C23: Fount 511 | D23: 15 | E23: 112500 | F23: =(E23*D23)*1.1 -> 1856250 | G23: =(E23*D23) -> 1687500 | H23: Consums | I23: Fount | J23: =(G23-(VLOOKUP(C23,Price!B:D,3,FALSE)*D23)) -> 487500 | K23: =(J23/(F23/11*10)) -> 0.28888889 | L23: 17.5 | N23: =A23 -> 0 | O23: 하이델베르그 | P23: =(C23) -> Fount 511 | Q23: =D23 -> 15 | R23: 80000 | S23: =(R23*D23)*1.1 -> 1320000 | T23: =(R23*Q23) -> 1200000 | U23: =IF(J23=W23,"O", "X") -> O | W23: =(G23-T23) -> 487500
B24: 프린피아 주안 | C24: 윤전용 실리콘 | D24: 10 | E24: 110000 | F24: =(E24*D24)*1.1 -> 1210000 | G24: =(E24*D24) -> 1100000 | H24: Consums | I24: Others | J24: =(G24-(VLOOKUP(C24,Price!B:D,3,FALSE)*D24)) -> 190000 | K24: =(J24/(F24/11*10)) -> 0.17272727 | L24: 17.5 | N24: =A24 -> 0 | O24: 하이델베르그 | P24: =(C24) -> 윤전용 실리콘 | Q24: =D24 -> 10 | R24: 91000 | S24: =(R24*D24)*1.1 -> 1001000 | T24: =(R24*Q24) -> 910000 | U24: =IF(J24=W24,"O", "X") -> O | W24: =(G24-T24) -> 190000
A25: 170517 | B25: 신한종합인쇄 | C25: 필터백 | D25: 2 | E25: 35000 | F25: =(E25*D25)*1.1 -> 77000 | G25: =(E25*D25) -> 70000 | H25: Technotrans | J25: =(G25-(VLOOKUP(C25,Price!B:D,3,FALSE)*D25)) -> 25078 | K25: =(J25/(F25/11*10)) -> 0.35825714 | L25: 17.5 | N25: =A25 -> 170517 | O25: Technotrans | P25: =(C25) -> 필터백 | Q25: =D25 -> 2 | R25: 19800 | S25: =(R25*D25)*1.1 -> 43560 | T25: =(R25*Q25) -> 39600 | U25: =IF(J25=W25,"O", "X") -> X | W25: =(G25-T25) -> 30400
B26: 국민피앤텍 | C26: 습수정화장치(beta.f) 필터세트 | D26: 1 | E26: 1100000 | F26: =(E26*D26)*1.1 -> 1210000 | G26: =(E26*D26) -> 1100000 | H26: Technotrans | J26: =(G26-(VLOOKUP(C26,Price!B:D,3,FALSE)*D26)) -> 556000 | K26: =(J26/(F26/11*10)) -> 0.50545455 | L26: 17.5 | N26: =A26 -> 0 | O26: Technotrans | P26: =(C26) -> 습수정화장치(beta.f) 필터세트 | Q26: =D26 -> 1 | R26: 544000 | S26: =(R26*D26)*1.1 -> 598400 | T26: =(R26*Q26) -> 544000 | U26: =IF(J26=W26,"O", "X") -> O | W26: =(G26-T26) -> 556000
A27: 170518 | B27: 덕수 | C27: Blanket(1060*860) | D27: 10 | E27: 110000 | F27: =(E27*D27)*1.1 -> 1210000 | G27: =(E27*D27) -> 1100000 | H27: Consums | I27: Blanket | J27: =(G27-(VLOOKUP(C27,Price!B:D,3,FALSE)*D27)) -> 271000 | K27: =(J27/(F27/11*10)) -> 0.24636364 | L27: 17.5 | N27: =A27 -> 170518 | O27: 동양잉크 | P27: =(C27) -> Blanket(1060*860) | Q27: =D27 -> 10 | R27: 82900 | S27: =(R27*D27)*1.1 -> 911900 | T27: =(R27*Q27) -> 829000 | U27: =IF(J27=W27,"O", "X") -> O | W27: =(G27-T27) -> 271000
B28: 덕수 | C28: UV wash(20L) | D28: 6 | E28: 135000 | F28: =(E28*D28)*1.1 -> 891000 | G28: =(E28*D28) -> 810000 | H28: Consums | I28: Wash | J28: =(G28-(VLOOKUP(C28,Price!B:D,3,FALSE)*D28)) -> 150000 | K28: =(J28/(F28/11*10)) -> 0.18518519 | L28: 17.5 | N28: =A28 -> 0 | O28: 붸처코리아 | P28: =(C28) -> UV wash(20L) | Q28: =D28 -> 6 | R28: 110000 | S28: =(R28*D28)*1.1 -> 726000 | T28: =(R28*Q28) -> 660000 | U28: =IF(J28=W28,"O", "X") -> O | W28: =(G28-T28) -> 150000
B29: 프린피아 문발 | C29: Blanket(1050*840) | D29: 5 | E29: 108000 | F29: =(E29*D29)*1.1 -> 594000 | G29: =(E29*D29) -> 540000 | H29: Consums | I29: Blanket | J29: =(G29-(VLOOKUP(C29,Price!B:D,3,FALSE)*D29)) -> 137500 | K29: =(J29/(F29/11*10)) -> 0.25462963 | L29: 17.5 | N29: =A29 -> 0 | O29: 동양잉크 | P29: =(C29) -> Blanket(1050*840) | Q29: =D29 -> 5 | R29: 80500 | S29: =(R29*D29)*1.1 -> 442750 | T29: =(R29*Q29) -> 402500 | U29: =IF(J29=W29,"O", "X") -> O | W29: =(G29-T29) -> 137500
B30: 프린피아 문발 | C30: Blanket(990*725) | D30: 5 | E30: 120000 | F30: =(E30*D30)*1.1 -> 660000 | G30: =(E30*D30) -> 600000 | H30: Consums | I30: Blanket | J30: =(G30-(VLOOKUP(C30,Price!B:D,3,FALSE)*D30)) -> 40000 | K30: =(J30/(F30/11*10)) -> 0.066666667 | L30: 17.5 | N30: =A30 -> 0 | O30: 화성메이저 | P30: =(C30) -> Blanket(990*725) | Q30: =D30 -> 5 | R30: 112000 | S30: =(R30*D30)*1.1 -> 616000 | T30: =(R30*Q30) -> 560000 | U30: =IF(J30=W30,"O", "X") -> O | W30: =(G30-T30) -> 40000
B31: 프린피아 문발 | C31: 윤전용 세척제(Web 504) | D31: 7 | E31: 172000 | F31: =(E31*D31)*1.1 -> 1324400 | G31: =(E31*D31) -> 1204000 | H31: Consums | I31: Wash | J31: =(G31-(VLOOKUP(C31,Price!B:D,3,FALSE)*D31)) -> 399000 | K31: =(J31/(F31/11*10)) -> 0.33139535 | L31: 17.5 | N31: =A31 -> 0 | O31: 하이델베르그 | P31: =(C31) -> 윤전용 세척제(Web 504) | Q31: =D31 -> 7 | R31: 115000 | S31: =(R31*D31)*1.1 -> 885500 | T31: =(R31*Q31) -> 805000 | U31: =IF(J31=W31,"O", "X") -> O | W31: =(G31-T31) -> 399000
B32: 프린피아 문발 | C32: 매엽용 세척제(Wash 562) | D32: 7 | E32: 59500 | F32: =(E32*D32)*1.1 -> 458150 | G32: =(E32*D32) -> 416500 | H32: Consums | I32: Wash | J32: =(G32-(VLOOKUP(C32,Price!B:D,3,FALSE)*D32)) -> 59500 | K32: =(J32/(F32/11*10)) -> 0.14285714 | L32: 17.5 | N32: =A32 -> 0 | O32: 하이델베르그 | P32: =(C32) -> 매엽용 세척제(Wash 562) | Q32: =D32 -> 7 | R32: 51000 | S32: =(R32*D32)*1.1 -> 392700 | T32: =(R32*Q32) -> 357000 | U32: =IF(J32=W32,"O", "X") -> O | W32: =(G32-T32) -> 59500
B33: 재능 | C33: ENGAGE 27 900X570MM WE | D33: 1000 | E33: 3990 | F33: =(E33*D33)*1.1 -> 4389000 | G33: =(E33*D33) -> 3990000 | H33: Consums | I33: CTP | J33: =(G33-(VLOOKUP(C33,Price!B:D,3,FALSE)*D33)) -> 1250000 | K33: =(J33/(F33/11*10)) -> 0.31328321 | L33: 17.5 | N33: =A33 -> 0 | O33: Agfa | P33: =(C33) -> ENGAGE 27 900X570MM WE | Q33: =D33 -> 1000 | R33: 2740 | S33: =(R33*D33)*1.1 -> 3014000 | T33: =(R33*Q33) -> 2740000 | U33: =IF(J33=W33,"O", "X") -> O | W33: =(G33-T33) -> 1250000
B34: 재능 | C34: THR200(20L) | D34: 10 | E34: 58000 | F34: =(E34*D34)*1.1 -> 638000 | G34: =(E34*D34) -> 580000 | H34: Consums | I34: CTP | J34: =(G34-(VLOOKUP(C34,Price!B:D,3,FALSE)*D34)) -> 230000 | K34: =(J34/(F34/11*10)) -> 0.39655172 | L34: 17.5 | N34: =A34 -> 0 | O34: Agfa | P34: =(C34) -> THR200(20L) | Q34: =D34 -> 10 | R34: 35000 | S34: =(R34*D34)*1.1 -> 385000 | T34: =(R34*Q34) -> 350000 | U34: =IF(J34=W34,"O", "X") -> O | W34: =(G34-T34) -> 230000
A35: 170522 | B35: 보광피앤피 | C35: 아니록스 롤러 | D35: 1 | E35: 9000000 | F35: =(E35*D35)*1.1 -> 9900000 | G35: =(E35*D35) -> 9000000 | H35: Consums | I35: Roller | J35: =(G35-(VLOOKUP(C35,Price!B:D,3,FALSE)*D35)) -> 2322094 | K35: =(J35/(F35/11*10)) -> 0.25801044 | L35: 17.5 | N35: =A35 -> 170522 | O35: Zecher | P35: =(C35) -> 아니록스 롤러 | Q35: =D35 -> 1 | R35: 6677906 | S35: =(R35*D35)*1.1 -> 7345696.6 | T35: =(R35*Q35) -> 6677906 | U35: =IF(J35=W35,"O", "X") -> O | W35: =(G35-T35) -> 2322094
B36: 대진PM | C36: 도져 필터세트 | D36: 1 | E36: 1700000 | F36: =(E36*D36)*1.1 -> 1870000 | G36: =(E36*D36) -> 1700000 | H36: Technotrans | J36: =(G36-(VLOOKUP(C36,Price!B:D,3,FALSE)*D36)) -> 600000 | K36: =(J36/(F36/11*10)) -> 0.35294118 | L36: 17.5 | N36: =A36 -> 0 | O36: Technotrans | P36: =(C36) -> 도져 필터세트 | Q36: =D36 -> 1 | R36: 1100000 | S36: =(R36*D36)*1.1 -> 1210000 | T36: =(R36*Q36) -> 1100000 | U36: =IF(J36=W36,"O", "X") -> O | W36: =(G36-T36) -> 600000
B37: 삼화인쇄 | C37: 재단목(Cutting Rubber) | D37: 10 | E37: 70000 | F37: =(E37*D37)*1.1 -> 770000 | G37: =(E37*D37) -> 700000 | H37: Goss | J37: =(G37-(VLOOKUP(C37,Price!B:D,3,FALSE)*D37)) -> 379360 | K37: =(J37/(F37/11*10)) -> 0.54194286 | L37: 17.5 | N37: =A37 -> 0 | O37: Goss | P37: =(C37) -> 재단목(Cutting Rubber) | Q37: =D37 -> 10 | R37: 32064 | S37: =(R37*D37)*1.1 -> 352704 | T37: =(R37*Q37) -> 320640 | U37: =IF(J37=W37,"O", "X") -> O | W37: =(G37-T37) -> 379360
A38: 170523 | B38: 신안테크 | C38: 필터백 | D38: 1 | E38: 30000 | F38: =(E38*D38)*1.1 -> 33000 | G38: =(E38*D38) -> 30000 | H38: Technotrans | J38: =(G38-(VLOOKUP(C38,Price!B:D,3,FALSE)*D38)) -> 7539 | K38: =(J38/(F38/11*10)) -> 0.2513 | L38: 17.5 | N38: =A38 -> 170523 | O38: Technotrans | P38: =(C38) -> 필터백 | Q38: =D38 -> 1 | R38: 19800 | S38: =(R38*D38)*1.1 -> 21780 | T38: =(R38*Q38) -> 19800 | U38: =IF(J38=W38,"O", "X") -> X | W38: =(G38-T38) -> 10200
A39: 170524 | B39: 세흥인쇄 | C39: 아스테이지(국전) | D39: 2 | E39: 110000 | F39: =(E39*D39)*1.1 -> 242000 | G39: =(E39*D39) -> 220000 | H39: Consums | I39: Others | J39: =(G39-(VLOOKUP(C39,Price!B:D,3,FALSE)*D39)) -> 120000 | K39: =(J39/(F39/11*10)) -> 0.54545455 | L39: 17.5 | N39: =A39 -> 170524 | O39: 대진PM | P39: =(C39) -> 아스테이지(국전) | Q39: =D39 -> 2 | R39: 50000 | S39: =(R39*D39)*1.1 -> 110000 | T39: =(R39*Q39) -> 100000 | U39: =IF(J39=W39,"O", "X") -> O | W39: =(G39-T39) -> 120000
B40: 세흥인쇄 | C40: 체인구리스(하이델) | D40: 2 | E40: 135000 | F40: =(E40*D40)*1.1 -> 297000 | G40: =(E40*D40) -> 270000 | H40: Consums | I40: Others | J40: =(G40-(VLOOKUP(C40,Price!B:D,3,FALSE)*D40)) -> 54000 | K40: =(J40/(F40/11*10)) -> 0.2 | L40: 17.5 | N40: =A40 -> 0 | O40: 하이델베르그 | P40: =(C40) -> 체인구리스(하이델) | Q40: =D40 -> 2 | R40: 108000 | S40: =(R40*D40)*1.1 -> 237600 | T40: =(R40*Q40) -> 216000 | U40: =IF(J40=W40,"O", "X") -> O | W40: =(G40-T40) -> 54000
A41: 170525 | B41: 세흥인쇄 | C41: 필름출력 현상기 롤라 | D41: 1 | E41: 790000 | F41: =(E41*D41)*1.1 -> 869000 | G41: =(E41*D41) -> 790000 | H41: Consums | I41: Roller | J41: =(G41-(VLOOKUP(C41,Price!B:D,3,FALSE)*D41)) -> 160000 | K41: =(J41/(F41/11*10)) -> 0.20253165 | L41: 17.5 | N41: =A41 -> 170525 | O41: Jprinting | P41: =(C41) -> 필름출력 현상기 롤라 | Q41: =D41 -> 1 | R41: 630000 | S41: =(R41*D41)*1.1 -> 693000 | T41: =(R41*Q41) -> 630000 | U41: =IF(J41=W41,"O", "X") -> O | W41: =(G41-T41) -> 160000
B42: 프린피아 주안 | C42: 스트리퍼 | D42: 50 | E42: 18000 | F42: =(E42*D42)*1.1 -> 990000 | G42: =(E42*D42) -> 900000 | H42: Goss | J42: =(G42-(VLOOKUP(C42,Price!B:D,3,FALSE)*D42)) -> 450000 | K42: =(J42/(F42/11*10)) -> 0.5 | L42: 17.5 | N42: =A42 -> 0 | O42: Goss | P42: =(C42) -> 스트리퍼 | Q42: =D42 -> 50 | R42: 6320 | S42: =(R42*D42)*1.1 -> 347600 | T42: =(R42*Q42) -> 316000 | U42: =IF(J42=W42,"O", "X") -> X | W42: =(G42-T42) -> 584000
A43: 170526 | B43: 재능 | C43: 프리미어 잉크 | D43: 1 | E43: 723000 | F43: =(E43*D43)*1.1 -> 795300 | G43: =(E43*D43) -> 723000 | H43: Consums | I43: Ink | J43: =(G43-T43) -> 79700 | K43: =(J43/(F43/11*10)) -> 0.11023513 | L43: 17.5 | N43: =A43 -> 170526 | O43: 동양잉크 | P43: =(C43) -> 프리미어 잉크 | Q43: =D43 -> 1 | R43: 643300 | S43: =(R43*D43)*1.1 -> 707630 | T43: =(R43*Q43) -> 643300 | U43: =IF(J43=W43,"O", "X") -> O | W43: =(G43-T43) -> 79700
B44: 미래인텍 | C44: 아스테이지(국전) | D44: 10 | E44: 70000 | F44: =(E44*D44)*1.1 -> 770000 | G44: =(E44*D44) -> 700000 | H44: Consums | I44: Others | J44: =(G44-(VLOOKUP(C44,Price!B:D,3,FALSE)*D44)) -> 200000 | K44: =(J44/(F44/11*10)) -> 0.28571429 | L44: 17.5 | N44: =A44 -> 0 | O44: 대진PM | P44: =(C44) -> 아스테이지(국전) | Q44: =D44 -> 10 | R44: 50000 | S44: =(R44*D44)*1.1 -> 550000 | T44: =(R44*Q44) -> 500000 | U44: =IF(J44=W44,"O", "X") -> O | W44: =(G44-T44) -> 200000
B45: 교학사 | C45: 스트리퍼 | D45: 40 | E45: 19000 | F45: =(E45*D45)*1.1 -> 836000 | G45: =(E45*D45) -> 760000 | H45: Goss | J45: =(G45-(VLOOKUP(C45,Price!B:D,3,FALSE)*D45)) -> 400000 | K45: =(J45/(F45/11*10)) -> 0.52631579 | L45: 17.5 | N45: =A45 -> 0 | O45: Goss | P45: =(C45) -> 스트리퍼 | Q45: =D45 -> 40 | R45: 6320 | S45: =(R45*D45)*1.1 -> 278080 | T45: =(R45*Q45) -> 252800 | U45: =IF(J45=W45,"O", "X") -> X | W45: =(G45-T45) -> 507200
B46: 덕수 | C46: UV wash(20L) | D46: 3 | E46: 135000 | F46: =(E46*D46)*1.1 -> 445500 | G46: =(E46*D46) -> 405000 | H46: Consums | I46: Wash | J46: =(G46-(VLOOKUP(C46,Price!B:D,3,FALSE)*D46)) -> 75000 | K46: =(J46/(F46/11*10)) -> 0.18518519 | L46: 17.5 | N46: =A46 -> 0 | O46: 붸처코리아 | P46: =(C46) -> UV wash(20L) | Q46: =D46 -> 3 | R46: 110000 | S46: =(R46*D46)*1.1 -> 363000 | T46: =(R46*Q46) -> 330000 | U46: =IF(J46=W46,"O", "X") -> O | W46: =(G46-T46) -> 75000
B47: 세흥인쇄 | C47: Agfa Film(24inch) | D47: 2 | E47: 327000 | F47: =(E47*D47)*1.1 -> 719400 | G47: =(E47*D47) -> 654000 | H47: Consums | I47: Film | J47: =(G47-(VLOOKUP(C47,Price!B:D,3,FALSE)*D47)) -> 115800 | K47: =(J47/(F47/11*10)) -> 0.17706422 | L47: 17.5 | N47: =A47 -> 0 | O47: Agfa | P47: =(C47) -> Agfa Film(24inch) | Q47: =D47 -> 2 | R47: 269100 | S47: =(R47*D47)*1.1 -> 592020 | T47: =(R47*Q47) -> 538200 | U47: =IF(J47=W47,"O", "X") -> O | W47: =(G47-T47) -> 115800
B48: 세흥인쇄 | C48: Agfa Film(28inch) | D48: 2 | E48: 401000 | F48: =(E48*D48)*1.1 -> 882200 | G48: =(E48*D48) -> 802000 | H48: Consums | I48: Film | J48: =(G48-(VLOOKUP(C48,Price!B:D,3,FALSE)*D48)) -> 174080 | K48: =(J48/(F48/11*10)) -> 0.21705736 | L48: 17.5 | N48: =A48 -> 0 | O48: Agfa | P48: =(C48) -> Agfa Film(28inch) | Q48: =D48 -> 2 | R48: 313960 | S48: =(R48*D48)*1.1 -> 690712 | T48: =(R48*Q48) -> 627920 | U48: =IF(J48=W48,"O", "X") -> O | W48: =(G48-T48) -> 174080
B49: 세흥인쇄 | C49: Agfa Film(32inch) | D49: 2 | E49: 448000 | F49: =(E49*D49)*1.1 -> 985600 | G49: =(E49*D49) -> 896000 | H49: Consums | I49: Film | J49: =(G49-(VLOOKUP(C49,Price!B:D,3,FALSE)*D49)) -> 155980 | K49: =(J49/(F49/11*10)) -> 0.17408482 | L49: 17.5 | N49: =A49 -> 0 | O49: Agfa | P49: =(C49) -> Agfa Film(32inch) | Q49: =D49 -> 2 | R49: 370010 | S49: =(R49*D49)*1.1 -> 814022 | T49: =(R49*Q49) -> 740020 | U49: =IF(J49=W49,"O", "X") -> O | W49: =(G49-T49) -> 155980
B50: 세흥인쇄 | C50: Agfa 현상액 G101C(10L) | D50: 2 | E50: 41000 | F50: =(E50*D50)*1.1 -> 90200 | G50: =(E50*D50) -> 82000 | H50: Consums | I50: Film | J50: =(G50-(VLOOKUP(C50,Price!B:D,3,FALSE)*D50)) -> 32000 | K50: =(J50/(F50/11*10)) -> 0.3902439 | L50: 17.5 | N50: =A50 -> 0 | O50: Agfa | P50: =(C50) -> Agfa 현상액 G101C(10L) | Q50: =D50 -> 2 | R50: 25000 | S50: =(R50*D50)*1.1 -> 55000 | T50: =(R50*Q50) -> 50000 | U50: =IF(J50=W50,"O", "X") -> O | W50: =(G50-T50) -> 32000
B51: 세흥인쇄 | C51: Agfa 정착액 G333C(20L) | D51: 1 | E51: 93000 | F51: =(E51*D51)*1.1 -> 102300 | G51: =(E51*D51) -> 93000 | H51: Consums | I51: Film | J51: =(G51-(VLOOKUP(C51,Price!B:D,3,FALSE)*D51)) -> 33000 | K51: =(J51/(F51/11*10)) -> 0.35483871 | L51: 17.5 | N51: =A51 -> 0 | O51: Agfa | P51: =(C51) -> Agfa 정착액 G333C(20L) | Q51: =D51 -> 1 | R51: 60000 | S51: =(R51*D51)*1.1 -> 66000 | T51: =(R51*Q51) -> 60000 | U51: =IF(J51=W51,"O", "X") -> O | W51: =(G51-T51) -> 33000
B52: 프린피아 문발 | C52: Blanket(1050*840) | D52: 5 | E52: 108000 | F52: =(E52*D52)*1.1 -> 594000 | G52: =(E52*D52) -> 540000 | H52: Consums | I52: Blanket | J52: =(G52-(VLOOKUP(C52,Price!B:D,3,FALSE)*D52)) -> 137500 | K52: =(J52/(F52/11*10)) -> 0.25462963 | L52: 17.5 | N52: =A52 -> 0 | O52: 동양잉크 | P52: =(C52) -> Blanket(1050*840) | Q52: =D52 -> 5 | R52: 80500 | S52: =(R52*D52)*1.1 -> 442750 | T52: =(R52*Q52) -> 402500 | U52: =IF(J52=W52,"O", "X") -> O | W52: =(G52-T52) -> 137500
B53: 프린피아 문발 | C53: 매엽용 세척제(Wash 562) | D53: 10 | E53: 59500 | F53: =(E53*D53)*1.1 -> 654500 | G53: =(E53*D53) -> 595000 | H53: Consums | I53: Wash | J53: =(G53-(VLOOKUP(C53,Price!B:D,3,FALSE)*D53)) -> 85000 | K53: =(J53/(F53/11*10)) -> 0.14285714 | L53: 17.5 | N53: =A53 -> 0 | O53: 하이델베르그 | P53: =(C53) -> 매엽용 세척제(Wash 562) | Q53: =D53 -> 10 | R53: 51000 | S53: =(R53*D53)*1.1 -> 561000 | T53: =(R53*Q53) -> 510000 | U53: =IF(J53=W53,"O", "X") -> O | W53: =(G53-T53) -> 85000
A54: 170529 | B54: 신안테크 | C54: 필터백 | D54: 5 | E54: 30000 | F54: =(E54*D54)*1.1 -> 165000 | G54: =(E54*D54) -> 150000 | H54: Technotrans | J54: =(G54-(VLOOKUP(C54,Price!B:D,3,FALSE)*D54)) -> 37695 | K54: =(J54/(F54/11*10)) -> 0.2513 | L54: 17.5 | N54: =A54 -> 170529 | O54: Technotrans | P54: =(C54) -> 필터백 | Q54: =D54 -> 5 | R54: 19800 | S54: =(R54*D54)*1.1 -> 108900 | T54: =(R54*Q54) -> 99000 | U54: =IF(J54=W54,"O", "X") -> X | W54: =(G54-T54) -> 51000
A55: 170530 | B55: 매일경제 | C55: 세정포-XL106 | D55: 5 | E55: 272000 | F55: =(E55*D55)*1.1 -> 1496000 | G55: =(E55*D55) -> 1360000 | H55: Consums | I55: Wash | J55: =(G55-(VLOOKUP(C55,Price!B:D,3,FALSE)*D55)) -> 320000 | K55: =(J55/(F55/11*10)) -> 0.23529412 | L55: 17.5 | N55: =A55 -> 170530 | O55: 대우피앤시 | P55: =(C55) -> 세정포-XL106 | Q55: =D55 -> 5 | R55: 208000 | S55: =(R55*D55)*1.1 -> 1144000 | T55: =(R55*Q55) -> 1040000 | U55: =IF(J55=W55,"O", "X") -> O | W55: =(G55-T55) -> 320000
B56: 매일경제 | C56: XL106 Blanket(1077*885) | D56: 10 | E56: 125000 | F56: =(E56*D56)*1.1 -> 1375000 | G56: =(E56*D56) -> 1250000 | H56: Consums | I56: Blanket | J56: =(G56-(VLOOKUP(C56,Price!B:D,3,FALSE)*D56)) -> 260000 | K56: =(J56/(F56/11*10)) -> 0.208 | L56: 17.5 | N56: =A56 -> 0 | O56: 하이델베르그 | P56: =(C56) -> XL106 Blanket(1077*885) | Q56: =D56 -> 10 | R56: 99000 | S56: =(R56*D56)*1.1 -> 1089000 | T56: =(R56*Q56) -> 990000 | U56: =IF(J56=W56,"O", "X") -> O | W56: =(G56-T56) -> 260000
B57: 프린피아 문발 | C57: 윤전용 실리콘 | D57: 5 | E57: 110000 | F57: =(E57*D57)*1.1 -> 605000 | G57: =(E57*D57) -> 550000 | H57: Consums | I57: Others | J57: =(G57-(VLOOKUP(C57,Price!B:D,3,FALSE)*D57)) -> 95000 | K57: =(J57/(F57/11*10)) -> 0.17272727 | L57: 17.5 | N57: =A57 -> 0 | O57: 하이델베르그 | P57: =(C57) -> 윤전용 실리콘 | Q57: =D57 -> 5 | R57: 91000 | S57: =(R57*D57)*1.1 -> 500500 | T57: =(R57*Q57) -> 455000 | U57: =IF(J57=W57,"O", "X") -> O | W57: =(G57-T57) -> 95000
A58: 2017.6 | B58: 매출 | N58: =A58 -> 2017.6 | O58: 매입 | U58: =IF(J58=W58,"O", "X") -> O
A59: 170529 | B59: 세흥인쇄 | C59: 공압콤푸레샤 종이필터 | D59: 2 | E59: 118000 | F59: =(E59*D59)*1.1 -> 259600 | G59: =(E59*D59) -> 236000 | H59: Consums | I59: Others | J59: =(G59-(VLOOKUP(C59,Price!B:D,3,FALSE)*D59)) -> 47200 | K59: =(J59/(F59/11*10)) -> 0.2 | L59: 17.6 | N59: =A59 -> 170529 | O59: 하이델베르그 | P59: =(C59) -> 공압콤푸레샤 종이필터 | Q59: =D59 -> 2 | R59: 94400 | S59: =(R59*D59)*1.1 -> 207680 | T59: =(R59*Q59) -> 188800 | U59: =IF(J59=W59,"O", "X") -> O | W59: =(G59-T59) -> 47200
A60: 170529 | B60: 재능(Ink & CTP) | C60: ENGAGE 27 900X570MM WE | D60: 1000 | E60: 3990 | F60: =(E60*D60)*1.1 -> 4389000 | G60: =(E60*D60) -> 3990000 | H60: Consums | I60: CTP | J60: =(G60-(VLOOKUP(C60,Price!B:D,3,FALSE)*D60)) -> 1250000 | K60: =(J60/(F60/11*10)) -> 0.31328321 | L60: 17.6 | N60: =A60 -> 170529 | O60: Agfa | P60: =(C60) -> ENGAGE 27 900X570MM WE | Q60: =D60 -> 1000 | R60: 2740 | S60: =(R60*D60)*1.1 -> 3014000 | T60: =(R60*Q60) -> 2740000 | U60: =IF(J60=W60,"O", "X") -> O | W60: =(G60-T60) -> 1250000
A61: 170531 | B61: 재능(Ink & CTP) | C61: 프리미어 잉크 | D61: 1 | E61: 2769600 | F61: =(E61*D61)*1.1 -> 3046560 | G61: =(E61*D61) -> 2769600 | H61: Consums | I61: Ink | J61: =(G61-T61) -> 296640 | K61: =(J61/(F61/11*10)) -> 0.10710572 | L61: 17.6 | N61: =A61 -> 170531 | O61: 동양잉크 | P61: =(C61) -> 프리미어 잉크 | Q61: =D61 -> 1 | R61: 2472960 | S61: =(R61*D61)*1.1 -> 2720256 | T61: =(R61*Q61) -> 2472960 | U61: =IF(J61=W61,"O", "X") -> O | W61: =(G61-T61) -> 296640
A62: 170531 | B62: 프린피아 주안 | C62: 필터백 | D62: 8 | E62: 30000 | F62: =(E62*D62)*1.1 -> 264000 | G62: =(E62*D62) -> 240000 | H62: Technotrans | J62: =(G62-(VLOOKUP(C62,Price!B:D,3,FALSE)*D62)) -> 60312 | K62: =(J62/(F62/11*10)) -> 0.2513 | L62: 17.6 | N62: =A62 -> 170531 | O62: Technotrans | P62: =(C62) -> 필터백 | Q62: =D62 -> 8 | R62: 19800 | S62: =(R62*D62)*1.1 -> 174240 | T62: =(R62*Q62) -> 158400 | U62: =IF(J62=W62,"O", "X") -> X | W62: =(G62-T62) -> 81600
A63: 170601 | B63: 대하팩키지 | C63: Blanket(1050*840)bar | D63: 10 | E63: 130000 | F63: =(E63*D63)*1.1 -> 1430000 | G63: =(E63*D63) -> 1300000 | H63: Consums | I63: Blanket | J63: =(G63-(VLOOKUP(C63,Price!B:D,3,FALSE)*D63)) -> 450000 | K63: =(J63/(F63/11*10)) -> 0.34615385 | L63: 17.6 | N63: =A63 -> 170601 | O63: 시엠시엔지니어링 | P63: =(C63) -> Blanket(1050*840)bar | Q63: =D63 -> 10 | R63: 85000 | S63: =(R63*D63)*1.1 -> 935000 | T63: =(R63*Q63) -> 850000 | U63: =IF(J63=W63,"O", "X") -> O | W63: =(G63-T63) -> 450000
A64: 170601 | B64: 프린피아 문발 | C64: Blanket(990*725) | D64: 10 | E64: 120000 | F64: =(E64*D64)*1.1 -> 1320000 | G64: =(E64*D64) -> 1200000 | H64: Consums | I64: Blanket | J64: =(G64-(VLOOKUP(C64,Price!B:D,3,FALSE)*D64)) -> 80000 | K64: =(J64/(F64/11*10)) -> 0.066666667 | L64: 17.6 | N64: =A64 -> 170601 | O64: 화성메이저 | P64: =(C64) -> Blanket(990*725) | Q64: =D64 -> 10 | R64: 112000 | S64: =(R64*D64)*1.1 -> 1232000 | T64: =(R64*Q64) -> 1120000 | U64: =IF(J64=W64,"O", "X") -> O | W64: =(G64-T64) -> 80000
A65: 170601 | B65: 신흥피앤피 | C65: M-600B 윤전기 기술 서비스 | D65: 1 | E65: 150000 | F65: =(E65*D65)*1.1 -> 165000 | G65: =(E65*D65) -> 150000 | H65: Service | J65: 150000 | K65: =(J65/(F65/11*10)) -> 1 | L65: 17.6 | N65: =A65 -> 170601 | P65: =(C65) -> M-600B 윤전기 기술 서비스 | Q65: =D65 -> 1 | S65: =(R65*D65)*1.1 -> 0 | T65: =(R65*Q65) -> 0 | U65: =IF(J65=W65,"O", "X") -> O | W65: =(G65-T65) -> 150000
A66: 170601 | B66: 동양인쇄재료상사 | C66: 미쯔비시 Blanket(1035*910) | D66: 15 | E66: 115000 | F66: =(E66*D66)*1.1 -> 1897500 | G66: =(E66*D66) -> 1725000 | H66: Consums | I66: Blanket | J66: =(G66-(VLOOKUP(C66,Price!B:D,3,FALSE)*D66)) -> 394500 | K66: =(J66/(F66/11*10)) -> 0.22869565 | L66: 17.6 | N66: =A66 -> 170601 | O66: 하이델베르그 | P66: =(C66) -> 미쯔비시 Blanket(1035*910) | Q66: =D66 -> 15 | R66: 88700 | S66: =(R66*D66)*1.1 -> 1463550 | T66: =(R66*Q66) -> 1330500 | U66: =IF(J66=W66,"O", "X") -> O | W66: =(G66-T66) -> 394500
A67: 170601 | B67: 동양인쇄재료상사 | C67: 로랜드 Blanket(1050*910) | D67: 5 | E67: 128500 | F67: =(E67*D67)*1.1 -> 706750 | G67: =(E67*D67) -> 642500 | H67: Consums | I67: Blanket | J67: =(G67-(VLOOKUP(C67,Price!B:D,3,FALSE)*D67)) -> 192500 | K67: =(J67/(F67/11*10)) -> 0.29961089 | L67: 17.6 | N67: =A67 -> 170601 | O67: 하이델베르그 | P67: =(C67) -> 로랜드 Blanket(1050*910) | Q67: =D67 -> 5 | R67: 90000 | S67: =(R67*D67)*1.1 -> 495000 | T67: =(R67*Q67) -> 450000 | U67: =IF(J67=W67,"O", "X") -> O | W67: =(G67-T67) -> 192500
A68: 170601 | B68: 신일디앤피 | C68: 아스테이지(T-3절) | D68: 3 | E68: 85000 | F68: =(E68*D68)*1.1 -> 280500 | G68: =(E68*D68) -> 255000 | H68: Consums | I68: Others | J68: =(G68-(VLOOKUP(C68,Price!B:D,3,FALSE)*D68)) -> 135000 | K68: =(J68/(F68/11*10)) -> 0.52941176 | L68: 17.6 | N68: =A68 -> 170601 | O68: 대진PM | P68: =(C68) -> 아스테이지(T-3절) | Q68: =D68 -> 3 | R68: 40000 | S68: =(R68*D68)*1.1 -> 132000 | T68: =(R68*Q68) -> 120000 | U68: =IF(J68=W68,"O", "X") -> O | W68: =(G68-T68) -> 135000
A69: 170601 | B69: 퍼시픽패키지 | C69: 아스테이지(국전) | D69: 5 | E69: 100000 | F69: =(E69*D69)*1.1 -> 550000 | G69: =(E69*D69) -> 500000 | H69: Consums | I69: Others | J69: =(G69-(VLOOKUP(C69,Price!B:D,3,FALSE)*D69)) -> 250000 | K69: =(J69/(F69/11*10)) -> 0.5 | L69: 17.6 | N69: =A69 -> 170601 | O69: 대진PM | P69: =(C69) -> 아스테이지(국전) | Q69: =D69 -> 5 | R69: 50000 | S69: =(R69*D69)*1.1 -> 275000 | T69: =(R69*Q69) -> 250000 | U69: =IF(J69=W69,"O", "X") -> O | W69: =(G69-T69) -> 250000
A70: 170601 | B70: 덕수 | C70: Blanket(1060*860) | D70: 10 | E70: 110000 | F70: =(E70*D70)*1.1 -> 1210000 | G70: =(E70*D70) -> 1100000 | H70: Consums | I70: Blanket | J70: =(G70-(VLOOKUP(C70,Price!B:D,3,FALSE)*D70)) -> 271000 | K70: =(J70/(F70/11*10)) -> 0.24636364 | L70: 17.6 | N70: =A70 -> 170601 | O70: 동양잉크 | P70: =(C70) -> Blanket(1060*860) | Q70: =D70 -> 10 | R70: 82900 | S70: =(R70*D70)*1.1 -> 911900 | T70: =(R70*Q70) -> 829000 | U70: =IF(J70=W70,"O", "X") -> O | W70: =(G70-T70) -> 271000
A71: 170601 | B71: 덕수 | C71: UV wash(20L) | D71: 5 | E71: 135000 | F71: =(E71*D71)*1.1 -> 742500 | G71: =(E71*D71) -> 675000 | H71: Consums | I71: Wash | J71: =(G71-(VLOOKUP(C71,Price!B:D,3,FALSE)*D71)) -> 125000 | K71: =(J71/(F71/11*10)) -> 0.18518519 | L71: 17.6 | N71: =A71 -> 170601 | O71: 붸처코리아 | P71: =(C71) -> UV wash(20L) | Q71: =D71 -> 5 | R71: 110000 | S71: =(R71*D71)*1.1 -> 605000 | T71: =(R71*Q71) -> 550000 | U71: =IF(J71=W71,"O", "X") -> O | W71: =(G71-T71) -> 125000
A72: 170601 | B72: 프린피아 주안 | C72: Insolating Strip(양면테이프) | D72: 30 | E72: 4500 | F72: =(E72*D72)*1.1 -> 148500 | G72: =(E72*D72) -> 135000 | H72: Goss | J72: =(G72-(VLOOKUP(C72,Import!C:G,4,FALSE)*D72)) -> 135000 | K72: =(J72/(F72/11*10)) -> 1 | L72: 17.6 | N72: =A72 -> 170601 | O72: Goss | P72: =(C72) -> Insolating Strip(양면테이프) | Q72: =D72 -> 30 | R72: =(Import!G4) -> 1497.2534 | S72: =(R72*D72)*1.1 -> 49409.362 | T72: =(R72*Q72) -> 44917.602 | U72: =IF(J72=W72,"O", "X") -> X | W72: =(G72-T72) -> 90082.398
A73: 170602 | B73: 맥스타 | C73: Fount 554 | D73: 2 | E73: 270000 | F73: =(E73*D73)*1.1 -> 594000 | G73: =(E73*D73) -> 540000 | H73: Consums | I73: Fount | J73: =(G73-(VLOOKUP(C73,Price!B:D,3,FALSE)*D73)) -> 260000 | K73: =(J73/(F73/11*10)) -> 0.48148148 | L73: 17.6 | N73: =A73 -> 170602 | O73: 하이델베르그 | P73: =(C73) -> Fount 554 | Q73: =D73 -> 2 | R73: 140000 | S73: =(R73*D73)*1.1 -> 308000 | T73: =(R73*Q73) -> 280000 | U73: =IF(J73=W73,"O", "X") -> O | W73: =(G73-T73) -> 260000
B74: 맥스타 | C74: 5MX(1050*840) | D74: 2 | E74: 140000 | F74: =(E74*D74)*1.1 -> 308000 | G74: =(E74*D74) -> 280000 | H74: Consums | I74: Blanket | J74: =(G74-(VLOOKUP(C74,Price!B:D,3,FALSE)*D74)) -> 90000 | K74: =(J74/(F74/11*10)) -> 0.32142857 | L74: 17.6 | N74: =A74 -> 0 | O74: 하이델베르그 | P74: =(C74) -> 5MX(1050*840) | Q74: =D74 -> 2 | R74: 95000 | S74: =(R74*D74)*1.1 -> 209000 | T74: =(R74*Q74) -> 190000 | U74: =IF(J74=W74,"O", "X") -> O | W74: =(G74-T74) -> 90000
A75: 170605 | B75: 매일경제 | C75: Plunger Parts | D75: 1000 | E75: 4350 | F75: =(E75*D75)*1.1 -> 4785000 | G75: =(E75*D75) -> 4350000 | H75: Consums | I75: Others | J75: =(G75-(VLOOKUP(C75,Price!B:D,3,FALSE)*D75)) -> 350000 | K75: =(J75/(F75/11*10)) -> 0.08045977 | L75: 17.6 | N75: =A75 -> 170605 | O75: 대한교역 | P75: =(C75) -> Plunger Parts | Q75: =D75 -> 1000 | R75: 4000 | S75: =(R75*D75)*1.1 -> 4400000 | T75: =(R75*Q75) -> 4000000 | U75: =IF(J75=W75,"O", "X") -> O | W75: =(G75-T75) -> 350000
A76: 170605 | B76: 보문특수칼라 | C76: 아스테이지(국전) | D76: 15 | E76: 65000 | F76: =(E76*D76)*1.1 -> 1072500 | G76: =(E76*D76) -> 975000 | H76: Consums | I76: Others | J76: =(G76-(VLOOKUP(C76,Price!B:D,3,FALSE)*D76)) -> 225000 | K76: =(J76/(F76/11*10)) -> 0.23076923 | L76: 17.6 | N76: =A76 -> 170605 | O76: 대진PM | P76: =(C76) -> 아스테이지(국전) | Q76: =D76 -> 15 | R76: 50000 | S76: =(R76*D76)*1.1 -> 825000 | T76: =(R76*Q76) -> 750000 | U76: =IF(J76=W76,"O", "X") -> O | W76: =(G76-T76) -> 225000
A77: 170605 | B77: 국민피앤텍 | C77: 필터백 | D77: 4 | E77: 45000 | F77: =(E77*D77)*1.1 -> 198000 | G77: =(E77*D77) -> 180000 | H77: Technotrans | J77: =(G77-(VLOOKUP(C77,Price!B:D,3,FALSE)*D77)) -> 90156 | K77: =(J77/(F77/11*10)) -> 0.50086667 | L77: 17.6 | N77: =A77 -> 170605 | O77: Technotrans | P77: =(C77) -> 필터백 | Q77: =D77 -> 4 | R77: 19800 | S77: =(R77*D77)*1.1 -> 87120 | T77: =(R77*Q77) -> 79200 | U77: =IF(J77=W77,"O", "X") -> X | W77: =(G77-T77) -> 100800
A78: 170605 | B78: 재능(Ink & CTP) | C78: 프리미어 잉크 | D78: 1 | E78: 964800 | F78: =(E78*D78)*1.1 -> 1061280 | G78: =(E78*D78) -> 964800 | H78: Consums | I78: Ink | J78: =(G78-T78) -> 88320 | K78: =(J78/(F78/11*10)) -> 0.091542289 | L78: 17.6 | N78: =A78 -> 170605 | O78: 동양잉크 | P78: =(C78) -> 프리미어 잉크 | Q78: =D78 -> 1 | R78: 876480 | S78: =(R78*D78)*1.1 -> 964128 | T78: =(R78*Q78) -> 876480 | U78: =IF(J78=W78,"O", "X") -> O | W78: =(G78-T78) -> 88320
A79: 170607 | B79: 세흥인쇄 | C79: 매엽용 세척제(Wash 562) | D79: 10 | E79: 69000 | F79: =(E79*D79)*1.1 -> 759000 | G79: =(E79*D79) -> 690000 | H79: Consums | I79: Wash | J79: =(G79-(VLOOKUP(C79,Price!B:D,3,FALSE)*D79)) -> 180000 | K79: =(J79/(F79/11*10)) -> 0.26086957 | L79: 17.6 | N79: =A79 -> 170607 | O79: 하이델베르그 | P79: =(C79) -> 매엽용 세척제(Wash 562) | Q79: =D79 -> 10 | R79: 51000 | S79: =(R79*D79)*1.1 -> 561000 | T79: =(R79*Q79) -> 510000 | U79: =IF(J79=W79,"O", "X") -> O | W79: =(G79-T79) -> 180000
A80: 170607 | B80: 재능(Ink & CTP) | C80: THR200(20L) | D80: 10 | E80: 58000 | F80: =(E80*D80)*1.1 -> 638000 | G80: =(E80*D80) -> 580000 | H80: Consums | I80: CTP | J80: =(G80-(VLOOKUP(C80,Price!B:D,3,FALSE)*D80)) -> 230000 | K80: =(J80/(F80/11*10)) -> 0.39655172 | L80: 17.6 | N80: =A80 -> 170607 | O80: Agfa | P80: =(C80) -> THR200(20L) | Q80: =D80 -> 10 | R80: 35000 | S80: =(R80*D80)*1.1 -> 385000 | T80: =(R80*Q80) -> 350000 | U80: =IF(J80=W80,"O", "X") -> O | W80: =(G80-T80) -> 230000
A81: 170607 | B81: 재능(Ink & CTP) | C81: ENGAGE 900X570 - 27RO | D81: 1000 | E81: 3990 | F81: =(E81*D81)*1.1 -> 4389000 | G81: =(E81*D81) -> 3990000 | H81: Consums | I81: CTP | J81: =(G81-(VLOOKUP(C81,Price!B:D,3,FALSE)*D81)) -> 1250000 | K81: =(J81/(F81/11*10)) -> 0.31328321 | L81: 17.6 | N81: =A81 -> 170607 | O81: Agfa | P81: =(C81) -> ENGAGE 900X570 - 27RO | Q81: =D81 -> 1000 | R81: 2740 | S81: =(R81*D81)*1.1 -> 3014000 | T81: =(R81*Q81) -> 2740000 | U81: =IF(J81=W81,"O", "X") -> O | W81: =(G81-T81) -> 1250000
A82: 170609 | B82: 덕수 | C82: Blanket(1060*860) | D82: 10 | E82: 110000 | F82: =(E82*D82)*1.1 -> 1210000 | G82: =(E82*D82) -> 1100000 | H82: Consums | I82: Blanket | J82: =(G82-(VLOOKUP(C82,Price!B:D,3,FALSE)*D82)) -> 271000 | K82: =(J82/(F82/11*10)) -> 0.24636364 | L82: 17.6 | N82: =A82 -> 170609 | O82: 동양잉크 | P82: =(C82) -> Blanket(1060*860) | Q82: =D82 -> 10 | R82: 82900 | S82: =(R82*D82)*1.1 -> 911900 | T82: =(R82*Q82) -> 829000 | U82: =IF(J82=W82,"O", "X") -> O | W82: =(G82-T82) -> 271000
A83: 170609 | B83: 덕수 | C83: UV wash(20L) | D83: 6 | E83: 135000 | F83: =(E83*D83)*1.1 -> 891000 | G83: =(E83*D83) -> 810000 | H83: Consums | I83: Wash | J83: =(G83-(VLOOKUP(C83,Price!B:D,3,FALSE)*D83)) -> 150000 | K83: =(J83/(F83/11*10)) -> 0.18518519 | L83: 17.6 | N83: =A83 -> 170609 | O83: 붸처코리아 | P83: =(C83) -> UV wash(20L) | Q83: =D83 -> 6 | R83: 110000 | S83: =(R83*D83)*1.1 -> 726000 | T83: =(R83*Q83) -> 660000 | U83: =IF(J83=W83,"O", "X") -> O | W83: =(G83-T83) -> 150000
A84: 170609 | B84: 송운사 | C84: Technotrans 알콜컨트롤 | D84: 1 | E84: 5000000 | F84: =(E84*D84)*1.1 -> 5500000 | G84: =(E84*D84) -> 5000000 | H84: Technotrans | J84: =(G84-T84) -> 1610000 | K84: =(J84/(F84/11*10)) -> 0.322 | L84: 17.6 | N84: =A84 -> 170609 | O84: Technotrans | P84: =(C84) -> Technotrans 알콜컨트롤 | Q84: =D84 -> 1 | R84: 3390000 | S84: =(R84*D84)*1.1 -> 3729000 | T84: =(R84*Q84) -> 3390000 | U84: =IF(J84=W84,"O", "X") -> O | W84: =(G84-T84) -> 1610000
A85: 170609 | B85: 프린피아 주안 | C85: Link, Chain - Special | D85: 30 | E85: 21000 | F85: =(E85*D85)*1.1 -> 693000 | G85: =(E85*D85) -> 630000 | H85: Goss | J85: =(G85-(VLOOKUP(C85,Import!C:G,4,FALSE)*D85)) -> 630000 | K85: =(J85/(F85/11*10)) -> 1 | L85: 17.6 | N85: =A85 -> 170609 | O85: Goss | P85: =(C85) -> Link, Chain - Special | Q85: =D85 -> 30 | R85: =Import!G12 -> 10340.483 | S85: =(R85*D85)*1.1 -> 341235.94 | T85: =(R85*Q85) -> 310214.49 | U85: =IF(J85=W85,"O", "X") -> X | W85: =(G85-T85) -> 319785.51
A86: 170609 | B86: 프린피아 주안 | C86: Brush, Head Stop | D86: 30 | E86: 27000 | F86: =(E86*D86)*1.1 -> 891000 | G86: =(E86*D86) -> 810000 | H86: Goss | J86: =(G86-(VLOOKUP(C86,Import!C:G,4,FALSE)*D86)) -> 810000 | K86: =(J86/(F86/11*10)) -> 1 | L86: 17.6 | N86: =A86 -> 170609 | O86: Goss | P86: =(C86) -> Brush, Head Stop | Q86: =D86 -> 30 | R86: =(Import!G10) -> 11428.511 | S86: =(R86*D86)*1.1 -> 377140.86 | T86: =(R86*Q86) -> 342855.33 | U86: =IF(J86=W86,"O", "X") -> X | W86: =(G86-T86) -> 467144.67
A87: 170609 | B87: 프린피아 문발 | C87: Brake Lining | D87: 4 | E87: 240000 | F87: =(E87*D87)*1.1 -> 1056000 | G87: =(E87*D87) -> 960000 | H87: Goss | J87: =(G87-(VLOOKUP(C87,Import!C:G,4,FALSE)*D87)) -> 960000 | K87: =(J87/(F87/11*10)) -> 1 | L87: 17.6 | N87: =A87 -> 170609 | O87: Goss | P87: =(C87) -> Brake Lining | Q87: =D87 -> 4 | R87: =(Import!G11) -> 121463.61 | S87: =(R87*D87)*1.1 -> 534439.89 | T87: =(R87*Q87) -> 485854.44 | U87: =IF(J87=W87,"O", "X") -> X | W87: =(G87-T87) -> 474145.56
A88: 170609 | B88: 케이피 | C88: Nozzle D 3.0 blue complete | D88: 6 | E88: 110000 | F88: =(E88*D88)*1.1 -> 726000 | G88: =(E88*D88) -> 660000 | H88: Technotrans | J88: =(G88-(VLOOKUP(C88,Import!C:G,4,FALSE)*D88)) -> 660000 | K88: =(J88/(F88/11*10)) -> 1 | L88: 17.6 | N88: =A88 -> 170609 | O88: Technotrans | P88: =(C88) -> Nozzle D 3.0 blue complete | Q88: =D88 -> 6 | R88: =(Import!G593) -> 34845.282 | S88: =(R88*D88)*1.1 -> 229978.86 | T88: =(R88*Q88) -> 209071.69 | U88: =IF(J88=W88,"O", "X") -> X | W88: =(G88-T88) -> 450928.31
A89: 170609 | B89: 케이피 | C89: stopcock blue kpl | D89: 5 | E89: 14000 | F89: =(E89*D89)*1.1 -> 77000 | G89: =(E89*D89) -> 70000 | H89: Technotrans | J89: =(G89-(VLOOKUP(C89,Import!C:G,4,FALSE)*D89)) -> 70000 | K89: =(J89/(F89/11*10)) -> 1 | L89: 17.6 | N89: =A89 -> 170609 | O89: Technotrans | P89: =(C89) -> stopcock blue kpl | Q89: =D89 -> 5 | R89: =(Import!G594) -> 4763.8569 | S89: =(R89*D89)*1.1 -> 26201.213 | T89: =(R89*Q89) -> 23819.285 | U89: =IF(J89=W89,"O", "X") -> X | W89: =(G89-T89) -> 46180.715
A90: 170609 | B90: 재능(Ink & CTP) | C90: 프리미어 잉크 | D90: 1 | E90: 1384800 | F90: =(E90*D90)*1.1 -> 1523280 | G90: =(E90*D90) -> 1384800 | H90: Consums | I90: Ink | J90: =(G90-T90) -> 148320 | K90: =(J90/(F90/11*10)) -> 0.10710572 | L90: 17.6 | N90: =A90 -> 170609 | O90: 동양잉크 | P90: =(C90) -> 프리미어 잉크 | Q90: =D90 -> 1 | R90: 1236480 | S90: =(R90*D90)*1.1 -> 1360128 | T90: =(R90*Q90) -> 1236480 | U90: =IF(J90=W90,"O", "X") -> O | W90: =(G90-T90) -> 148320
A91: 170612 | B91: 퍼시픽패키지 | C91: 필터백 | D91: 20 | E91: 35000 | F91: =(E91*D91)*1.1 -> 770000 | G91: =(E91*D91) -> 700000 | H91: Technotrans | J91: =(G91-(VLOOKUP(C91,Price!B:D,3,FALSE)*D91)) -> 250780 | K91: =(J91/(F91/11*10)) -> 0.35825714 | L91: 17.6 | N91: =A91 -> 170612 | O91: Technotrans | P91: =(C91) -> 필터백 | Q91: =D91 -> 20 | R91: 19800 | S91: =(R91*D91)*1.1 -> 435600 | T91: =(R91*Q91) -> 396000 | U91: =IF(J91=W91,"O", "X") -> X | W91: =(G91-T91) -> 304000
A92: 170612 | B92: 프린피아 주안 | C92: 윤전용 실리콘 | D92: 10 | E92: 110000 | F92: =(E92*D92)*1.1 -> 1210000 | G92: =(E92*D92) -> 1100000 | H92: Consums | I92: Others | J92: =(G92-(VLOOKUP(C92,Price!B:D,3,FALSE)*D92)) -> 190000 | K92: =(J92/(F92/11*10)) -> 0.17272727 | L92: 17.6 | N92: =A92 -> 170612 | O92: 하이델베르그 | P92: =(C92) -> 윤전용 실리콘 | Q92: =D92 -> 10 | R92: 91000 | S92: =(R92*D92)*1.1 -> 1001000 | T92: =(R92*Q92) -> 910000 | U92: =IF(J92=W92,"O", "X") -> O | W92: =(G92-T92) -> 190000
A93: 170612 | B93: 신흥피앤피 | C93: M-600B 윤전기 기술 서비스 | D93: 1 | E93: 150000 | F93: =(E93*D93)*1.1 -> 165000 | G93: =(E93*D93) -> 150000 | H93: Service | J93: 150000 | K93: =(J93/(F93/11*10)) -> 1 | L93: 17.6 | N93: =A93 -> 170612 | P93: =(C93) -> M-600B 윤전기 기술 서비스 | Q93: =D93 -> 1 | S93: =(R93*D93)*1.1 -> 0 | T93: =(R93*Q93) -> 0 | U93: =IF(J93=W93,"O", "X") -> O | W93: =(G93-T93) -> 150000
A94: 170612 | B94: 재능(Ink & CTP) | C94: 프리미어 잉크 | D94: 1 | E94: 5770000 | F94: =(E94*D94)*1.1 -> 6347000 | G94: =(E94*D94) -> 5770000 | H94: Consums | I94: Ink | J94: =(G94-T94) -> 618000 | K94: =(J94/(F94/11*10)) -> 0.10710572 | L94: 17.6 | N94: =A94 -> 170612 | O94: 동양잉크 | P94: =(C94) -> 프리미어 잉크 | Q94: =D94 -> 1 | R94: 5152000 | S94: =(R94*D94)*1.1 -> 5667200 | T94: =(R94*Q94) -> 5152000 | U94: =IF(J94=W94,"O", "X") -> O | W94: =(G94-T94) -> 618000
A95: 170614 | B95: 매일경제 | C95: Spark Plug | D95: 2 | E95: 1200000 | F95: =(E95*D95)*1.1 -> 2640000 | G95: =(E95*D95) -> 2400000 | H95: Goss | J95: =(G95-(VLOOKUP(C95,Import!C:G,4,FALSE)*D95)) -> 2400000 | K95: =(J95/(F95/11*10)) -> 1 | L95: 17.6 | N95: =A95 -> 170614 | O95: Goss | P95: =(C95) -> Spark Plug | Q95: =D95 -> 2 | R95: =(Import!G20) -> 507411.78 | S95: =(R95*D95)*1.1 -> 1116305.9 | T95: =(R95*Q95) -> 1014823.6 | U95: =IF(J95=W95,"O", "X") -> X | W95: =(G95-T95) -> 1385176.4
A96: 170615 | B96: 재능 | C96: 서비스 계약(4회분할 중 2회차) | D96: 1 | E96: 1250000 | F96: =(E96*D96)*1.1 -> 1375000 | G96: =(E96*D96) -> 1250000 | H96: Service | J96: 1250000 | K96: =(J96/(F96/11*10)) -> 1 | L96: 17.6 | N96: =A96 -> 170615 | P96: =(C96) -> 서비스 계약(4회분할 중 2회차) | Q96: =D96 -> 1 | S96: =(R96*D96)*1.1 -> 0 | T96: =(R96*Q96) -> 0 | U96: =IF(J96=W96,"O", "X") -> O | W96: =(G96-T96) -> 1250000
A97: 170617 | B97: 프린피아 주안 | C97: M-600 서비스 비용 | D97: 1 | E97: 250000 | F97: =(E97*D97)*1.1 -> 275000 | G97: =(E97*D97) -> 250000 | H97: Service | J97: 250000 | K97: =(J97/(F97/11*10)) -> 1 | L97: 17.6 | N97: =A97 -> 170617 | P97: =(C97) -> M-600 서비스 비용 | Q97: =D97 -> 1 | S97: =(R97*D97)*1.1 -> 0 | T97: =(R97*Q97) -> 0 | U97: =IF(J97=W97,"O", "X") -> O | W97: =(G97-T97) -> 250000
A98: 170620 | B98: 프린피아 문발 | C98: 윤전용 세척제(Web 504) | D98: 7 | E98: 172000 | F98: =(E98*D98)*1.1 -> 1324400 | G98: =(E98*D98) -> 1204000 | H98: Consums | I98: Wash | J98: =(G98-(VLOOKUP(C98,Price!B:D,3,FALSE)*D98)) -> 399000 | K98: =(J98/(F98/11*10)) -> 0.33139535 | L98: 17.6 | N98: =A98 -> 170620 | O98: 하이델베르그 | P98: =(C98) -> 윤전용 세척제(Web 504) | Q98: =D98 -> 7 | R98: 115000 | S98: =(R98*D98)*1.1 -> 885500 | T98: =(R98*Q98) -> 805000 | U98: =IF(J98=W98,"O", "X") -> O | W98: =(G98-T98) -> 399000
A99: 170620 | B99: 재능(Roller) | C99: Water Form Roller-CD102용 | D99: 2 | E99: 400000 | F99: =(E99*D99)*1.1 -> 880000 | G99: =(E99*D99) -> 800000 | H99: Consums | I99: Roller | J99: =(G99-(VLOOKUP(C99,Price!B:D,3,FALSE)*D99)) -> 100000 | K99: =(J99/(F99/11*10)) -> 0.125 | L99: 17.6 | N99: =A99 -> 170620 | O99: 삼화롤러스 | P99: =(C99) -> Water Form Roller-CD102용 | Q99: =D99 -> 2 | R99: 350000 | S99: =(R99*D99)*1.1 -> 770000 | T99: =(R99*Q99) -> 700000 | U99: =IF(J99=W99,"O", "X") -> O | W99: =(G99-T99) -> 100000
A100: 170620 | B100: 재능(Roller) | C100: Water Pan Roller-CD102용 | D100: 2 | E100: 430000 | F100: =(E100*D100)*1.1 -> 946000 | G100: =(E100*D100) -> 860000 | H100: Consums | I100: Roller | J100: =(G100-(VLOOKUP(C100,Price!B:D,3,FALSE)*D100)) -> 100000 | K100: =(J100/(F100/11*10)) -> 0.11627907 | L100: 17.6 | N100: =A100 -> 170620 | O100: 삼화롤러스 | P100: =(C100) -> Water Pan Roller-CD102용 | Q100: =D100 -> 2 | R100: 380000 | S100: =(R100*D100)*1.1 -> 836000 | T100: =(R100*Q100) -> 760000 | U100: =IF(J100=W100,"O", "X") -> O | W100: =(G100-T100) -> 100000
...

Sheet Import
A1: Date | B1: Num | C1: Item | D1: Qtt | E1: Price | F1: Price(Total) | G1: Price(KRW) | H1: Total Price(KRW) | I1: Exchange Rate | J1: Tax | K1: Freight | L1: 판매처 | M1: 재고여부 | N1: 비고
A2: Goss
A3: 170131 | B3: 100 | C3: Replaces Part Number 050-41743 | D3: 2 | E3: 3945.72 | G3: =(I3*E3)+(J3*(E3/SUMIF(B:B,B3,E:E)))/D3+((K3*I3)*(E3/SUMIF(B:B,B3,E:E)))/D3 -> 3371039.5 | H3: =(G3*D3) -> 6742079 | I3: 831.03 | J3: 0 | K3: 240
B4: 100 | C4: Insolating Strip(양면테이프) | D4: 60 | E4: 1.8 | G4: =(I4*E4)+(J4*(E4/SUMIF(B:B,B4,E:E)))/D4+((K4*I4)*(E4/SUMIF(B:B,B4,E:E)))/D4 -> 1497.2534 | H4: =(G4*D4) -> 89835.204 | I4: 831.03 | J4: 0 | K4: 240
B5: 100 | C5: Nip Roll | D5: 1 | E5: 317.61 | G5: =(I5*E5)+(J5*(E5/SUMIF(B:B,B5,E:E)))/D5+((K5*I5)*(E5/SUMIF(B:B,B5,E:E)))/D5 -> 278758.96 | H5: =(G5*D5) -> 278758.96 | I5: 831.03 | J5: 0 | K5: 240
B6: 100 | C6: Brush, Head Stop | D6: 36 | E6: 10.55 | G6: =(I6*E6)+(J6*(E6/SUMIF(B:B,B6,E:E)))/D6+((K6*I6)*(E6/SUMIF(B:B,B6,E:E)))/D6 -> 8781.0366 | H6: =(G6*D6) -> 316117.32 | I6: 831.03 | J6: 0 | K6: 240
A7: 170512 | B7: 101 | C7: Rubber Cutting Stick | D7: 10 | E7: 35.91 | G7: =(I7*E7)+(J7*(E7/SUMIF(B:B,B7,E:E)))/D7+((K7*I7)*(E7/SUMIF(B:B,101,E:E)))/D7 -> 31235.232 | H7: =(G7*D7) -> 312352.32 | I7: 811.72 | J7: 0 | K7: 180
B8: 101 | C8: I/O Terminal Program Controller | D8: 2 | E8: 215.57 | G8: =(I8*E8)+(J8*(E8/SUMIF(B:B,B8,E:E)))/D8+((K8*I8)*(E8/SUMIF(B:B,101,E:E)))/D8 -> 237605.45 | H8: =(G8*D8) -> 475210.89 | I8: 811.72 | J8: 0 | K8: 180
A9: 170518 | B9: 102 | C9: Ink Module Drive Board | D9: 3 | E9: 3386.95 | G9: =(I9*E9)+(J9*(E9/SUMIF(B:B,B9,E:E)))/D9+((K9*I9)*(E9/SUMIF(B:B,B9,E:E)))/D9 -> 2773606.7 | H9: =(G9*D9) -> 8320820 | I9: 811.72 | J9: 0 | K9: 90 | L9: 매일신문
A10: 170523 | B10: 103 | C10: Brush, Head Stop | D10: 30 | E10: 13.55 | G10: =(I10*E10)+(J10*(E10/SUMIF(B:B,B10,E:E)))/D10+((K10*I10)*(E10/SUMIF(B:B,B10,E:E)))/D10 -> 11428.511 | H10: =(G10*D10) -> 342855.33 | I10: 812.3 | J10: 0 | K10: 180 | L10: 프린피아 주안 | M10: X
B11: 103 | C11: Brake Lining | D11: 8 | E11: 130.74 | G11: =(I11*E11)+(J11*(E11/SUMIF(B:B,B11,E:E)))/D11+((K11*I11)*(E11/SUMIF(B:B,B11,E:E)))/D11 -> 121463.61 | H11: =(G11*D11) -> 971708.89 | I11: 812.3 | J11: 0 | K11: 180 | L11: 프린피아 문발
B12: 103 | C12: Link, Chain - Special | D12: 30 | E12: 12.26 | G12: =(I12*E12)+(J12*(E12/SUMIF(B:B,B12,E:E)))/D12+((K12*I12)*(E12/SUMIF(B:B,B12,E:E)))/D12 -> 10340.483 | H12: =(G12*D12) -> 310214.49 | I12: 812.3 | J12: 0 | K12: 180 | L12: 프린피아 문발
A13: 170608 | B13: 104 | C13: Pin, Folder | D13: 300 | E13: 2.5 | G13: =(I13*E13)+(J13*(E13/SUMIF(B:B,B13,E:E)))/D13+((K13*I13)*(E13/SUMIF(B:B,B13,E:E)))/D13 -> 2044.0598 | H13: =(G13*D13) -> 613217.93 | I13: 817.49 | J13: 0 | K13: 360 | L13: 하이델베르그
B14: 104 | C14: Moteur Baumer(WM.5793784) | D14: 1 | E14: 2923.13 | G14: =(I14*E14)+(J14*(E14/SUMIF(B:B,B14,E:E)))/D14+((K14*I14)*(E14/SUMIF(B:B,B14,E:E)))/D14 -> 2507056.2 | H14: =(G14*D14) -> 2507056.2 | I14: 817.49 | J14: 0 | K14: 360 | L14: 하이델베르그
B15: 104 | C15: Moteur Baumer(WM.5793785) | D15: 1 | E15: 3196.52 | G15: =(I15*E15)+(J15*(E15/SUMIF(B:B,B15,E:E)))/D15+((K15*I15)*(E15/SUMIF(B:B,B15,E:E)))/D15 -> 2741532.3 | H15: =(G15*D15) -> 2741532.3 | I15: 817.49 | J15: 0 | K15: 360 | L15: 하이델베르그
B16: 104 | C16: Diaphragm Orange | D16: 4 | E16: 278.93 | G16: =(I16*E16)+(J16*(E16/SUMIF(B:B,B16,E:E)))/D16+((K16*I16)*(E16/SUMIF(B:B,B16,E:E)))/D16 -> 230823.75 | H16: =(G16*D16) -> 923294.99 | I16: 817.49 | J16: 0 | K16: 360 | L16: 하이델베르그
B17: 104 | C17: Cutting Rubber | D17: 50 | E17: 28.73 | G17: =(I17*E17)+(J17*(E17/SUMIF(B:B,B17,E:E)))/D17+((K17*I17)*(E17/SUMIF(B:B,B17,E:E)))/D17 -> 23509.57 | H17: =(G17*D17) -> 1175478.5 | I17: 817.49 | J17: 0 | K17: 360 | L17: 하이델베르그 | N17: WP1006160
B18: 104 | C18: Blade rotative folder chopper | D18: 5 | E18: 218.44 | G18: =(I18*E18)+(J18*(E18/SUMIF(B:B,B18,E:E)))/D18+((K18*I18)*(E18/SUMIF(B:B,B18,E:E)))/D18 -> 180327.53 | H18: =(G18*D18) -> 901637.65 | I18: 817.49 | J18: 0 | K18: 360 | L18: 하이델베르그
B19: 104 | C19: Blade Cut Off Knife | D19: 10 | E19: 71.93 | G19: =(I19*E19)+(J19*(E19/SUMIF(B:B,B19,E:E)))/D19+((K19*I19)*(E19/SUMIF(B:B,B19,E:E)))/D19 -> 59091.01 | H19: =(G19*D19) -> 590910.1 | I19: 817.49 | J19: 0 | K19: 360 | L19: 하이델베르그
B20: 104 | C20: Spark Plug | D20: 2 | E20: 605.81 | G20: =(I20*E20)+(J20*(E20/SUMIF(B:B,B20,E:E)))/D20+((K20*I20)*(E20/SUMIF(B:B,B20,E:E)))/D20 -> 507411.78 | H20: =(G20*D20) -> 1014823.6 | I20: 817.49 | J20: 0 | K20: 360 | L20: 매일경제 | M20: X
A21: 170623 | B21: 105 | C21: Stripper(T33985) | D21: 150 | E21: 9.9 | G21: =(I21*E21)+(J21*(E21/SUMIF(B:B,B21,E:E)))/D21+((K21*I21)*(E21/SUMIF(B:B,B21,E:E)))/D21 -> 8192.951 | H21: =(G21*D21) -> 1228942.7 | I21: 827.23 | J21: 0 | K21: 320
B22: 105 | C22: Stripper(T33986) | D22: 30 | E22: 9.9 | G22: =(I22*E22)+(J22*(E22/SUMIF(B:B,B22,E:E)))/D22+((K22*I22)*(E22/SUMIF(B:B,B22,E:E)))/D22 -> 8206.4471 | H22: =(G22*D22) -> 246193.41 | I22: 827.23 | J22: 0 | K22: 320
B23: 105 | C23: Stripper(T34124) | D23: 60 | E23: 9.5 | G23: =(I23*E23)+(J23*(E23/SUMIF(B:B,B23,E:E)))/D23+((K23*I23)*(E23/SUMIF(B:B,B23,E:E)))/D23 -> 7866.7793 | H23: =(G23*D23) -> 472006.76 | I23: 827.23 | J23: 0 | K23: 320
B24: 105 | C24: Stripper(T34125) | D24: 50 | E24: 9.5 | G24: =(I24*E24)+(J24*(E24/SUMIF(B:B,B24,E:E)))/D24+((K24*I24)*(E24/SUMIF(B:B,B24,E:E)))/D24 -> 7868.3981 | H24: =(G24*D24) -> 393419.91 | I24: 827.23 | J24: 0 | K24: 320
B25: 105 | C25: Roller(WH.976718) | D25: 1 | E25: 1827.38 | G25: =(I25*E25)+(J25*(E25/SUMIF(B:B,B25,E:E)))/D25+((K25*I25)*(E25/SUMIF(B:B,B25,E:E)))/D25 -> 1605082.3 | H25: =(G25*D25) -> 1605082.3 | I25: 827.23 | J25: 0 | K25: 320 | N25: 반송
B26: 105 | C26: UPP Diamphram Lockup Bar | D26: 1 | E26: 3311.93 | G26: =(I26*E26)+(J26*(E26/SUMIF(B:B,B26,E:E)))/D26+((K26*I26)*(E26/SUMIF(B:B,B26,E:E)))/D26 -> 2909039.2 | H26: =(G26*D26) -> 2909039.2 | I26: 827.23 | J26: 0 | K26: 320
A27: 170629 | B27: 106 | C27: 스플라이서 롤러 | D27: 1 | E27: =E25+260 -> 2087.38 | G27: =(I27*E27)+(J27*(E27/SUMIF(B:B,B27,E:E)))/D27+((K27*I27)*(E27/SUMIF(B:B,B27,E:E)))/D27 -> 1929921.9 | H27: =(G27*D27) -> 1929921.9 | I27: 822.16 | J27: 0 | K27: 260 | L27: 교학사 | N27: Roller(Spiral Type)
A28: 170713 | B28: 107 | C28: Roll Pinch | D28: 8 | E28: 1367.93 | G28: =(I28*E28)+(J28*(E28/SUMIF(B:B,B28,E:E)))/D28+((K28*I28)*(E28/SUMIF(B:B,B28,E:E)))/D28 -> 1224325.9 | H28: =(G28*D28) -> 9794607 | I28: 839.77 | J28: 0 | K28: 720 | L28: 하이델베르그
A29: 170720 | B29: 108 | C29: Air Cylinder Mecman 1300 | D29: 2 | E29: 161.24 | G29: =(I29*E29)+(J29*(E29/SUMIF(B:B,B29,E:E)))/D29+((K29*I29)*(E29/SUMIF(B:B,B29,E:E)))/D29 -> 156492.49 | H29: =(G29*D29) -> 312984.97 | I29: 839.73 | J29: 0 | K29: 90 | N29: WM.005801103
B30: 108 | C30: Air Cylinder, Leibfried | D30: 2 | E30: 127.6 | G30: =(I30*E30)+(J30*(E30/SUMIF(B:B,B30,E:E)))/D30+((K30*I30)*(E30/SUMIF(B:B,B30,E:E)))/D30 -> 123842.98 | H30: =(G30*D30) -> 247685.95 | I30: 839.73 | J30: 0 | K30: 90 | N30: WM.X73028
A31: 170817 | B31: 109 | C31: 핀, 레버 | D31: 4 | E31: 130.76 | G31: =(I31*E31)+(J31*(E31/SUMIF(B:B,B31,E:E)))/D31+((K31*I31)*(E31/SUMIF(B:B,B31,E:E)))/D31 -> 128433.41 | H31: =(G31*D31) -> 513733.65 | I31: 838.01 | J31: 0 | K31: 90 | L31: 프린피아 주안
A32: 170830 | B32: 110 | C32: 스프링블레이드(대) | D32: 2 | E32: 41.03 | G32: =(I32*E32)+(J32*(E32/SUMIF(B:B,B32,E:E)))/D32+((K32*I32)*(E32/SUMIF(B:B,B32,E:E)))/D32 -> 43994.666 | H32: =(G32*D32) -> 87989.331 | I32: 841.52 | J32: 0 | K32: 45
B33: 110 | C33: 스프링블레이드(소) | D33: 5 | E33: 41.03 | G33: =(I33*E33)+(J33*(E33/SUMIF(B:B,B33,E:E)))/D33+((K33*I33)*(E33/SUMIF(B:B,B33,E:E)))/D33 -> 38314.406 | H33: =(G33*D33) -> 191572.03 | I33: 841.52 | J33: 0 | K33: 45
A34: 170920 | B34: 111 | C34: 온도 센서 | D34: 1 | E34: 538.36 | G34: =(I34*E34)+(J34*(E34/SUMIF(B:B,B34,E:E)))/D34+((K34*I34)*(E34/SUMIF(B:B,B34,E:E)))/D34 -> 533379.59 | H34: =(G34*D34) -> 533379.59 | I34: 846.94 | J34: 0 | K34: 350 | L34: 재능
B35: 111 | C35: 파이프(1) | D35: 4 | E35: 143.92 | G35: =(I35*E35)+(J35*(E35/SUMIF(B:B,B35,E:E)))/D35+((K35*I35)*(E35/SUMIF(B:B,B35,E:E)))/D35 -> 127065.85 | H35: =(G35*D35) -> 508263.4 | I35: 846.94 | J35: 0 | K35: 350
B36: 111 | C36: 파이프(2) | D36: 2 | E36: 113.33 | G36: =(I36*E36)+(J36*(E36/SUMIF(B:B,B36,E:E)))/D36+((K36*I36)*(E36/SUMIF(B:B,B36,E:E)))/D36 -> 104132.64 | H36: =(G36*D36) -> 208265.28 | I36: 846.94 | J36: 0 | K36: 350
B37: 111 | C37: 잉크 파운틴 호일 | D37: 1 | E37: 380 | G37: =(I37*E37)+(J37*(E37/SUMIF(B:B,B37,E:E)))/D37+((K37*I37)*(E37/SUMIF(B:B,B37,E:E)))/D37 -> 376484.59 | H37: =(G37*D37) -> 376484.59 | I37: 846.94 | J37: 0 | K37: 350
B38: 111 | C38: 연소 튜브 | D38: 2 | E38: 509.92 | G38: =(I38*E38)+(J38*(E38/SUMIF(B:B,B38,E:E)))/D38+((K38*I38)*(E38/SUMIF(B:B,B38,E:E)))/D38 -> 468537.17 | H38: =(G38*D38)+SUM(H39:H41) -> 972711.23 | I38: 846.94 | J38: 0 | K38: 350 | L38: 교학사
B39: 111 | C39: Screw | D39: 4 | E39: 2.9 | G39: =(I39*E39)+(J39*(E39/SUMIF(B:B,B39,E:E)))/D39+((K39*I39)*(E39/SUMIF(B:B,B39,E:E)))/D39 -> 2560.3875 | H39: =(G39*D39) -> 10241.55 | I39: 846.94 | J39: 0 | K39: 350
B40: 111 | C40: Nut | D40: 4 | E40: 2.9 | G40: =(I40*E40)+(J40*(E40/SUMIF(B:B,B40,E:E)))/D40+((K40*I40)*(E40/SUMIF(B:B,B40,E:E)))/D40 -> 2560.3875 | H40: =(G40*D40) -> 10241.55 | I40: 846.94 | J40: 0 | K40: 350
B41: 111 | C41: Washer | D41: 6 | E41: 2.9 | G41: =(I41*E41)+(J41*(E41/SUMIF(B:B,B41,E:E)))/D41+((K41*I41)*(E41/SUMIF(B:B,B41,E:E)))/D41 -> 2525.6336 | H41: =(G41*D41) -> 15153.802 | I41: 846.94 | J41: 0 | K41: 350
B42: 111 | C42: 점화 플러그 | D42: 2 | E42: 175.87 | G42: =(I42*E42)+(J42*(E42/SUMIF(B:B,B42,E:E)))/D42+((K42*I42)*(E42/SUMIF(B:B,B42,E:E)))/D42 -> 161597.17 | H42: =(G42*D42) -> 323194.35 | I42: 846.94 | J42: 0 | K42: 350
B43: 111 | C43: 프레임 로드 | D43: 2 | E43: 191.17 | G43: =(I43*E43)+(J43*(E43/SUMIF(B:B,B43,E:E)))/D43+((K43*I43)*(E43/SUMIF(B:B,B43,E:E)))/D43 -> 175655.49 | H43: =(G43*D43) -> 351310.99 | I43: 846.94 | J43: 0 | K43: 350
A44: 170929 | B44: 112 | C44: Alimentation 9V/67A 600W | D44: 1 | E44: 805.74 | G44: =(I44*E44)+(J44*(E44/SUMIF(B:B,B44,E:E)))/D44+((K44*I44)*(E44/SUMIF(B:B,B44,E:E)))/D44 -> 925698.57 | H44: =(G44*D44) -> 925698.57 | I44: 1148.88 | J44: 0 | K44: 0 | N44: US달러
A45: 171030 | B45: 113 | C45: 스트리퍼(대) | D45: 100 | E45: 11 | G45: =(I45*E45)+(J45*(E45/SUMIF(B:B,B45,E:E)))/D45+((K45*I45)*(E45/SUMIF(B:B,B45,E:E)))/D45 -> 9268.0803 | H45: =(G45*D45) -> 926808.03 | I45: 836.7 | J45: 0 | K45: 240 | L45: 재능
B46: 113 | C46: 스트리퍼(소) | D46: 30 | E46: 11 | G46: =(I46*E46)+(J46*(E46/SUMIF(B:B,B46,E:E)))/D46+((K46*I46)*(E46/SUMIF(B:B,B46,E:E)))/D46 -> 9429.5575 | H46: =(G46*D46) -> 282886.72 | I46: 837.7 | J46: 0 | K46: 240
B47: 113 | C47: 벨트 | D47: 50 | E47: 9.27 | G47: =(I47*E47)+(J47*(E47/SUMIF(B:B,B47,E:E)))/D47+((K47*I47)*(E47/SUMIF(B:B,B47,E:E)))/D47 -> 7883.5184 | H47: =(G47*D47) -> 394175.92 | I47: 838.7 | J47: 0 | K47: 240 | N47: TAPE
B48: 113 | C48: 재단목 | D48: 5 | E48: 35.91 | G48: =(I48*E48)+(J48*(E48/SUMIF(B:B,B48,E:E)))/D48+((K48*I48)*(E48/SUMIF(B:B,B48,E:E)))/D48 -> 34372.147 | H48: =(G48*D48) -> 171860.73 | I48: 839.7 | J48: 0 | K48: 240 | N48: RUBBER
B49: 113 | C49: 재단칼 러버 | D49: 8 | E49: 28.73 | G49: =(I49*E49)+(J49*(E49/SUMIF(B:B,B49,E:E)))/D49+((K49*I49)*(E49/SUMIF(B:B,B49,E:E)))/D49 -> 26265.23 | H49: =(G49*D49) -> 210121.84 | I49: 840.7 | J49: 0 | K49: 240 | N49: CHEEKWOOD
B50: 113 | C50: 횡미싱 | D50: 2 | E50: 101.92 | G50: =(I50*E50)+(J50*(E50/SUMIF(B:B,B50,E:E)))/D50+((K50*I50)*(E50/SUMIF(B:B,B50,E:E)))/D50 -> 115789.93 | H50: =(G50*D50) -> 231579.87 | I50: 841.7 | J50: 0 | K50: 240 | N50: CROSS PERFORATION BLADE
B51: 113 | C51: 잉크키 보호 필름 | D51: 1 | E51: 145.27 | G51: =(I51*E51)+(J51*(E51/SUMIF(B:B,B51,E:E)))/D51+((K51*I51)*(E51/SUMIF(B:B,B51,E:E)))/D51 -> 208051.69 | H51: =(G51*D51) -> 208051.69 | I51: 842.7 | J51: 0 | K51: 240 | N51: MYLAR-INK KEY PROTECTION
A52: 171117 | B52: 114 | C52: 에어 실린더 | D52: 2 | E52: 127.6 | G52: =(I52*E52)+(J52*(E52/SUMIF(B:B,B52,E:E)))/D52+((K52*I52)*(E52/SUMIF(B:B,B52,E:E)))/D52 -> 140485.53 | H52: =(G52*D52) -> 280971.06 | I52: 841.7 | J52: 0 | K52: 80 | L52: 프린피아 주안
B53: 114 | C53: 양면 테이프 | D53: 30 | E53: 2.25 | G53: =(I53*E53)+(J53*(E53/SUMIF(B:B,B53,E:E)))/D53+((K53*I53)*(E53/SUMIF(B:B,B53,E:E)))/D53 -> 1935.0138 | H53: =(G53*D53) -> 58050.413 | I53: 842.7 | J53: 0 | K53: 80
A54: 171130 | B54: 115 | C54: STUD | D54: 1 | E54: 178.29 | G54: =(I54*E54)+(J54*(E54/SUMIF(B:B,B54,E:E)))/D54+((K54*I54)*(E54/SUMIF(B:B,B54,E:E)))/D54 -> 233900.23 | H54: =(G54*D54) -> 233900.23 | I54: 841.7 | J54: 0 | K54: 180 | L54: 프린피아 주안
B55: 115 | C55: 파이프 | D55: 6 | E55: 143.92 | G55: =(I55*E55)+(J55*(E55/SUMIF(B:B,B55,E:E)))/D55+((K55*I55)*(E55/SUMIF(B:B,B55,E:E)))/D55 -> 132573.53 | H55: =(G55*D55) -> 795441.16 | I55: 842.7 | J55: 0 | K55: 180 | L55: 프린피아 주안
A56: 171215 | B56: 116 | C56: 상하 핀맞춤 모터 | D56: 1 | E56: 3765.08 | G56: =(I56*E56)+(J56*(E56/SUMIF(B:B,B56,E:E)))/D56+((K56*I56)*(E56/SUMIF(B:B,B56,E:E)))/D56 -> 3194822.7 | H56: =(G56*D56) -> 3194822.7 | I56: 816.03 | J56: 0 | K56: 150 | L56: 재능 | N56: MOTOR, REGISTER
A57: 171226 | B57: 117 | C57: Inking Motor Reducer Siemens | D57: 1 | E57: 3186.6 | G57: =(I57*E57)+(J57*(E57/SUMIF(B:B,B57,E:E)))/D57+((K57*I57)*(E57/SUMIF(B:B,B57,E:E)))/D57 -> 2879362.1 | H57: =(G57*D57) -> 2879362.1 | I57: 814.47 | J57: 0 | K57: 350 | L57: 하이델베르그
B58: 117 | C58: Link, Chain | D58: 34 | E58: 12.26 | G58: =(I58*E58)+(J58*(E58/SUMIF(B:B,B58,E:E)))/D58+((K58*I58)*(E58/SUMIF(B:B,B58,E:E)))/D58 -> 10017.536 | H58: =(G58*D58) -> 340596.22 | I58: 814.47 | J58: 0 | K58: 350
A59: 180118 | B59: 118 | C59: Stipper 50 wide | D59: 50 | E59: 11 | G59: =(I59*E59)+(J59*(E59/SUMIF(B:B,B59,E:E)))/D59+((K59*I59)*(E59/SUMIF(B:B,B59,E:E)))/D59 -> 8978.9711 | H59: =(G59*D59) -> 448948.56 | I59: 809.33 | J59: 0 | K59: 262
B60: 118 | C60: Stripper 30 wide | D60: 30 | E60: 11 | G60: =(I60*E60)+(J60*(E60/SUMIF(B:B,B60,E:E)))/D60+((K60*I60)*(E60/SUMIF(B:B,B60,E:E)))/D60 -> 9029.8652 | H60: =(G60*D60) -> 270895.96 | I60: 809.33 | J60: 0 | K60: 262
B61: 118 | C61: Stripper 30 wide | D61: 70 | E61: 11 | G61: =(I61*E61)+(J61*(E61/SUMIF(B:B,B61,E:E)))/D61+((K61*I61)*(E61/SUMIF(B:B,B61,E:E)))/D61 -> 8957.1594 | H61: =(G61*D61) -> 627001.16 | I61: 809.33 | J61: 0 | K61: 262
B62: 118 | C62: Stripper 50 wide | D62: 40 | E62: 11 | G62: =(I62*E62)+(J62*(E62/SUMIF(B:B,B62,E:E)))/D62+((K62*I62)*(E62/SUMIF(B:B,B62,E:E)))/D62 -> 8998.0564 | H62: =(G62*D62) -> 359922.26 | I62: 809.33 | J62: 0 | K62: 262
B63: 118 | C63: Pressure Dif. Converter | D63: 2 | E63: 550.72 | G63: =(I63*E63)+(J63*(E63/SUMIF(B:B,B63,E:E)))/D63+((K63*I63)*(E63/SUMIF(B:B,B63,E:E)))/D63 -> 541265.57 | H63: =(G63*D63) -> 1082531.1 | I63: 809.33 | J63: 0 | K63: 262 | L63: 재능
B64: 118 | C64: Strip, Closed Cell Foam PVC | D64: 20 | E64: 2.8 | G64: =(I64*E64)+(J64*(E64/SUMIF(B:B,B64,E:E)))/D64+((K64*I64)*(E64/SUMIF(B:B,B64,E:E)))/D64 -> 2314.7047 | H64: =(G64*D64) -> 46294.095 | I64: 809.33 | J64: 0 | K64: 262
B65: 118 | C65: Brush, Head Stop | D65: 30 | E65: 13.55 | G65: =(I65*E65)+(J65*(E65/SUMIF(B:B,B65,E:E)))/D65+((K65*I65)*(E65/SUMIF(B:B,B65,E:E)))/D65 -> 11123.152 | H65: =(G65*D65) -> 333694.57 | I65: 809.33 | J65: 0 | K65: 262 | L65: 프린피아 주안
A66: 180207 | B66: 119 | C66: 파이프 | D66: 4 | E66: 152.92 | G66: =(I66*E66)+(J66*(E66/SUMIF(B:B,B66,E:E)))/D66+((K66*I66)*(E66/SUMIF(B:B,B66,E:E)))/D66 -> 130763.07 | H66: =(G66*D66) -> 523052.3 | I66: 823.81 | J66: 0 | K66: 280 | L66: 보진재
B67: 119 | C67: 워시-업 블레이드 | D67: 20 | E67: 9.72 | G67: =(I67*E67)+(J67*(E67/SUMIF(B:B,B67,E:E)))/D67+((K67*I67)*(E67/SUMIF(B:B,B67,E:E)))/D67 -> 8068.276 | H67: =(G67*D67) -> 161365.52 | I67: 823.81 | J67: 0 | K67: 280 | L67: 프린피아 문발
B68: 119 | C68: 에어 실린더(X73208) | D68: 2 | E68: 127.6 | G68: =(I68*E68)+(J68*(E68/SUMIF(B:B,B68,E:E)))/D68+((K68*I68)*(E68/SUMIF(B:B,B68,E:E)))/D68 -> 113105.34 | H68: =(G68*D68) -> 226210.68 | I68: 823.81 | J68: 0 | K68: 280 | L68: 프린피아 문발
B69: 119 | C69: 다이아프램 | D69: 2 | E69: 420 | G69: =(I69*E69)+(J69*(E69/SUMIF(B:B,B69,E:E)))/D69+((K69*I69)*(E69/SUMIF(B:B,B69,E:E)))/D69 -> 372290.3 | H69: =(G69*D69) -> 744580.59 | I69: 823.81 | J69: 0 | K69: 280 | L69: 삼화인쇄 2.8
B70: 119 | C70: 잉크 키 모터 | D70: 20 | E70: 99.56 | G70: =(I70*E70)+(J70*(E70/SUMIF(B:B,B70,E:E)))/D70+((K70*I70)*(E70/SUMIF(B:B,B70,E:E)))/D70 -> 82641.724 | H70: =(G70*D70) -> 1652834.5 | I70: 823.81 | J70: 0 | K70: 280 | L70: 한국경제
B71: 119 | C71: 벨트 | D71: 20 | E71: 6.91 | G71: =(I71*E71)+(J71*(E71/SUMIF(B:B,B71,E:E)))/D71+((K71*I71)*(E71/SUMIF(B:B,B71,E:E)))/D71 -> 5735.7806 | H71: =(G71*D71) -> 114715.61 | I71: 823.81 | J71: 0 | K71: 280 | L71: 프린피아 문발
B72: 119 | C72: 온도 센서(WH.942725) | D72: 1 | E72: 664.63 | G72: =(I72*E72)+(J72*(E72/SUMIF(B:B,B72,E:E)))/D72+((K72*I72)*(E72/SUMIF(B:B,B72,E:E)))/D72 -> 630734.49 | H72: =(G72*D72) -> 630734.49 | I72: 823.81 | J72: 0 | K72: 280 | L72: 프린피아 문발
B73: 119 | C73: 온도 센서(WH.916671) | D73: 1 | E73: 361.18 | G73: =(I73*E73)+(J73*(E73/SUMIF(B:B,B73,E:E)))/D73+((K73*I73)*(E73/SUMIF(B:B,B73,E:E)))/D73 -> 342760.16 | H73: =(G73*D73) -> 342760.16 | I73: 823.81 | J73: 0 | K73: 280 | L73: 프린피아 문발
A74: 180214 | B74: 120 | C74: 에어 실린더(X73208) | D74: 2 | E74: 127.6 | G74: =(I74*E74)+(J74*(E74/SUMIF(B:B,B74,E:E)))/D74+((K74*I74)*(E74/SUMIF(B:B,B74,E:E)))/D74 -> 122673.7 | H74: =(G74*D74) -> 245347.4 | I74: 828.69 | J74: 0 | K74: 140 | L74: 프린피아 주안
B75: 120 | C75: 다이아프램 | D75: 1 | E75: 217.53 | G75: =(I75*E75)+(J75*(E75/SUMIF(B:B,B75,E:E)))/D75+((K75*I75)*(E75/SUMIF(B:B,B75,E:E)))/D75 -> 237998.54 | H75: =(G75*D75) -> 237998.54 | I75: 828.69 | J75: 0 | K75: 140 | L75: 삼화인쇄
B76: 120 | C76: 스프링 블레이드 | D76: 5 | E76: 46 | G76: =(I76*E76)+(J76*(E76/SUMIF(B:B,B76,E:E)))/D76+((K76*I76)*(E76/SUMIF(B:B,B76,E:E)))/D76 -> 40561.468 | H76: =(G76*D76) -> 202807.34 | I76: 828.69 | J76: 0 | K76: 140 | L76: 삼화인쇄 | N76: 스프링블레이드 set
B77: 120 | C77: 스프링 레이드 | D77: 11 | E77: 46 | G77: =(I77*E77)+(J77*(E77/SUMIF(B:B,B77,E:E)))/D77+((K77*I77)*(E77/SUMIF(B:B,B77,E:E)))/D77 -> 39229.617 | H77: =(G77*D77) -> 431525.78 | I77: 828.69 | J77: 0 | K77: 140 | L77: 삼화인쇄
A78: 180305 | B78: 121 | C78: 롤러 브랑켓 | D78: 1 | E78: 277.29 | G78: =(I78*E78)+(J78*(E78/SUMIF(B:B,B78,E:E)))/D78+((K78*I78)*(E78/SUMIF(B:B,B78,E:E)))/D78 -> 307068.25 | H78: =(G78*D78) -> 307068.25 | I78: 823.03 | J78: 0 | K78: 280 | L78: 프린피아 주안
B79: 121 | C79: 연소 튜브 | D79: 1 | E79: =509.92+2.9*8 -> 533.12 | G79: =(I79*E79)+(J79*(E79/SUMIF(B:B,B79,E:E)))/D79+((K79*I79)*(E79/SUMIF(B:B,B79,E:E)))/D79 -> 590371.9 | H79: =(G79*D79) -> 590371.9 | I79: 823.03 | J79: 0 | K79: 280 | L79: 팩컴
B80: 122 | C80: 재능 옴니콘 업그레이드 계약금 | D80: 1 | E80: 26400 | G80: =(I80*E80)+(J80*(E80/SUMIF(B:B,B80,E:E)))/D80+((K80*I80)*(E80/SUMIF(B:B,B80,E:E)))/D80 -> 28865232 | H80: =(G80*D80) -> 28865232 | I80: 1093.38 | K80: 0 | L80: 재능 | N80: USD
B81: 123 | C81: 재능 옴니콘 업그레이드 중도금 | D81: 1 | E81: 33000 | G81: =(I81*E81)+(J81*(E81/SUMIF(B:B,B81,E:E)))/D81+((K81*I81)*(E81/SUMIF(B:B,B81,E:E)))/D81 -> 35841960 | H81: =(G81*D81) -> 35841960 | I81: 1086.12 | J81: 0 | K81: 0 | L81: 재능 | N81: USD
B82: 124 | C82: 재능 옴니콘 업그레이드 잔금 | D82: 1 | E82: 6600 | G82: =(I82*E82)+(J82*(E82/SUMIF(B:B,B82,E:E)))/D82+((K82*I82)*(E82/SUMIF(B:B,B82,E:E)))/D82 -> 7594000 | H82: =(G82*D82) -> 7594000 | I82: 1065 | J82: 565000 | K82: 0 | L82: 재능
A83: 180409 | B83: 125 | C83: 브러쉬, 헤드 스톱 | D83: 30 | E83: 13.55 | G83: =(I83*E83)+(J83*(E83/SUMIF(B:B,B83,E:E)))/D83+((K83*I83)*(E83/SUMIF(B:B,B83,E:E)))/D83 -> 11730.592 | H83: =(G83*D83) -> 351917.77 | I83: 815.18 | J83: 0 | K83: 380 | L83: 프린피아 주안
B84: 125 | C84: 커팅 러버 | D84: 6 | E84: 28.73 | G84: =(I84*E84)+(J84*(E84/SUMIF(B:B,B84,E:E)))/D84+((K84*I84)*(E84/SUMIF(B:B,B84,E:E)))/D84 -> 30681.108 | H84: =(G84*D84) -> 184086.65 | I84: 815.18 | J84: 0 | K84: 380 | L84: 보진재
B85: 125 | C85: 스트리퍼(대) | D85: 200 | E85: 11 | G85: =(I85*E85)+(J85*(E85/SUMIF(B:B,B85,E:E)))/D85+((K85*I85)*(E85/SUMIF(B:B,B85,E:E)))/D85 -> 9050.3815 | H85: =(G85*D85) -> 1810076.3 | I85: 815.18 | J85: 0 | K85: 380 | L85: 프린피아 주안 | N85: 재고잇음(5/14)
B86: 125 | C86: 스트리퍼(소) | D86: 50 | E86: 11 | G86: =(I86*E86)+(J86*(E86/SUMIF(B:B,B86,E:E)))/D86+((K86*I86)*(E86/SUMIF(B:B,B86,E:E)))/D86 -> 9300.5861 | H86: =(G86*D86) -> 465029.3 | I86: 815.18 | J86: 0 | K86: 380 | L86: 프린피아 주안 | N86: 재고잇음(5/14)
B87: 125 | C87: 브레이크 라이닝 | D87: 8 | E87: 140 | G87: =(I87*E87)+(J87*(E87/SUMIF(B:B,B87,E:E)))/D87+((K87*I87)*(E87/SUMIF(B:B,B87,E:E)))/D87 -> 140662.05 | H87: =(G87*D87) -> 1125296.4 | I87: 815.18 | J87: 0 | K87: 380 | L87: 프린피아 주안
A88: 180430 | B88: 126 | C88: 접지칼 | D88: 6 | E88: 45.82 | G88: =(I88*E88)+(J88*(E88/SUMIF(B:B,B88,E:E)))/D88+((K88*I88)*(E88/SUMIF(B:B,B88,E:E)))/D88 -> 52569.807 | H88: =(G88*D88) -> 315418.84 | I88: 819.44 | J88: 0 | K88: 110 | L88: 매일경제
A89: 180516 | B89: 127 | C89: 솔레노이드 밸브(single) | D89: 2 | E89: 354.55 | G89: =(I89*E89)+(J89*(E89/SUMIF(B:B,B89,E:E)))/D89+((K89*I89)*(E89/SUMIF(B:B,B89,E:E)))/D89 -> 445556.31 | H89: =(G89*D89) -> 891112.62 | I89: 1083.51 | J89: 373240 | K89: 110 | L89: 한국경제 | N89: USD
B90: 127 | C90: 솔레노이드 밸브(double) | D90: 2 | E90: 401.82 | G90: =(I90*E90)+(J90*(E90/SUMIF(B:B,B90,E:E)))/D90+((K90*I90)*(E90/SUMIF(B:B,B90,E:E)))/D90 -> 504959.63 | H90: =(G90*D90) -> 1009919.3 | I90: 1083.51 | J90: 373240 | K90: 110
B91: 127 | C91: 체크 밸브 | D91: 4 | E91: 661.83 | G91: =(I91*E91)+(J91*(E91/SUMIF(B:B,B91,E:E)))/D91+((K91*I91)*(E91/SUMIF(B:B,B91,E:E)))/D91 -> 774404.36 | H91: =(G91*D91) -> 3097617.5 | I91: 1083.51 | J91: 373240 | K91: 110
B92: 127 | C92: O-ring 0024 | D92: 10 | E92: 3.59 | G92: =(I92*E92)+(J92*(E92/SUMIF(B:B,B92,E:E)))/D92+((K92*I92)*(E92/SUMIF(B:B,B92,E:E)))/D92 -> 4014.1378 | H92: =(G92*D92) -> 40141.378 | I92: 1083.51 | J92: 373240 | K92: 110
A93: 180522 | B93: 128 | C93: 페이퍼 홀더 | D93: 150 | E93: 37.77 | G93: =(I93*E93)+(J93*(E93/SUMIF(B:B,B93,E:E)))/D93+((K93*I93)*(E93/SUMIF(B:B,B93,E:E)))/D93 -> 42946.725 | H93: =(G93*D93) -> 6442008.7 | I93: 1083.51 | J93: 0 | K93: 280 | L93: 매일경제 | N93: USD
A94: 180528 | B94: 129 | C94: 웹 가이드 센서 | D94: 3 | E94: 778.45 | G94: =(I94*E94)+(J94*(E94/SUMIF(B:B,B94,E:E)))/D94+((K94*I94)*(E94/SUMIF(B:B,B94,E:E)))/D94 -> 882018.95 | H94: =(G94*D94) -> 2646056.9 | I94: 1091 | J94: 0 | K94: 90 | N94: USD
A95: 180608 | B95: 130 | C95: 베트남 부품 세트 | D95: 1 | E95: 38280.88 | G95: =(I95*E95)+(J95*(E95/SUMIF(B:B,B95,E:E)))/D95+((K95*I95)*(E95/SUMIF(B:B,B95,E:E)))/D95+2*G88 -> 31902419 | H95: =(G95*D95) -> 31902419 | I95: 810.93 | J95: 0 | K95: 930 | L95: 하이델베르그 | N95: SGD
A96: 180615 | B96: 131 | C96: 스트리퍼 | D96: 400 | E96: 8.22 | G96: =(I96*E96)+(J96*(E96/SUMIF(B:B,B96,E:E)))/D96+((K96*I96)*(E96/SUMIF(B:B,B96,E:E)))/D96 -> 9511.1768 | H96: =(G96*D96) -> 3804470.7 | I96: 1081.43 | J96: 0 | K96: 230 | N96: USD
A97: 180705 | B97: 132 | C97: 웹 가이드 센서 | D97: 1 | E97: 760.68 | G97: =(I97*E97)+(J97*(E97/SUMIF(B:B,B97,E:E)))/D97+((K97*I97)*(E97/SUMIF(B:B,B97,E:E)))/D97 -> 968773.27 | H97: =(G97*D97) -> 968773.27 | I97: 1126.74 | J97: 0 | K97: 110 | N97: USD
B98: 132 | C98: 재단목 | D98: 10 | E98: 26.26 | G98: =(I98*E98)+(J98*(E98/SUMIF(B:B,B98,E:E)))/D98+((K98*I98)*(E98/SUMIF(B:B,B98,E:E)))/D98 -> 29973.747 | H98: =(G98*D98) -> 299737.47 | I98: 1126.74 | J98: 0 | K98: 110 | L98: 팩컴 | N98: USD
B99: 132 | C99: 재단칼 | D99: 5 | E99: 57.22 | G99: =(I99*E99)+(J99*(E99/SUMIF(B:B,B99,E:E)))/D99+((K99*I99)*(E99/SUMIF(B:B,B99,E:E)))/D99 -> 66152.296 | H99: =(G99*D99) -> 330761.48 | I99: 1126.74 | J99: 0 | K99: 110 | L99: 매일경제 | N99: USD
A100: 180717 | B100: 133 | C100: 에어 실린더 | D100: 10 | E100: 107.85 | G100: =(I100*E100)+(J100*(E100/SUMIF(B:B,B100,E:E)))/D100+((K100*I100)*(E100/SUMIF(B:B,B100,E:E)))/D100 -> 125468.6 | H100: =(G100*D100) -> 1254686 | I100: 1129.3 | J100: 0 | K100: 120 | L100: 프린피아 파주출판단지 | N100: USD
...

Sheet 2023
A1: Sales
B2: 2023
A3: Product | B3: 1 | C3: 2 | D3: 3 | E3: 4 | F3: 5 | G3: 6 | H3: 7 | I3: 8 | J3: 9 | K3: 10 | L3: 11 | M3: 12 | N3: TOTAL | O3: Portion
A4: Film | B4: =SUMIF(INDIRECT("Report!I5612:I5676"),A4,INDIRECT("Report!G5612:G5676")) -> 6726000 | C4: =SUMIF(INDIRECT("Report!I5677:I5748"),A4,INDIRECT("Report!G5677:G5748")) -> 500000 | D4: =SUMIF(INDIRECT("Report!I5749:I5818"),A4,INDIRECT("Report!G5749:G5818")) -> 180000 | E4: =SUMIF(INDIRECT("Report!I5819:I5885"),A4,INDIRECT("Report!G5819:G5885")) -> 3363000 | F4: =SUMIF(INDIRECT("Report!I5886:I5962"),A4,INDIRECT("Report!G5886:G5962")) -> 404000 | G4: =SUMIF(INDIRECT("Report!I5963:I6041"),A4,INDIRECT("Report!G5963:G6041")) -> 3915000 | H4: =SUMIF(INDIRECT("Report!I6042:I6109"),A4,INDIRECT("Report!G6042:G6109")) -> 3363000 | I4: =SUMIF(INDIRECT("Report!I6110:I6174"),A4,INDIRECT("Report!G6110:G6174")) -> 3647000 | J4: =SUMIF(INDIRECT("Report!I6175:I6250"),A4,INDIRECT("Report!G6175:G6250")) -> 3693000 | K4: =SUMIF(INDIRECT("Report!I6251:I6319"),A4,INDIRECT("Report!G6251:G6319")) -> 4113000 | L4: =SUMIF(INDIRECT("Report!I6321:I6421"),A4,INDIRECT("Report!G6321:G6421")) -> 6633000 | M4: =SUMIF(INDIRECT("Report!I6422:I6510"),A4,INDIRECT("Report!G6422:G6510")) -> 3554000 | N4: =SUM(B4:M4) -> 40091000 | O4: =N4/$N$20 -> 0.015967865
A5: Fount | B5: =SUMIF(INDIRECT("Report!I5612:I5676"),A5,INDIRECT("Report!G5612:G5676")) -> 0 | C5: =SUMIF(INDIRECT("Report!I5677:I5748"),A5,INDIRECT("Report!G5677:G5748")) -> 5790000 | D5: =SUMIF(INDIRECT("Report!I5749:I5818"),A5,INDIRECT("Report!G5749:G5818")) -> 2895000 | E5: =SUMIF(INDIRECT("Report!I5819:I5885"),A5,INDIRECT("Report!G5819:G5885")) -> 1930000 | F5: =SUMIF(INDIRECT("Report!I5886:I5962"),A5,INDIRECT("Report!G5886:G5962")) -> 2895000 | G5: =SUMIF(INDIRECT("Report!I5963:I6041"),A5,INDIRECT("Report!G5963:G6041")) -> 1930000 | H5: =SUMIF(INDIRECT("Report!I6042:I6109"),A5,INDIRECT("Report!G6042:G6109")) -> 2895000 | I5: =SUMIF(INDIRECT("Report!I6110:I6174"),A5,INDIRECT("Report!G6110:G6174")) -> 2895000 | J5: =SUMIF(INDIRECT("Report!I6175:I6250"),A5,INDIRECT("Report!G6175:G6250")) -> 1930000 | K5: =SUMIF(INDIRECT("Report!I6251:I6319"),A5,INDIRECT("Report!G6251:G6319")) -> 5790000 | L5: =SUMIF(INDIRECT("Report!I6321:I6421"),A5,INDIRECT("Report!G6321:G6421")) -> 3860000 | M5: =SUMIF(INDIRECT("Report!I6422:I6510"),A5,INDIRECT("Report!G6422:G6510")) -> 4825000 | N5: =SUM(B5:M5) -> 37635000 | O5: =N5/$N$20 -> 0.014989664
A6: Roller | B6: =SUMIF(INDIRECT("Report!I5612:I5676"),A6,INDIRECT("Report!G5612:G5676")) -> 11781000 | C6: =SUMIF(INDIRECT("Report!I5677:I5748"),A6,INDIRECT("Report!G5677:G5748")) -> 0 | D6: =SUMIF(INDIRECT("Report!I5749:I5818"),A6,INDIRECT("Report!G5749:G5818")) -> 0 | E6: =SUMIF(INDIRECT("Report!I5819:I5885"),A6,INDIRECT("Report!G5819:G5885")) -> 6644000 | F6: =SUMIF(INDIRECT("Report!I5886:I5962"),A6,INDIRECT("Report!G5886:G5962")) -> 23780000 | G6: =SUMIF(INDIRECT("Report!I5963:I6041"),A6,INDIRECT("Report!G5963:G6041")) -> 0 | H6: =SUMIF(INDIRECT("Report!I6042:I6109"),A6,INDIRECT("Report!G6042:G6109")) -> 0 | I6: =SUMIF(INDIRECT("Report!I6110:I6174"),A6,INDIRECT("Report!G6110:G6174")) -> 0 | J6: =SUMIF(INDIRECT("Report!I6175:I6250"),A6,INDIRECT("Report!G6175:G6250")) -> 8558000 | K6: =SUMIF(INDIRECT("Report!I6251:I6319"),A6,INDIRECT("Report!G6251:G6319")) -> 0 | L6: =SUMIF(INDIRECT("Report!I6321:I6421"),A6,INDIRECT("Report!G6321:G6421")) -> 0 | M6: =SUMIF(INDIRECT("Report!I6422:I6510"),A6,INDIRECT("Report!G6422:G6510")) -> 0 | N6: =SUM(B6:M6) -> 50763000 | O6: =N6/$N$20 -> 0.020218422
A7: Blanket | B7: =SUMIF(INDIRECT("Report!I5612:I5676"),A7,INDIRECT("Report!G5612:G5676")) -> 4044000 | C7: =SUMIF(INDIRECT("Report!I5677:I5748"),A7,INDIRECT("Report!G5677:G5748")) -> 9074000 | D7: =SUMIF(INDIRECT("Report!I5749:I5818"),A7,INDIRECT("Report!G5749:G5818")) -> 8774000 | E7: =SUMIF(INDIRECT("Report!I5819:I5885"),A7,INDIRECT("Report!G5819:G5885")) -> 10760000 | F7: =SUMIF(INDIRECT("Report!I5886:I5962"),A7,INDIRECT("Report!G5886:G5962")) -> 6805000 | G7: =SUMIF(INDIRECT("Report!I5963:I6041"),A7,INDIRECT("Report!G5963:G6041")) -> 8054000 | H7: =SUMIF(INDIRECT("Report!I6042:I6109"),A7,INDIRECT("Report!G6042:G6109")) -> 8094000 | I7: =SUMIF(INDIRECT("Report!I6110:I6174"),A7,INDIRECT("Report!G6110:G6174")) -> 8484000 | J7: =SUMIF(INDIRECT("Report!I6175:I6250"),A7,INDIRECT("Report!G6175:G6250")) -> 7914000 | K7: =SUMIF(INDIRECT("Report!I6251:I6319"),A7,INDIRECT("Report!G6251:G6319")) -> 5440000 | L7: =SUMIF(INDIRECT("Report!I6321:I6421"),A7,INDIRECT("Report!G6321:G6421")) -> 13408000 | M7: =SUMIF(INDIRECT("Report!I6422:I6510"),A7,INDIRECT("Report!G6422:G6510")) -> 7268000 | N7: =SUM(B7:M7) -> 98119000 | O7: =N7/$N$20 -> 0.039079868
A8: Wash | B8: =SUMIF(INDIRECT("Report!I5612:I5676"),A8,INDIRECT("Report!G5612:G5676")) -> 10707000 | C8: =SUMIF(INDIRECT("Report!I5677:I5748"),A8,INDIRECT("Report!G5677:G5748")) -> 14800000 | D8: =SUMIF(INDIRECT("Report!I5749:I5818"),A8,INDIRECT("Report!G5749:G5818")) -> 13278000 | E8: =SUMIF(INDIRECT("Report!I5819:I5885"),A8,INDIRECT("Report!G5819:G5885")) -> 6835000 | F8: =SUMIF(INDIRECT("Report!I5886:I5962"),A8,INDIRECT("Report!G5886:G5962")) -> 22325000 | G8: =SUMIF(INDIRECT("Report!I5963:I6041"),A8,INDIRECT("Report!G5963:G6041")) -> 9603000 | H8: =SUMIF(INDIRECT("Report!I6042:I6109"),A8,INDIRECT("Report!G6042:G6109")) -> 10370000 | I8: =SUMIF(INDIRECT("Report!I6110:I6174"),A8,INDIRECT("Report!G6110:G6174")) -> 11198000 | J8: =SUMIF(INDIRECT("Report!I6175:I6250"),A8,INDIRECT("Report!G6175:G6250")) -> 12431000 | K8: =SUMIF(INDIRECT("Report!I6251:I6319"),A8,INDIRECT("Report!G6251:G6319")) -> 14870000 | L8: =SUMIF(INDIRECT("Report!I6321:I6421"),A8,INDIRECT("Report!G6321:G6421")) -> 14051000 | M8: =SUMIF(INDIRECT("Report!I6422:I6510"),A8,INDIRECT("Report!G6422:G6510")) -> 19523000 | N8: =SUM(B8:M8) -> 159991000 | O8: =N8/$N$20 -> 0.063722899
A9: 농도계 | B9: =SUMIF(INDIRECT("Report!I5612:I5676"),A9,INDIRECT("Report!G5612:G5676")) -> 0 | C9: =SUMIF(INDIRECT("Report!I5677:I5748"),A9,INDIRECT("Report!G5677:G5748")) -> 0 | D9: =SUMIF(INDIRECT("Report!I5749:I5818"),A9,INDIRECT("Report!G5749:G5818")) -> 0 | E9: =SUMIF(INDIRECT("Report!I5819:I5885"),A9,INDIRECT("Report!G5819:G5885")) -> 0 | F9: =SUMIF(INDIRECT("Report!I5886:I5962"),A9,INDIRECT("Report!G5886:G5962")) -> 0 | G9: =SUMIF(INDIRECT("Report!I5963:I6041"),A9,INDIRECT("Report!G5963:G6041")) -> 0 | H9: =SUMIF(INDIRECT("Report!I6042:I6109"),A9,INDIRECT("Report!G6042:G6109")) -> 0 | I9: =SUMIF(INDIRECT("Report!I6110:I6174"),A9,INDIRECT("Report!G6110:G6174")) -> 0 | J9: =SUMIF(INDIRECT("Report!I6175:I6250"),A9,INDIRECT("Report!G6175:G6250")) -> 0 | K9: =SUMIF(INDIRECT("Report!I6251:I6319"),A9,INDIRECT("Report!G6251:G6319")) -> 0 | L9: =SUMIF(INDIRECT("Report!I6321:I6421"),A9,INDIRECT("Report!G6321:G6421")) -> 0 | M9: =SUMIF(INDIRECT("Report!I6422:I6510"),A9,INDIRECT("Report!G6422:G6510")) -> 0 | N9: =SUM(B9:M9) -> 0 | O9: =N9/$N$20 -> 0
A10: UV lamp | B10: =SUMIF(INDIRECT("Report!I5612:I5676"),A10,INDIRECT("Report!G5612:G5676")) -> 0 | C10: =SUMIF(INDIRECT("Report!I5677:I5748"),A10,INDIRECT("Report!G5677:G5748")) -> 0 | D10: =SUMIF(INDIRECT("Report!I5749:I5818"),A10,INDIRECT("Report!G5749:G5818")) -> 0 | E10: =SUMIF(INDIRECT("Report!I5819:I5885"),A10,INDIRECT("Report!G5819:G5885")) -> 0 | F10: =SUMIF(INDIRECT("Report!I5886:I5962"),A10,INDIRECT("Report!G5886:G5962")) -> 1580000 | G10: =SUMIF(INDIRECT("Report!I5963:I6041"),A10,INDIRECT("Report!G5963:G6041")) -> 0 | H10: =SUMIF(INDIRECT("Report!I6042:I6109"),A10,INDIRECT("Report!G6042:G6109")) -> 0 | I10: =SUMIF(INDIRECT("Report!I6110:I6174"),A10,INDIRECT("Report!G6110:G6174")) -> 0 | J10: =SUMIF(INDIRECT("Report!I6175:I6250"),A10,INDIRECT("Report!G6175:G6250")) -> 0 | K10: =SUMIF(INDIRECT("Report!I6251:I6319"),A10,INDIRECT("Report!G6251:G6319")) -> 0 | L10: =SUMIF(INDIRECT("Report!I6321:I6421"),A10,INDIRECT("Report!G6321:G6421")) -> 0 | M10: =SUMIF(INDIRECT("Report!I6422:I6510"),A10,INDIRECT("Report!G6422:G6510")) -> 4650000 | N10: =SUM(B10:M10) -> 6230000 | O10: =N10/$N$20 -> 0.00248135
A11: CTP(IHK) | B11: =SUMIF(INDIRECT("Report!I5612:I5676"),A11,INDIRECT("Report!G5612:G5676")) -> 0 | C11: =SUMIF(INDIRECT("Report!I5677:I5748"),A11,INDIRECT("Report!G5677:G5748")) -> 2695000 | D11: =SUMIF(INDIRECT("Report!I5749:I5818"),A11,INDIRECT("Report!G5749:G5818")) -> 4820000 | E11: =SUMIF(INDIRECT("Report!I5819:I5885"),A11,INDIRECT("Report!G5819:G5885")) -> 2447200 | F11: =SUMIF(INDIRECT("Report!I5886:I5962"),A11,INDIRECT("Report!G5886:G5962")) -> 4576000 | G11: =SUMIF(INDIRECT("Report!I5963:I6041"),A11,INDIRECT("Report!G5963:G6041")) -> 7096400 | H11: =SUMIF(INDIRECT("Report!I6042:I6109"),A11,INDIRECT("Report!G6042:G6109")) -> 4820000 | I11: =SUMIF(INDIRECT("Report!I6110:I6174"),A11,INDIRECT("Report!G6110:G6174")) -> 7169200 | J11: =SUMIF(INDIRECT("Report!I6175:I6250"),A11,INDIRECT("Report!G6175:G6250")) -> 4820000 | K11: =SUMIF(INDIRECT("Report!I6251:I6319"),A11,INDIRECT("Report!G6251:G6319")) -> 6621050 | L11: =SUMIF(INDIRECT("Report!I6321:I6421"),A11,INDIRECT("Report!G6321:G6421")) -> 4592000 | M11: =SUMIF(INDIRECT("Report!I6422:I6510"),A11,INDIRECT("Report!G6422:G6510")) -> 0 | N11: =SUM(B11:M11) -> 49656850 | O11: =N11/$N$20 -> 0.019777853
A12: Others(IHK) | B12: =SUMIF(INDIRECT("Report!I5612:I5676"),A12,INDIRECT("Report!G5612:G5676")) -> 8188000 | C12: =SUMIF(INDIRECT("Report!I5677:I5748"),A12,INDIRECT("Report!G5677:G5748")) -> 11748000 | D12: =SUMIF(INDIRECT("Report!I5749:I5818"),A12,INDIRECT("Report!G5749:G5818")) -> 7835000 | E12: =SUMIF(INDIRECT("Report!I5819:I5885"),A12,INDIRECT("Report!G5819:G5885")) -> 11680000 | F12: =SUMIF(INDIRECT("Report!I5886:I5962"),A12,INDIRECT("Report!G5886:G5962")) -> 11555000 | G12: =SUMIF(INDIRECT("Report!I5963:I6041"),A12,INDIRECT("Report!G5963:G6041")) -> 8355000 | H12: =SUMIF(INDIRECT("Report!I6042:I6109"),A12,INDIRECT("Report!G6042:G6109")) -> 9660000 | I12: =SUMIF(INDIRECT("Report!I6110:I6174"),A12,INDIRECT("Report!G6110:G6174")) -> 8075000 | J12: =SUMIF(INDIRECT("Report!I6175:I6250"),A12,INDIRECT("Report!G6175:G6250")) -> 8025000 | K12: =SUMIF(INDIRECT("Report!I6251:I6319"),A12,INDIRECT("Report!G6251:G6319")) -> 9725000 | L12: =SUMIF(INDIRECT("Report!I6321:I6421"),A12,INDIRECT("Report!G6321:G6421")) -> 18084000 | M12: =SUMIF(INDIRECT("Report!I6422:I6510"),A12,INDIRECT("Report!G6422:G6510")) -> 12170000 | N12: =SUM(B12:M12) -> 125100000 | O12: =N12/$N$20 -> 0.049826145
A13: Technotrans | B13: =SUMIF(INDIRECT("Report!I5612:I5676"),A13,INDIRECT("Report!G5612:G5676")) -> 2870000 | C13: =SUMIF(INDIRECT("Report!I5677:I5748"),A13,INDIRECT("Report!G5677:G5748")) -> 1985000 | D13: =SUMIF(INDIRECT("Report!I5749:I5818"),A13,INDIRECT("Report!G5749:G5818")) -> 4450000 | E13: =SUMIF(INDIRECT("Report!I5819:I5885"),A13,INDIRECT("Report!G5819:G5885")) -> 0 | F13: =SUMIF(INDIRECT("Report!I5886:I5962"),A13,INDIRECT("Report!G5886:G5962")) -> 500000 | G13: =SUMIF(INDIRECT("Report!I5963:I6041"),A13,INDIRECT("Report!G5963:G6041")) -> 3230000 | H13: =SUMIF(INDIRECT("Report!I6042:I6109"),A13,INDIRECT("Report!G6042:G6109")) -> 2020000 | I13: =SUMIF(INDIRECT("Report!I6110:I6174"),A13,INDIRECT("Report!G6110:G6174")) -> 750000 | J13: =SUMIF(INDIRECT("Report!I6175:I6250"),A13,INDIRECT("Report!G6175:G6250")) -> 840000 | K13: =SUMIF(INDIRECT("Report!I6251:I6319"),A13,INDIRECT("Report!G6251:G6319")) -> 0 | L13: =SUMIF(INDIRECT("Report!I6321:I6421"),A13,INDIRECT("Report!G6321:G6421")) -> 1365000 | M13: =SUMIF(INDIRECT("Report!I6422:I6510"),A13,INDIRECT("Report!G6422:G6510")) -> 1500000 | N13: =SUM(B13:M13) -> 19510000 | O13: =N13/$N$20 -> 0.0077706481
A14: GOSS | B14: =SUMIF(INDIRECT("Report!I5612:I5676"),A14,INDIRECT("Report!G5612:G5676")) -> 11530000 | C14: =SUMIF(INDIRECT("Report!I5677:I5748"),A14,INDIRECT("Report!G5677:G5748")) -> 41860000 | D14: =SUMIF(INDIRECT("Report!I5749:I5818"),A14,INDIRECT("Report!G5749:G5818")) -> 20660000 | E14: =SUMIF(INDIRECT("Report!I5819:I5885"),A14,INDIRECT("Report!G5819:G5885")) -> 426428000 | F14: =SUMIF(INDIRECT("Report!I5886:I5962"),A14,INDIRECT("Report!G5886:G5962")) -> 20800000 | G14: =SUMIF(INDIRECT("Report!I5963:I6041"),A14,INDIRECT("Report!G5963:G6041")) -> 99835000 | H14: =SUMIF(INDIRECT("Report!I6042:I6109"),A14,INDIRECT("Report!G6042:G6109")) -> 54011000 | I14: =SUMIF(INDIRECT("Report!I6110:I6174"),A14,INDIRECT("Report!G6110:G6174")) -> 0 | J14: =SUMIF(INDIRECT("Report!I6175:I6250"),A14,INDIRECT("Report!G6175:G6250")) -> 9410000 | K14: =SUMIF(INDIRECT("Report!I6251:I6319"),A14,INDIRECT("Report!G6251:G6319")) -> 9950000 | L14: =SUMIF(INDIRECT("Report!I6321:I6421"),A14,INDIRECT("Report!G6321:G6421")) -> 106536364 | M14: =SUMIF(INDIRECT("Report!I6422:I6510"),A14,INDIRECT("Report!G6422:G6510")) -> 10310000 | N14: =SUM(B14:M14) -> 811330364 | O14: =N14/$N$20 -> 0.3231452
A15: Service | B15: =SUMIF(INDIRECT("Report!I5612:I5676"),A15,INDIRECT("Report!G5612:G5676")) -> 1115000 | C15: =SUMIF(INDIRECT("Report!I5677:I5748"),A15,INDIRECT("Report!G5677:G5748")) -> 1000000 | D15: =SUMIF(INDIRECT("Report!I5749:I5818"),A15,INDIRECT("Report!G5749:G5818")) -> 0 | E15: =SUMIF(INDIRECT("Report!I5819:I5885"),A15,INDIRECT("Report!G5819:G5885")) -> 2625000 | F15: =SUMIF(INDIRECT("Report!I5886:I5962"),A15,INDIRECT("Report!G5886:G5962")) -> 5780000 | G15: =SUMIF(INDIRECT("Report!I5963:I6041"),A15,INDIRECT("Report!G5963:G6041")) -> 4215000 | H15: =SUMIF(INDIRECT("Report!I6042:I6109"),A15,INDIRECT("Report!G6042:G6109")) -> 16760000 | I15: =SUMIF(INDIRECT("Report!I6110:I6174"),A15,INDIRECT("Report!G6110:G6174")) -> 2625000 | J15: =SUMIF(INDIRECT("Report!I6175:I6250"),A15,INDIRECT("Report!G6175:G6250")) -> 0 | K15: =SUMIF(INDIRECT("Report!I6251:I6319"),A15,INDIRECT("Report!G6251:G6319")) -> 6425000 | L15: =SUMIF(INDIRECT("Report!I6321:I6421"),A15,INDIRECT("Report!G6321:G6421")) -> 0 | M15: =SUMIF(INDIRECT("Report!I6422:I6510"),A15,INDIRECT("Report!G6422:G6510")) -> 700000 | N15: =SUM(B15:M15) -> 41245000 | O15: =N15/$N$20 -> 0.016427493
... A19: Others | B19: =SUMIF(INDIRECT("Report!I5612:I5676"),A19,INDIRECT("Report!G5612:G5676")) -> 22602636 | C19: =SUMIF(INDIRECT("Report!I5677:I5748"),A19,INDIRECT("Report!G5677:G5748")) -> 78982850 | D19: =SUMIF(INDIRECT("Report!I5749:I5818"),A19,INDIRECT("Report!G5749:G5818")) -> 23599455 | E19: =SUMIF(INDIRECT("Report!I5819:I5885"),A19,INDIRECT("Report!G5819:G5885")) -> 23999000 | F19: =SUMIF(INDIRECT("Report!I5886:I5962"),A19,INDIRECT("Report!G5886:G5962")) -> 24131000 | G19: =SUMIF(INDIRECT("Report!I5963:I6041"),A19,INDIRECT("Report!G5963:G6041")) -> 27078000 | H19: =SUMIF(INDIRECT("Report!I6042:I6109"),A19,INDIRECT("Report!G6042:G6109")) -> 16298000 | I19: =SUMIF(INDIRECT("Report!I6110:I6174"),A19,INDIRECT("Report!G6110:G6174")) -> 17866000 | J19: =SUMIF(INDIRECT("Report!I6175:I6250"),A19,INDIRECT("Report!G6175:G6250")) -> 25671000 | K19: =SUMIF(INDIRECT("Report!I6251:I6319"),A19,INDIRECT("Report!G6251:G6319")) -> 24691637 | L19: =SUMIF(INDIRECT("Report!I6321:I6421"),A19,INDIRECT("Report!G6321:G6421")) -> 71886728 | M19: =SUMIF(INDIRECT("Report!I6422:I6510"),A19,INDIRECT("Report!G6422:G6510")) -> 75071454 | N19: =SUM(B19:M19) -> 4.3187776e+08 | O19: =N19/$N$20 -> 0.17201282
A20: Total(VAT x) | B20: =SUM(B4:B19) -> 142115436 | C20: =SUM(C4:C19) -> 231870050 | D20: =SUM(D4:D19) -> 149612455 | E20: =SUM(E4:E19) -> 554335600 | F20: =SUM(F4:F19) -> 181183000 | G20: =SUM(G4:G19) -> 214048000 | H20: =SUM(H4:H19) -> 171289600 | I20: =SUM(I4:I19) -> 113837000 | ... O20: =SUM(O4:O19) -> 1
A22: Margin
B23: 2023
A24: Product | B24: 1 | C24: 2 | D24: 3 | E24: 4 | F24: 5 | G24: 6 | H24: 7 | I24: 8 | J24: 9 | K24: 10 | L24: 11 | M24: 12 | N24: TOTAL | O24: Portion | P24: 품목별 Margin
A25: Film | B25: =SUMIF(INDIRECT("Report!I5612:I5676"),A25,INDIRECT("Report!J5612:J5676")) -> 3041720 | C25: =SUMIF(INDIRECT("Report!I5677:I5748"),A25,INDIRECT("Report!J5677:J5748")) -> 205700 | D25: =SUMIF(INDIRECT("Report!I5749:I5818"),A25,INDIRECT("Report!J5749:J5818")) -> -170000 | E25: =SUMIF(INDIRECT("Report!I5819:I5885"),A25,INDIRECT("Report!J5819:J5885")) -> 601940 | F25: =SUMIF(INDIRECT("Report!I5886:I5962"),A25,INDIRECT("Report!J5886:J5962")) -> 144000 | G25: =SUMIF(INDIRECT("Report!I5963:I6041"),A25,INDIRECT("Report!J5963:J6041")) -> 800780 | H25: =SUMIF(INDIRECT("Report!I6042:I6109"),A25,INDIRECT("Report!J6042:J6109")) -> 601940 | I25: =SUMIF(INDIRECT("Report!I6110:I6174"),A25,INDIRECT("Report!J6110:J6174")) -> 695940 | J25: =SUMIF(INDIRECT("Report!I6175:I6250"),A25,INDIRECT("Report!J6175:J6250")) -> 231940 | K25: =SUMIF(INDIRECT("Report!I6251:I6319"),A25,INDIRECT("Report!J6251:J6319")) -> 1083580 | L25: =SUMIF(INDIRECT("Report!I6321:I6421"),A25,INDIRECT("Report!J6321:J6421")) -> 2223060 | M25: =SUMIF(INDIRECT("Report!I6422:I6510"),A25,INDIRECT("Report!J6422:J6510")) -> 668940 | N25: =SUM(B25:M25) -> 10129540 | O25: =N25/$N$41 -> 0.019461995 | P25: =N25/N4 -> 0.25266369
